Workbook

Sheet US
A1: TIMELINE | B1: 2000-2030
A2: COUNTRY | B2: USA
A5: Notation | B5: Parameter Description | C5: Unit of Measure | D5: Max_Value | E5: Min_Value | F5: Distribution | G5: Source/Justification | H5: 36526 | I5: 36557 | J5: 36586 | K5: 36617 | L5: 36647 | M5: 36678 | N5: 36708 | O5: 36739 | P5: 36770 | Q5: 36800 | R5: 36831 | S5: 36861 | T5: 36892 | U5: 36923 | V5: 36951 | W5: 36982 | X5: 37012 | Y5: 37043 | Z5: 37073 | AA5: 37104 | AB5: 37135 | AC5: 37165 | AD5: 37196 | AE5: 37226 | AF5: 37257 | AG5: 37288 | AH5: 37316 | AI5: 37347 | AJ5: 37377 | AK5: 37408 | AL5: 37438 | AM5: 37469 | AN5: 37500 | AO5: 37530 | AP5: 37561 | AQ5: 37591 | AR5: 37622 | AS5: 37653 | AT5: 37681 | AU5: 37712 | AV5: 37742 | AW5: 37773 | AX5: 37803 | AY5: 37834 | AZ5: 37865 | BA5: 37895 | BB5: 37926 | BC5: 37956 | BD5: 37987 | BE5: 38018 | BF5: 38047 | BG5: 38078 | BH5: 38108 | BI5: 38139 | BJ5: 38169 | BK5: 38200 | BL5: 38231 | BM5: 38261 | BN5: 38292 | BO5: 38322 | BP5: 38353 | BQ5: 38384 | BR5: 38412 | BS5: 38443 | BT5: 38473 | BU5: 38504 | BV5: 38534 | BW5: 38565 | BX5: 38596 | BY5: 38626 | BZ5: 38657 | CA5: 38687 | CB5: 38718 | CC5: 38749 | CD5: 38777 | CE5: 38808 | CF5: 38838 | CG5: 38869 | CH5: 38899 | CI5: 38930 | CJ5: 38961 | CK5: 38991 | CL5: 39022 | CM5: 39052 | CN5: 39083 | CO5: 39114 | CP5: 39142 | CQ5: 39173 | CR5: 39203 | CS5: 39234 | CT5: 39264 | CU5: 39295 | CV5: 39326 | CW5: 39356 | CX5: 39387 | CY5: 39417 | CZ5: 39448 | DA5: 39479 | DB5: 39508 | DC5: 39539 | DD5: 39569 | DE5: 39600 | DF5: 39630 | DG5: 39661 | DH5: 39692 | DI5: 39722 | DJ5: 39753 | DK5: 39783 | DL5: 39814 | DM5: 39845 | DN5: 39873 | DO5: 39904 | DP5: 39934 | DQ5: 39965 | DR5: 39995 | DS5: 40026 | DT5: 40057 | DU5: 40087 | DV5: 40118 | DW5: 40148 | DX5: 40179 | DY5: 40210 | DZ5: 40238 | EA5: 40269 | EB5: 40299 | EC5: 40330 | ED5: 40360 | EE5: 40391 | EF5: 40422 | EG5: 40452 | EH5: 40483 | EI5: 40513 | EJ5: 40544 | EK5: 40575 | EL5: 40603 | EM5: 40634 | EN5: 40664 | EO5: 40695 | EP5: 40725 | EQ5: 40756 | ER5: 40787 | ES5: 40817 | ET5: 40848 | EU5: 40878 | EV5: 40909 | EW5: 40940 | EX5: 40969 | EY5: 41000 | EZ5: 41030 | FA5: 41061 | FB5: 41091 | FC5: 41122 | FD5: 41153 | FE5: 41183 | FF5: 41214 | FG5: 41244 | FH5: 41275 | FI5: 41306 | FJ5: 41334 | FK5: 41365 | FL5: 41395 | FM5: 41426 | FN5: 41456 | FO5: 41487 | FP5: 41518 | FQ5: 41548 | FR5: 41579 | FS5: 41609 | FT5: 41640 | FU5: 41671 | FV5: 41699 | FW5: 41730 | FX5: 41760 | FY5: 41791 | FZ5: 41821 | GA5: 41852 | GB5: 41883 | GC5: 41913 | GD5: 41944 | GE5: 41974 | GF5: 42005 | GG5: 42036 | GH5: 42064 | GI5: 42095 | GJ5: 42125 | GK5: 42156 | GL5: 42186 | GM5: 42217 | GN5: 42248 | GO5: 42278 | GP5: 42309 | GQ5: 42339 | GR5: 42370 | GS5: 42401 | GT5: 42430 | GU5: 42461 | GV5: 42491 | GW5: 42522 | GX5: 42552 | GY5: 42583 | GZ5: 42614 | HA5: 42644 | HB5: 42675 | HC5: 42705 | HD5: 42736 | HE5: 42767 | HF5: 42795 | HG5: 42826 | HH5: 42856 | HI5: 42887 | HJ5: 42917 | HK5: 42948 | HL5: 42979 | HM5: 43009 | HN5: 43040 | HO5: 43070 | HP5: 43101 | HQ5: 43132 | HR5: 43160 | HS5: 43191 | HT5: 43221 | HU5: 43252 | HV5: 43282 | HW5: 43313 | HX5: 43344 | HY5: 43374 | HZ5: 43405 | IA5: 43435 | IB5: 43466 | IC5: 43497 | ID5: 43525 | IE5: 43556 | IF5: 43586 | IG5: 43617 | IH5: 43647 | II5: 43678 | IJ5: 43709 | IK5: 43739 | IL5: 43770 | IM5: 43800 | IN5: 43831 | IO5: 43862 | IP5: 43891 | IQ5: 43922 | IR5: 43952 | IS5: 43983 | IT5: 44013 | IU5: 44044 | IV5: 44075 | IW5: 44105 | IX5: 44136 | IY5: 44166 | IZ5: 44197 | JA5: 44228 | JB5: 44256 | JC5: 44287 | JD5: 44317 | JE5: 44348 | JF5: 44378 | JG5: 44409 | JH5: 44440 | JI5: 44470 | JJ5: 44501 | JK5: 44531 | JL5: 44562 | JM5: 44593 | JN5: 44621 | JO5: 44652 | JP5: 44682 | JQ5: 44713 | JR5: 44743 | JS5: 44774 | JT5: 44805 | JU5: 44835 | JV5: 44866 | JW5: 44896 | JX5: 44927 | JY5: 44958 | JZ5: 44986 | KA5: 45017 | KB5: 45047 | KC5: 45078 | KD5: 45108 | KE5: 45139 | KF5: 45170 | KG5: 45200 | KH5: 45231 | KI5: 45261 | KJ5: 45292 | KK5: 45323 | KL5: 45352 | KM5: 45383 | KN5: 45413 | KO5: 45444 | KP5: 45474 | KQ5: 45505 | KR5: 45536 | KS5: 45566 | KT5: 45597
A6: C_m (ICE) | B6: ICE unit production costs | C6: Dollars / car | D6: 50000 | E6: 5000 | F6: NK | G6: In Grieco et al. (2024) we see that prices (of non-luxury cars) range from 15k to 50k from 1980 to 2020, while mark-ups range from 10 to 50%. This range of costs is consistent with that observation, allwoing for a 10% deviation due to further innovation.
A7: C_m (EV) | B7: EV unit production costs | C7: Dollars / car | D7: 50000 | E7: 5000 | F7: NK | G7: No reason to assume it is different for Evs.
A8: C_m (RPT) | B8: Monthly maintainance cost of rural public transport (rural areas within a district) | C8: Dollars / month | D8: =10^5 -> 100000 | E8: =10^6 -> 1000000 | F8: We could use multiple cities and rural circles and initialise to the case of the US; then make costs proportional to area population. | G8: Federal Support of Public Transportation Operating Expenses and https://www.apta.com/research-technical-resources/transit-statistics/public-transportation-fact-book/
A9: C_m (UPT) | B9: Monthly maintainance cost of urban public transport (of a city) | C9: Dollars / month | D9: =10^6 -> 1000000 | E9: =8*10^8 -> 800000000 | F9: We could use multiple cities and rural circles and initialise to the case of the US; then make costs proportional to area population. | G9: Federal Support of Public Transportation Operating Expenses and https://www.apta.com/research-technical-resources/transit-statistics/public-transportation-fact-book/
A10: c_m (gasoline) | B10: Gasoline cost per Kilowatt Hour | C10: $ / KwH | F10: Single value per fuel type | G10: https://www.eia.gov/petroleum/gasdiesel/ | H10: {=$B$54*INDEX('Gasoline and electricity'!$H$1:$I$413,MATCH(US!H$5,'Gasoline and electricity'!$I$1:$I$413,0),1)} -> 0.037946588 | I10: {=$B$54*INDEX('Gasoline and electricity'!$H$1:$I$413,MATCH(US!I$5,'Gasoline and electricity'!$I$1:$I$413,0),1)} -> 0.040667656 | J10: {=$B$54*INDEX('Gasoline and electricity'!$H$1:$I$413,MATCH(US!J$5,'Gasoline and electricity'!$I$1:$I$413,0),1)} -> 0.044458457 | K10: {=$B$54*INDEX('Gasoline and electricity'!$H$1:$I$413,MATCH(US!K$5,'Gasoline and electricity'!$I$1:$I$413,0),1)} -> 0.042626113 | L10: {=$B$54*INDEX('Gasoline and electricity'!$H$1:$I$413,MATCH(US!L$5,'Gasoline and electricity'!$I$1:$I$413,0),1)} -> 0.043216617 | M10: {=$B$54*INDEX('Gasoline and electricity'!$H$1:$I$413,MATCH(US!M$5,'Gasoline and electricity'!$I$1:$I$413,0),1)} -> 0.04782641 | N10: {=$B$54*INDEX('Gasoline and electricity'!$H$1:$I$413,MATCH(US!N$5,'Gasoline and electricity'!$I$1:$I$413,0),1)} -> 0.045364985 | O10: {=$B$54*INDEX('Gasoline and electricity'!$H$1:$I$413,MATCH(US!O$5,'Gasoline and electricity'!$I$1:$I$413,0),1)} -> 0.042707715 | ... KT10: {=$B$54*INDEX('Gasoline and electricity'!$H$1:$I$413,MATCH(US!KT$5,'Gasoline and electricity'!$I$1:$I$413,0),1)} -> 0.087903066
A11: c_m (electricity) | B11: Electricity cost (retail) per Kilowatt Hour | C11: $ / KwH | F11: Single value per fuel type | G11: https://fred.stlouisfed.org/series/APU000072610 | H11: {=INDEX('Gasoline and electricity'!$K$1:$L$553,MATCH(US!H$5,'Gasoline and electricity'!$K$1:$K$553,0),2)} -> 0.084 | I11: {=INDEX('Gasoline and electricity'!$K$1:$L$553,MATCH(US!I$5,'Gasoline and electricity'!$K$1:$K$553,0),2)} -> 0.085 | J11: {=INDEX('Gasoline and electricity'!$K$1:$L$553,MATCH(US!J$5,'Gasoline and electricity'!$K$1:$K$553,0),2)} -> 0.085 | K11: {=INDEX('Gasoline and electricity'!$K$1:$L$553,MATCH(US!K$5,'Gasoline and electricity'!$K$1:$K$553,0),2)} -> 0.085 | L11: {=INDEX('Gasoline and electricity'!$K$1:$L$553,MATCH(US!L$5,'Gasoline and electricity'!$K$1:$K$553,0),2)} -> 0.085 | M11: {=INDEX('Gasoline and electricity'!$K$1:$L$553,MATCH(US!M$5,'Gasoline and electricity'!$K$1:$K$553,0),2)} -> 0.09 | N11: {=INDEX('Gasoline and electricity'!$K$1:$L$553,MATCH(US!N$5,'Gasoline and electricity'!$K$1:$K$553,0),2)} -> 0.091 | O11: {=INDEX('Gasoline and electricity'!$K$1:$L$553,MATCH(US!O$5,'Gasoline and electricity'!$K$1:$K$553,0),2)} -> 0.091 | ... KT11: {=INDEX('Gasoline and electricity'!$K$1:$L$553,MATCH(US!KT$5,'Gasoline and electricity'!$K$1:$K$553,0),2)} -> #N/A
A12: d^-_i | B12: Minimum distance requirement | C12: Miles / month | D12: 200 | E12: 0 | F12: Matching the income sensitvity distribution (https://www.urban.org/features/unequal-commute) -> Should give an average within the range (150-175) | G12: The 2017 National Household Travel Survey reports an average of 175 to 150 vehicle miles traveled weekly for work and shopping; it also reports inequality on the work/residence mismatch, so we account for it by replicating the distribution
A13: d^G_z (urban) | B13: Travelled distance of urban public transportation | C13: Miles / month | D13: 1500 | E13: 830 | F13: We could use multiple cities and rural circles and initialise to the case of the US; then make costs proportional to area population. | G13: https://www.transit.dot.gov/ntd/data-product/monthly-module-raw-data-release
A14: d^G_z (rural) | B14: Travelled distance of rural public transportation | C14: Miles / month | D14: 40000 | E14: =10^6 -> 1000000 | F14: We could use multiple cities and rural circles and initialise to the case of the US; then make costs proportional to area population. | G14: https://www.transit.dot.gov/ntd/data-product/monthly-module-raw-data-release
A15: E_m (EV) | B15: Technology production emissions (EV) | C15: Kilograms of CO2 / car | D15: =(5.4+1.2+1.8)*1000 -> 8400 | E15: =(5.4+1.2+2.8)*1000 -> 9400 | F15: Single value for the entire NK, these are just scenarios of GHG minerals | G15: https://www.iea.org/data-and-statistics/charts/comparative-life-cycle-greenhouse-gas-emissions-of-a-mid-size-bev-and-ice-vehicle
A16: E_m (ICE) | B16: Technology production emissions (ICE) | C16: Kilograms of CO2 / car | D16: 6000 | E16: 6000 | F16: NK | G16: https://www.iea.org/data-and-statistics/charts/comparative-life-cycle-greenhouse-gas-emissions-of-a-mid-size-bev-and-ice-vehicle
A17: e_m (gasoline) | B17: Fuel emissions per KWh | C17: Kilograms of CO2 / KWh | D17: =8.887*B54 -> 0.2637092 | E17: =D17 -> 0.2637092 | F17: Single value per fuel type | G17: https://www.epa.gov/greenvehicles/greenhouse-gas-emissions-typical-passenger-vehicle
A18: e_m (electricity) | B18: Electricity emsissions per KWh | C18: Kilograms of CO2 / KWh | D18: ='Electricity emissions'!A36*'Electricity emissions'!B38 -> 0.37335188 | E18: =D18 -> 0.37335188 | F18: Single value per fuel type | G18: https://www.epa.gov/egrid/summary-data
A19: O_i (rural) | B19: Individual place of residence | C19: Binary (0=rural, 1=urban) | D19: 0.2 | E19: 0.2 | F19: Single value per origin type | G19: https://www.census.gov/newsroom/press-releases/2022/urban-rural-populations.html
A20: O_i (urban) | B20: Individual place of residence | C20: Binary (0=rural, 1=urban) | D20: 0.8 | E20: 0.8 | F20: Single value per origin type | G20: https://www.census.gov/newsroom/press-releases/2022/urban-rural-populations.html
A21: P^G_z | B21: Monthly ticket fare of public transportation z (urban) | C21: Dolars / month | D21: 40 | E21: 70 | F21: APTA Annual Public Transportation Fact Book
A22: P^G_z | B22: Monthly ticket fare of public transportation z (rural) | C22: Dolars / month | E22: 20 | F22: APTA Annual Public Transportation Fact Book
A23: Q_m | B23: Vehicle quality | C23: Utility / kilometre | D23: (if beta is 0 then you dont care about price, price is all relative) CALIBRATE S.T. SOMEONE WITH BETA=0 and GAMMA=0 would be willing to pay 50 to 100k for a new car | G23: This has to be calibrated in such way that a person with no carbon or price sensitivity should be willing to pay around 80-50k for a new car (average price of a high-range non-luxury car)
A24: r | B24: Discount rate | C24: Percent | D24: 0 | E24: 0.05 | F24: We can just follow the trend of the 1-year Treasury bond | G24: https://fred.stlouisfed.org/series/DGS1/#0 | H24: What is the idea behind this discount rate?
A25: T^+ | B25: Time limit for unsold used cars | C25: Months | D25: 1 | E25: 2 | F25: Just pick-up a value | G25: NADA (National Automobile Dealers Association) reports average used car inventory holding time of 52 days https://www.nada.org/media/4694/download?inline
A26: α | B26: Utility scale of returns to distance travelled | C26: Scale | D26: INDIRECT CALIBRATION | F26: Global param
A27: β_i | B27: Individual price sensitivity | C27: Utility / Monetary units | D27: INDIRECT CALIBRATION | F27: Try to match income distribution for this distribution
A28: β_s | B28: Segment price sensitivity | C28: Utility / Monetary units | D28: In-segment average
A29: β̂ | B29: High income threshold | C29: Utility / Monetary units | D29: Set at the equivalent of what is considered the high-income tier
A30: γ_i | B30: Individual environmental awareness | C30: Utility / Kilograms of CO2 | D30: INDIRECT CALIBRATION
A31: γ_s | B31: Segment environmental awareness | C31: Utility / Kilograms of CO2 | D31: In-segment average
A32: γ̂ | B32: Environmental awareness threshold | C32: Utility / Kilograms of CO2 | D32: Set at average
A33: δ_z | B33: Depreciation rate | C33: Percent | D33: 0.01 | E33: 0.03 | F33: CALIBRATE TO MATCH VEHICLE AGE
A34: η | B34: Time sensitivity | C34: Utility / Hours | D34: INDIRECT CALIBRATION
A35: ι | B35: Probability of successful innovation | C35: Percent | D35: 45627
A36: κ | B36: Intensity of competition | C36: Scale | D36: INDIRECT CALIBRATION, or maybe just get from the discrete choice models out there
A37: λ | B37: Rate of exploitation in firm search | C37: Scale | D37: Copy from papers on managerial sciences about optimal rates of exploration/exploitation
A38: μ | B38: Used car dealer mark-up (This is the discount on the original price not the markup) | C38: Percent | D38: 0.3
A39: ν_i | B39: Average time spent travelling | C39: Hours / Kilometre | D39: ???
A40: ρ_{f,z} | B40: Attribute f correlation w.r.t attribute f=0 | C40: [-1,1] | D40: [1,.5,0]
A41: χ_i | B41: Adoption threshold | C41: Percent | D41: Get from that nice paper
A42: ω_m | B42: Fuel efficiency (EV) (should be in km) | C42: km / KWh | D42: 4 | E42: 7 | F42: https://www.fueleconomy.gov/feg/PowerSearch.do?action=Cars&vtype=Electric&srchtyp=evSelect&rowLimit=50&sortBy=Comb&year1=2006&year2=2011&mclass=Small%20Cars,Coupes,Sports/Sporty%20Cars,Hatchbacks,Family%20Sedans,Upscale%20Sedans,Luxury%20Sedans,Sport%20Utility%20Vehicles&range=&drive=
A43: ω_m | B43: Fuel efficiency (ICE) (should be in km) | C43: km/ KWh | D43: 0.5 | E43: 2 | F43: https://afdc.energy.gov/data/10305 (THIS IS MPG DATA BUT CAN BE CONVERTED TO Km/kWhr, assume that EVs dont contribute to fleet significantly)
B44: inflation metric | C44: $
B45: density of connections urban
B46: density of connections urban
B47: density of connections between urban and rural
B48: population ratio urban versus rural
A50: EV Innovation/Production | B50: =12*5 -> 60 | C50: (Starting after)
A53: KwH/Galon | B53: 33.7 | C53: MPGE Metric
A54: Galon/KwH | B54: =1/B53 -> 0.02967359
A56: DAN : Comments and data that dont directly fit in but i thought might be useful for direct or indirect calibration
B57: i found this online(kg/mhw): 0.263
B58: https://www.volker-quaschning.de/datserv/CO2-spez/index_e.php
A59: miles/gallon(need to multply by (km/miles = 0.625)*(gallon/kWhr = 0.02967)) = 0.0185ish | B59: https://www.bts.gov/content/average-fuel-efficiency-us-light-duty-vehicles | C59: CAFE Data, its a policy. This can be used i think for all cars? We can match this data roughly. its not just the ICE car, its a harmonic mean of the fleet of cars produced i think.
A60: paper sets out scope for improvement in ICE cars efficiency | B60: https://www.sciencedirect.com/science/article/pii/S2666691X20300063
A62: Veza et al 2023 | B62: EVs possess the lowest maintenance costs among the evaluated vehicles at only 0.00419 USD/km. This is for indonesia and a small sample size but if we wanted to we could add this in.
A63: Grey literature but may be useful | B63: TCO is dominated by initial cost of vehicle | C63: https://nickelinstitute.org/media/8d993d0fd3dfd5b/tco-north-american-automotive-final.pdf
A64: Greene et al 2014 | B64: LAVE-trans model of transition to EV for california, uses 16% innovators and 84 percent majority, use the 16% as the value of what percentage of society has 0 threshold
A65: California EV mandate policy | B65: 2035 all sales are EVs | C65: https://ww2.arb.ca.gov/news/california-moves-accelerate-100-new-zero-emission-vehicle-sales-2035
B66: A lot of state level data, may be useful but from 2017 | C66: https://theicct.org/wp-content/uploads/2021/06/Transition_EV_US_Cities_20180724.pdf
B67: Public transport data, more from the energy perspective, but data on users number | C67: https://www.energy.ca.gov/data-reports/energy-almanac/transportation-energy/public-transit-california
B68: public transort usage by californians at about 5%, but varies significatly depending on where it is. 30+% in san fran but 9% in LA | C68: https://www.homearea.com/rankings/place-in-ca/percent_using_public_transportation/#:~:text=The%20California%20percent%20using%20public,fallen%201.2%25%20from%205.1%25.
B69: comparing the emissions per kilometer of different cars(first eu second australia) | C69: https://www.transportenvironment.org/articles/how-clean-are-electric-cars | D69: https://electricvehiclecouncil.com.au/lifecycle-emissions-calculator/
A70: Zahabi et al 2014 | B70: Hybrids 20-28% more efficient in fuel economy than gasoline cars | C70: https://www.sciencedirect.com/science/article/pii/S1361920914000923
A71: Hao et al 2020 | B71: 15.2 KWh/100km for EV taxi
B72: california ICE data emissions intensity and BEV popultation!! AND THE ELECTRICITY INTENSITY EMISSIONS!! | C72: https://ww2.arb.ca.gov/sites/default/files/2024-09/nc-2000_2022_ghg_inventory_trends.pdf
B73: gasoline price california | C73: https://www.eia.gov/dnav/pet/hist/LeafHandler.ashx?n=PET&s=EMM_EPM0_PTE_SCA_DPG&f=M
B74: electricity price california | C74: https://fred.stlouisfed.org/series/APUS49B72610#0
B75: california income distribution disribution | C75: https://data.census.gov/table/ACSST5Y2022.S1901?q=california%20income&moe=false
B76: CPI california | C76: https://dof.ca.gov/forecasting/economics/economic-indicators/inflation/
B77: Carbon price from cap and trade california. Not sure if this covers production emissions. It definitely covers electricity and fuel | C77: https://ww2.arb.ca.gov/our-work/programs/cap-and-trade-program/program-data/cap-and-trade-program-data-dashboard
B78: emissions intensity california monthly | C78: https://ember-energy.org/data/us-electricity-data-explorer/
B79: EV sales count | C79: https://www.energy.ca.gov/files/zev-and-infrastructure-stats-data
B80: Ev range evolution | C80: https://www.iea.org/data-and-statistics/charts/evolution-of-average-range-of-electric-vehicles-by-powertrain-2010-2021
B81: Data on commuite times in THE BAY AREA, use to parameterise nu! or justify the relations | C81: https://vitalsigns.mtc.ca.gov/indicators/commute-time | J81: ERROR(Cali-CIty) | L81: Average error | M81: =AVERAGE(J98:J383) -> 3.3314685
B82: Data on commute times in LA, but no speeds | C82: https://www.ppic.org/wp-content/uploads/content/pubs/cacounts/CC_206EBCC.pdf
B83: Subsidy/tax rebate for EVS | C83: https://fueleconomy.gov/feg/tax2023.shtml
A84: 7500 dollars | B84: https://www.irs.gov/irb/2009-48_IRB | C84: https://cleanvehiclerebate.org/en/rebate-statistics | E84: https://www.fueleconomy.gov/feg/tax2023.shtml | F84: https://www.ladwp.com/residential-services/programs-and-rebates-residential/electric-vehicles/used-electric-vehicle-rebate-program
B85: Urban versus rural california | C85: https://www.ppic.org/publication/rural-california/ | D85: 286 | E85: https://www.fueleconomy.gov/feg/taxused.shtml | F85: 45566 | G85: 389 | H85: =G85/10 -> 38.9 | I85: =AVERAGE(H85,E85) -> 38.9
A86: beta use income inequality | B86: quintile data from 2019-2020 | C86: https://www.bls.gov/cex/tables/geographic/mean/cu-state-ca-income-quintiles-before-taxes-2-year-average-2020.htm
A88: https://www.eia.gov/opendata/browser/electricity/retail-sales?frequency=monthly&data=price;&facets=stateid;sectorid;&stateid=CA;&sectorid=RES;&start=2001-01&end=2024-09&sortColumn=period;&sortDirection=desc;
A90: Future calibrations:
A91: Emissiosn intensity of california | B91: https://iopscience.iop.org/article/10.1088/1748-9326/abb7ad/data | C91: Gubert 2020
A98: 45536 | B98: 31.64 | C98: 45536 | D98: 282 | E98: =D98/10 -> 28.2 | F98: 45536 | G98: 383 | H98: =G98/10 -> 38.3 | I98: =AVERAGE(H98,E98) -> 33.25 | J98: =(I98-B98) -> 1.61
A99: 45505 | B99: 31.05 | C99: 45505 | D99: 282 | E99: =D99/10 -> 28.2 | F99: 45505 | G99: 381 | H99: =G99/10 -> 38.1 | I99: =AVERAGE(H99,E99) -> 33.15 | J99: =(I99-B99) -> 2.1
A100: 45474 | B100: 32.55 | C100: 45474 | D100: 282 | E100: =D100/10 -> 28.2 | F100: 45474 | G100: 381 | H100: =G100/10 -> 38.1 | I100: =AVERAGE(H100,E100) -> 33.15 | J100: =(I100-B100) -> 0.6
A101: 45444 | B101: 32.99 | C101: 45444 | D101: 277 | E101: =D101/10 -> 27.7 | F101: 45444 | G101: 419 | H101: =G101/10 -> 41.9 | I101: =AVERAGE(H101,E101) -> 34.8 | J101: =(I101-B101) -> 1.81
A102: 45413 | B102: 34.3 | C102: 45413 | D102: 286 | E102: =D102/10 -> 28.6 | F102: 45413 | G102: 413 | H102: =G102/10 -> 41.3 | I102: =AVERAGE(H102,E102) -> 34.95 | J102: =(I102-B102) -> 0.65
A103: 45383 | B103: 34.26 | C103: 45383 | D103: 287 | E103: =D103/10 -> 28.7 | F103: 45383 | G103: 413 | H103: =G103/10 -> 41.3 | I103: =AVERAGE(H103,E103) -> 35 | J103: =(I103-B103) -> 0.74
A104: 45352 | B104: 32.48 | C104: 45352 | D104: 291 | E104: =D104/10 -> 29.1 | F104: 45352 | G104: 413 | H104: =G104/10 -> 41.3 | I104: =AVERAGE(H104,E104) -> 35.2 | J104: =(I104-B104) -> 2.72
A105: 45323 | B105: 31.24 | C105: 45323 | D105: 285 | E105: =D105/10 -> 28.5 | F105: 45323 | G105: 412 | H105: =G105/10 -> 41.2 | I105: =AVERAGE(H105,E105) -> 34.85 | J105: =(I105-B105) -> 3.61
A106: 45292 | B106: 29.49 | C106: 45292 | D106: 285 | E106: =D106/10 -> 28.5 | F106: 45292 | G106: 412 | H106: =G106/10 -> 41.2 | I106: =AVERAGE(H106,E106) -> 34.85 | J106: =(I106-B106) -> 5.36
A107: 45261 | B107: 29.12 | C107: 45261 | D107: 288 | E107: =D107/10 -> 28.8 | F107: 45261 | G107: 350 | H107: =G107/10 -> 35 | I107: =AVERAGE(H107,E107) -> 31.9 | J107: =(I107-B107) -> 2.78
A108: 45231 | B108: 29.54 | C108: 45231 | D108: 287 | E108: =D108/10 -> 28.7 | F108: 45231 | G108: 350 | H108: =G108/10 -> 35 | I108: =AVERAGE(H108,E108) -> 31.85 | J108: =(I108-B108) -> 2.31
A109: 45200 | B109: 31.78 | C109: 45200 | D109: 287 | E109: =D109/10 -> 28.7 | F109: 45200 | G109: 350 | H109: =G109/10 -> 35 | I109: =AVERAGE(H109,E109) -> 31.85 | J109: =(I109-B109) -> 0.07
... A383: 36892 | B383: 10.89 | C383: 36861 | D383: 116 | E383: =D383/10 -> 11.6 | F383: 36861 | G383: 115 | H383: =G383/10 -> 11.5 | I383: =AVERAGE(H383,E383) -> 11.55 | J383: =(I383-B383) -> 0.66
C384: 36831 | D384: 116 | E384: =D384/10 -> 11.6 | F384: 36831 | G384: 115 | H384: =G384/10 -> 11.5 | I384: =AVERAGE(H384,E384) -> 11.55
C385: 36800 | D385: 116 | E385: =D385/10 -> 11.6 | F385: 36800 | G385: 115 | H385: =G385/10 -> 11.5 | I385: =AVERAGE(H385,E385) -> 11.55
C386: 36770 | D386: 116 | E386: =D386/10 -> 11.6 | F386: 36770 | G386: 115 | H386: =G386/10 -> 11.5 | I386: =AVERAGE(H386,E386) -> 11.55
C387: 36739 | D387: 116 | E387: =D387/10 -> 11.6 | F387: 36739 | G387: 115 | H387: =G387/10 -> 11.5 | I387: =AVERAGE(H387,E387) -> 11.55
C388: 36708 | D388: 116 | E388: =D388/10 -> 11.6 | F388: 36708 | G388: 115 | H388: =G388/10 -> 11.5 | I388: =AVERAGE(H388,E388) -> 11.55
...

Sheet outputs
A1: Notation | B1: Parameter Description | C1: Unit of Measure | D1: Max_Value | E1: Min_Value | F1: Distribution | G1: Source/Justification
A2: Total emissions
A3: Ev uptake
A4: Km/Mile | B4: 1.609
A7: Output variable | B7: 2000 | C7: 2001 | D7: 2002 | E7: 2003 | F7: 2004 | G7: 2005 | H7: 2006 | I7: 2007 | J7: 2008 | K7: 2009 | L7: 2010 | M7: 2011 | N7: 2012 | O7: 2013 | P7: 2014 | Q7: 2015 | R7: 2016 | S7: 2017 | T7: 2018 | U7: 2019 | V7: 2020 | W7: 2021 | X7: 2022 | Y7: 2023 | Z7: 2024 | AA7: Source/Justificaiton
A8: Transit Ridership (I don't know the measure) | B8: 1,311,824,696.00 | C8: 1,346,517,005.00 | D8: 1,377,987,092.00 | E8: 1,327,293,349.00 | F8: 1,294,728,947.00 | G8: 1,357,675,691.00 | H8: 1,406,095,938.00 | I8: 1,441,805,116.00 | J8: 1,459,165,411.00 | K8: 1,474,373,826.00 | L8: 1,403,504,000.00 | M8: 1,386,899,775.00 | N8: 1,418,917,723.00 | O8: 1,441,811,356.00 | P8: 1,458,600,707.00 | Q8: 1,435,297,360.00 | R8: 1,398,152,646.00 | S8: 1,324,436,440.00 | T8: 1,293,074,046.00 | U8: 1,267,399,653.00 | V8: 1,000,292,915.00 | W8: 489,444,294.00 | X8: 705,670,207.00 | AA8: https://www.bts.gov/browse-statistical-products-and-data/state-transportation-statistics/state-highway-travel
A9: Highway use of gasoline (thousand gallons) | B9: 14,378,254.00 | C9: 14,691,753.00 | D9: 15,385,840.00 | E9: 15,358,354.00 | F9: 15,579,476.00 | G9: 15,614,464.00 | H9: 15,509,940.00 | I9: 15,402,164.00 | J9: 14,787,997.00 | K9: 14,575,049.00 | L9: 14,555,037.00 | M9: 14,276,055.00 | N9: 14,221,198.00 | O9: 14,201,939.00 | P9: 14,660,111.00 | Q9: 14,188,342.00 | R9: 14,540,213.00 | S9: 14,613,569.00 | T9: 14,536,101.00 | U9: 14,432,583.00 | V9: 11,487,227.00 | W9: 12,812,146.00 | X9: 12,516,732.00 | AA9: https://www.bts.gov/browse-statistical-products-and-data/state-transportation-statistics/state-highway-travel
A10: Highway vehicle-miles traveled (millions) | B10: 306,649.00 | C10: 310,575.00 | D10: 320,942.00 | E10: 323,592.00 | F10: 328,917.00 | G10: 329,267.00 | H10: 327,478.00 | I10: 328,312.00 | J10: 327,286.00 | K10: 324,486.00 | L10: 322,849.40 | M10: 320,783.91 | N10: 326,271.65 | O10: 329,534.13 | P10: 332,857.20 | Q10: 335,538.56 | R10: 340,115.00 | S10: 343,862.11 | T10: 348,795.71 | U10: 340,836.25 | V10: 299,811.68 | W10: 310,822.73 | X10: 315,243.57 | AA10: https://www.bts.gov/browse-statistical-products-and-data/state-transportation-statistics/state-highway-travel
A11: Vehicles | B11: 27,697,920.00 | C11: 28,780,060.00 | D11: 29,618,610.00 | E11: 30,248,070.00 | F11: 31,399,600.00 | G11: 32,487,480.00 | H11: 33,182,060.00 | I11: 33,935,390.00 | J11: 33,483,060.00 | K11: 34,433,210.00 | L11: 31,014,130.00 | M11: 29,176,700.00 | N11: 27,702,150.00 | O11: 28,074,980.00 | P11: 28,686,650.00 | Q11: 29,424,012.00 | R11: 30,221,033.00 | S11: 30,795,141.00 | T11: 31,022,328.00 | U11: 31,247,270.05 | V11: 30,398,249.00 | W11: 31,349,073.00 | X11: 31,119,113.00 | AA11: https://www.bts.gov/browse-statistical-products-and-data/state-transportation-statistics/state-highway-travel
A12: Licensed drivers | B12: 21,243,939.00 | C12: 21,623,793.00 | D12: 22,394,800.00 | E12: 22,657,288.00 | F12: 22,761,088.00 | G12: 22,895,965.00 | H12: 23,021,279.00 | I12: 23,467,452.00 | J12: 23,697,667.00 | K12: 23,680,643.00 | L12: 23,753,441.00 | M12: 23,856,600.00 | N12: 24,200,997.00 | O12: 24,390,236.00 | P12: 24,813,346.00 | Q12: 25,532,920.00 | R12: 26,199,436.00 | S12: 26,777,132.00 | T12: 27,039,400.00 | U12: 27,213,650.00 | V12: 27,005,302.00 | W12: 27,112,595.00 | X12: 27,632,103.00 | Z12: 1586413 | AA12: https://www.bts.gov/browse-statistical-products-and-data/state-transportation-statistics/state-highway-travel
A13: Vehicle-to-driver ratio | B13: =B11/B12 -> 1.3038034 | C13: =C11/C12 -> 1.3309441 | D13: =D11/D12 -> 1.3225664 | E13: =E11/E12 -> 1.3350261 | F13: =F11/F12 -> 1.3795298 | G13: =G11/G12 -> 1.4189173 | H13: =H11/H12 -> 1.4413647 | I13: =I11/I12 -> 1.446062 | ... X13: =X11/X12 -> 1.1261942 | Z13: =Z12/X12 -> 0.057411953
A14: Ridership per vehicle | B14: =B8/B$11 -> 47.361849 | C14: =C8/C$11 -> 46.786456 | D14: =D8/D$11 -> 46.524367 | E14: =E8/E$11 -> 43.880266 | F14: =F8/F$11 -> 41.233931 | G14: =G8/G$11 -> 41.790736 | H14: =H8/H$11 -> 42.375185 | I14: =I8/I$11 -> 42.48677 | ... X14: =X8/X$11 -> 22.676424 | Z14: =Z13/12 -> 0.0047843294
A15: Gasoline per vehicle (gallons) | B15: =1000*B9/B$11 -> 519.10952 | C15: =1000*C9/C$11 -> 510.48375 | D15: =1000*D9/D$11 -> 519.4653 | E15: =1000*E9/E$11 -> 507.74658 | F15: =1000*F9/F$11 -> 496.16798 | G15: =1000*G9/G$11 -> 480.6302 | H15: =1000*H9/H$11 -> 467.41944 | I15: =1000*I9/I$11 -> 453.8673 | ... X15: =1000*X9/X$11 -> 402.22008
A16: Distance per vehicle (miles) | B16: =10^6*B10/B$11 -> 11071.192 | C16: =10^6*C10/C$11 -> 10791.326 | D16: =10^6*D10/D$11 -> 10835.822 | E16: =10^6*E10/E$11 -> 10697.939 | F16: =10^6*F10/F$11 -> 10475.197 | G16: =10^6*G10/G$11 -> 10135.197 | H16: =10^6*H10/H$11 -> 9869.1281 | I16: =10^6*I10/I$11 -> 9674.6199 | ... X16: =10^6*X10/X$11 -> 10130.224
A17: Distance per vehicle (km/Month) | B17: =$B$4*B16/12 -> 1484.4624 | C17: =$B$4*C16/12 -> 1446.9369 | D17: =$B$4*D16/12 -> 1452.9032 | E17: =$B$4*E16/12 -> 1434.4153 | F17: =$B$4*F16/12 -> 1404.5493 | G17: =$B$4*G16/12 -> 1358.961 | H17: =$B$4*H16/12 -> 1323.2856 | I17: =$B$4*I16/12 -> 1297.2053 | ... X17: =$B$4*X16/12 -> 1358.2941

Sheet EV Data
A1: img href | B1: img src | C1: model | D1: current | E1: title-wrap | F1: battery | G1: price-range | H1: roofrack | I1: 3-phase | J1: plug-type2-ccs | K1: shape-sedan | L1: icons-row-1 | M1: heatpump | N1: tow-hitch | O1: towweight | P1: safety | Q1: icons-row-2 | R1: icons-row-2 2 | S1: icons-row-2 3 | T1: icons-row-2 4 | U1: tag | V1: acceleration | W1: tag 2 | X1: topspeed | Y1: tag 3 | Z1: erange_real | AA1: tag 4 | AB1: efficiency | AC1: tag 5 | AD1: fastcharge_speed_print | AE1: fastcharge_speed | AF1: country_de | AG1: country_nl | AH1: country_uk | AI1: pricefilter | AJ1: pricesort | AK1: date_from | AL1: rank | AM1: id | AN1: v2xl | AO1: icons-row-2 5 | AP1: size-c | AQ1: shape-hatchback | AR1: size-b | AT1: Efficiency | AU1: km/kWh | AV1: price-range | AW1: Top Speed | AX1: battery | AY1: Range | AZ1: Acceleration | BB1: https://ev-database.org/compare/efficiency-electric-vehicle-most-efficient#sort:path~type~order=.efficiency~number~asc|rs-price:prev~next=10000~100000|rs-range:prev~next=0~1000|rs-fastcharge:prev~next=0~1500|rs-acceleration:prev~next=2~23|rs-topspeed:prev~next=110~350|rs-battery:prev~next=10~200|rs-towweight:prev~next=0~2500|rs-eff:prev~next=100~350|rs-safety:prev~next=-1~5|paging:currentPage=8|paging:number=50
A2: https://ev-database.org/car/1991/Tesla-Model-3 | B2: https://ev-database.org/img/auto/Tesla_Model_3_2024/Tesla_Model_3_2024-01-thumb.jpg | C2: Model 3 | D2: Available to order since September 2023 | E2: kWh useable battery *| /km of range | F2: 57.5 | G2: 102 | H2: Roofbox possible | I2: 3-Phase Charging | J2: Type 2 CCS | K2: Sedan | L2: 5 | M2: Heatpump | N2: Towbar possible | O2: 1000 | P2: -1 | Q2: V2 | R2: L | S2: H | T2: G | U2: 0 - 100 | V2: 6.1 sec | W2: Top Speed | X2: 201 km/h | Y2: Range | Z2: 420 km | AA2: Efficiency | AB2: 137 Wh/km | AC2: Fastcharge | AD2: 730 km/h | AE2: 730 | AF2: 40.97 | AG2: 40.99 | AH2: £39,990 | AI2: 42649 | AJ2: 42649 | AK2: 1.69E+09 | AL2: 7170 | AM2: 1991 | AT2: 137 | AU2: 7.30 | AV2: 102 | AW2: 201 | AX2: 57.5 | AY2: 420 | AZ2: 45297
A3: https://ev-database.org/car/3034/Tesla-Model-3-Long-Range-RWD | B3: https://ev-database.org/img/auto/Tesla_Model_3_2024/Tesla_Model_3_2024-01-thumb.jpg | C3: Model 3 Long Range RWD | D3: Available to order since October 2024 | E3: kWh useable battery *| /km of range* | F3: 75 | G3: 87 | H3: Roofbox possible | I3: 3-Phase Charging | J3: Type 2 CCS | K3: Sedan | L3: 5 | M3: Heatpump | N3: Towbar possible | O3: 1000 | P3: -1 | Q3: V2 | R3: L | S3: H | T3: G | U3: 0 - 100 | V3: 5.2 sec | W3: Top Speed | X3: 201 km/h | Y3: Range* | Z3: 545 km | AA3: Efficiency* | AB3: 138 Wh/km | AC3: Fastcharge | AD3: 840 km/h | AE3: 840 | AF3: 44.99 | AG3: 45.99 | AH3: £44,990 | AI3: 47572 | AJ3: 47572 | AK3: 1.73E+09 | AL3: 3612 | AM3: 3034 | AT3: 138 | AU3: 7.25 | AV3: 87 | AW3: 201 | AX3: 75 | AY3: 545 | AZ3: 45327
A4: https://ev-database.org/car/1992/Tesla-Model-3-Long-Range-Dual-Motor | B4: https://ev-database.org/img/auto/Tesla_Model_3_2024/Tesla_Model_3_2024-01-thumb.jpg | C4: Model 3 Long Range Dual Motor | D4: Available to order since September 2023 | E4: kWh useable battery *| /km of range | F4: 75 | G4: 101 | H4: Roofbox possible | I4: 3-Phase Charging | J4: Type 2 CCS | K4: Sedan | L4: 5 | M4: Heatpump | N4: Towbar possible | O4: 1000 | P4: -1 | Q4: V2 | R4: L | S4: H | T4: G | U4: 0 - 100 | V4: 4.4 sec | W4: Top Speed | X4: 201 km/h | Y4: Range | Z4: 525 km | AA4: Efficiency | AB4: 143 Wh/km | AC4: Fastcharge | AD4: 810 km/h | AE4: 810 | AF4: 49.99 | AG4: 50.99 | AH4: £49,990 | AI4: 52822 | AJ4: 52822 | AK4: 1.69E+09 | AL4: 3902 | AM4: 1992 | AT4: 143 | AU4: 6.99 | AV4: 101 | AW4: 201 | AX4: 75 | AY4: 525 | AZ4: 45386
A5: https://ev-database.org/car/1717/Hyundai-IONIQ-6-Standard-Range-2WD | B5: https://ev-database.org/img/auto/Hyundai_IONIQ6_2022/Hyundai_IONIQ6_2022-01-thumb.jpg | C5: IONIQ 6 Standard Range 2WD | D5: Available to order since January 2023 | E5: kWh useable battery *| /km of range* | F5: 50 | G5: 134 | H5: Roofbox possible | I5: 3-Phase Charging | J5: Type 2 CCS | K5: Sedan | L5: 5 | M5: Heatpump | N5: Towbar possible | O5: 750 | P5: 5 | Q5: 5 | R5: V2 | S5: L | T5: H | U5: 0 - 100 | V5: 8.8 sec | W5: Top Speed | X5: 185 km/h | Y5: Range* | Z5: 335 km | AA5: Efficiency* | AB5: 149 Wh/km | AC5: Fastcharge | AD5: 780 km/h | AE5: 780 | AF5: 43.9 | AG5: 45.895 | AH5: N/A | AI5: 44897 | AJ5: 44897 | AK5: 1.67E+09 | AL5: 795 | AM5: 1717 | AN5: V2XL | AO5: G | AT5: 149 | AU5: 6.71 | AV5: 134 | AW5: 185 | AX5: 50 | AY5: 335 | AZ5: 45512
A6: https://ev-database.org/car/1718/Hyundai-IONIQ-6-Long-Range-2WD | B6: https://ev-database.org/img/auto/Hyundai_IONIQ6_2022/Hyundai_IONIQ6_2022-01-thumb.jpg | C6: IONIQ 6 Long Range 2WD | D6: Available to order since December 2022 | E6: kWh useable battery *| /km of range | F6: 74 | G6: 107 | H6: Roofbox possible | I6: 3-Phase Charging | J6: Type 2 CCS | K6: Sedan | L6: 5 | M6: Heatpump | N6: Towbar possible | O6: 1500 | P6: 5 | Q6: 5 | R6: V2 | S6: L | T6: H | U6: 0 - 100 | V6: 7.4 sec | W6: Top Speed | X6: 185 km/h | Y6: Range | Z6: 495 km | AA6: Efficiency | AB6: 149 Wh/km | AC6: Fastcharge | AD6: 1290 km/h | AE6: 1290 | AF6: 54 | AG6: 50.895 | AH6: £47,040 | AI6: 52997 | AJ6: 52997 | AK6: 1.67E+09 | AL6: 1006 | AM6: 1718 | AN6: V2XL | AO6: G | AT6: 149 | AU6: 6.71 | AV6: 107 | AW6: 185 | AX6: 74 | AY6: 495 | AZ6: 45389
A7: https://ev-database.org/car/3050/Citroen-e-C4-X-54-kWh | B7: https://ev-database.org/img/auto/Citroen_e-C4_X_2024/Citroen_e-C4_X_2024-01-thumb.jpg | C7: e-C4 X 54 kWh | D7: Available to order since October 2024 | E7: kWh useable battery | /km of range* | F7: 50.8 | G7: 107 | H7: Roofbox possible | I7: 3-Phase Charging | J7: Type 2 CCS | K7: Sedan | L7: 5 | M7: Heatpump | P7: 4 | Q7: 4 | R7: V2 | S7: L | T7: H | U7: 0 - 100 | V7: 10.1 sec | W7: Top Speed | X7: 150 km/h | Y7: Range* | Z7: 340 km | AA7: Efficiency* | AB7: 149 Wh/km | AC7: Fastcharge | AD7: 490 km/h | AE7: 490 | AF7: 34.8 | AG7: 38.165 | AH7: N/A | AI7: 36482 | AJ7: 36482 | AK7: 1.73E+09 | AL7: 594 | AM7: 3050 | AN7: V2XL | AO7: G | AP7: C | AT7: 149 | AU7: 6.71 | AV7: 107 | AW7: 150 | AX7: 50.8 | AY7: 340 | AZ7: 45301
A8: https://ev-database.org/car/2126/Dacia-Spring-Electric-45 | B8: https://ev-database.org/img/auto/Dacia_Spring_Electric_2024/Dacia_Spring_Electric_2024-01-thumb.jpg | C8: Spring Electric 45 | D8: Available to order since April 2024 | E8: kWh useable battery *| /km of range* | F8: 25 | G8: 107 | J8: Type 2 CCS | L8: 4 | P8: -1 | Q8: V2 | R8: L | S8: H | T8: G | U8: 0 - 100* | V8: 19.1 sec | W8: Top Speed | X8: 125 km/h | Y8: Range* | Z8: 165 km | AA8: Efficiency* | AB8: 152 Wh/km | AC8: Fastcharge | AD8: 180 km/h | AE8: 180 | AF8: 16.9 | AG8: 18.95 | AH8: £14,995 | AI8: 17698 | AJ8: 17698 | AK8: 1.71E+09 | AL8: 758 | AM8: 2126 | AQ8: Hatchback | AT8: 152 | AU8: 6.58 | AV8: 107 | AW8: 125 | AX8: 25 | AY8: 165 | AZ8: 45310
A9: https://ev-database.org/car/3048/Citroen-e-C4-54-kWh | B9: https://ev-database.org/img/auto/Citroen_e-C4_2024/Citroen_e-C4_2024-01-thumb.jpg | C9: e-C4 54 kWh | D9: Available to order since October 2024 | E9: kWh useable battery | /km of range* | F9: 50.8 | G9: 107 | H9: Roofbox possible | I9: 3-Phase Charging | J9: Type 2 CCS | L9: 5 | M9: Heatpump | P9: 4 | Q9: 4 | R9: V2 | S9: L | T9: H | U9: 0 - 100 | V9: 10.0 sec | W9: Top Speed | X9: 150 km/h | Y9: Range* | Z9: 335 km | AA9: Efficiency* | AB9: 152 Wh/km | AC9: Fastcharge | AD9: 480 km/h | AE9: 480 | AF9: 34.1 | AG9: 37.465 | AH9: N/A | AI9: 35782 | AJ9: 35782 | AK9: 1.73E+09 | AL9: 280 | AM9: 3048 | AN9: V2XL | AO9: G | AP9: C | AQ9: Hatchback | AT9: 152 | AU9: 6.58 | AV9: 107 | AW9: 150 | AX9: 50.8 | AY9: 335 | AZ9: 10
A10: https://ev-database.org/car/1942/Opel-Corsa-Electric-51-kWh | B10: https://ev-database.org/img/auto/Opel_Corsa_Electric_2023/Opel_Corsa_Electric_2023-01-thumb.jpg | C10: Corsa Electric 51 kWh | D10: Available to order since July 2023 | E10: kWh useable battery | /km of range* | F10: 48.1 | G10: 124 | H10: Roofbox possible | I10: 3-Phase Charging | J10: Type 2 CCS | L10: 5 | M10: Heatpump | P10: -1 | Q10: V2 | R10: L | S10: H | T10: G | U10: 0 - 100 | V10: 8.1 sec | W10: Top Speed | X10: 150 km/h | Y10: Range* | Z10: 315 km | AA10: Efficiency* | AB10: 153 Wh/km | AC10: Fastcharge | AD10: 490 km/h | AE10: 490 | AF10: 38.045 | AG10: 37.999 | AH10: £35,475 | AI10: 38946 | AJ10: 38946 | AK10: 1.69E+09 | AL10: 452 | AM10: 1942 | AQ10: Hatchback | AR10: B | AT10: 153 | AU10: 6.54 | AV10: 124 | AW10: 150 | AX10: 48.1 | AY10: 315 | AZ10: 45299
A11: https://ev-database.org/car/2188/Tesla-Model-3-Performance | B11: https://ev-database.org/img/auto/Tesla_Model_3_Performance_2024/Tesla_Model_3_Performance_2024-01-thumb.jpg | C11: Model 3 Performance | D11: Available to order since April 2024 | E11: kWh useable battery *| /km of range | F11: 75 | G11: 126 | H11: Roofbox possible | I11: 3-Phase Charging | J11: Type 2 CCS | K11: Sedan | L11: 5 | M11: Heatpump | P11: -1 | Q11: V2 | R11: L | S11: H | T11: G | U11: 0 - 100* | V11: 3.2 sec | W11: Top Speed | X11: 262 km/h | Y11: Range | Z11: 490 km | AA11: Efficiency | AB11: 153 Wh/km | AC11: Fastcharge* | AD11: 760 km/h | AE11: 760 | AF11: 58.47 | AG11: 58.49 | AH11: £59,990 | AI11: 61982 | AJ11: 61982 | AK11: 1.71E+09 | AL11: 1603 | AM11: 2188 | AT11: 153 | AU11: 6.54 | AV11: 126 | AW11: 262 | AX11: 75 | AY11: 490 | AZ11: 45325
A12: https://ev-database.org/car/3035/Dongfeng-Box-314-kWh | B12: https://ev-database.org/img/auto/Dongfeng_Box/Dongfeng_Box-01-thumb.jpg | C12: Box 31.4 kWh | E12: kWh useable battery *| /km of range* | F12: 29 | G12: 118 | J12: Type 2 CCS | L12: 5 | P12: -1 | Q12: V2 | R12: L | S12: H | T12: G | U12: 0 - 100* | V12: 12.5 sec | W12: Top Speed | X12: 140 km/h | Y12: Range* | Z12: 190 km | AA12: Efficiency* | AB12: 153 Wh/km | AC12: Fastcharge | AD12: 180 km/h | AE12: 180 | AF12: N/A | AG12: 22.4 | AH12: N/A | AI12: 22400 | AJ12: 22400 | AK12: 1.75E+09 | AL12: 351 | AM12: 3035 | AN12: V2XL | AQ12: Hatchback | AR12: B | AT12: 153 | AU12: 6.54 | AV12: 118 | AW12: 140 | AX12: 29 | AY12: 190 | AZ12: 45424
A13: https://ev-database.org/car/1536/Renault-Megane-E-Tech-EV40-130hp | B13: https://ev-database.org/img/auto/Renault_Megane_ETech/Renault_Megane_ETech-01-thumb.jpg | C13: Megane E-Tech EV40 130hp | D13: Available to order since April 2022 | E13: kWh useable battery | /km of range* | F13: 40 | G13: 151 | H13: Roofbox possible | I13: 3-Phase Charging | J13: Type 2 CCS | L13: 5 | M13: Heatpump | N13: Towbar possible | O13: 500 | P13: 5 | Q13: 5 | R13: V2 | S13: L | T13: H | U13: 0 - 100 | V13: 10.0 sec | W13: Top Speed | X13: 150 km/h | Y13: Range* | Z13: 260 km | AA13: Efficiency* | AB13: 154 Wh/km | AC13: Fastcharge | AD13: 340 km/h | AE13: 340 | AF13: 42 | AG13: 36.37 | AH13: N/A | AI13: 39185 | AJ13: 39185 | AK13: 1.65E+09 | AL13: 237 | AM13: 1536 | AO13: G | AP13: C | AQ13: Hatchback | AT13: 154 | AU13: 6.49 | AV13: 151 | AW13: 150 | AX13: 40 | AY13: 260 | AZ13: 10
A14: https://ev-database.org/car/1938/Citroen-e-C4-54-kWh | B14: https://ev-database.org/img/auto/Citroen_e-C4/Citroen_e-C4-01-thumb.jpg | C14: e-C4 54 kWh | D14: Available to order since June 2023 | E14: kWh useable battery | /km of range* | F14: 50.8 | G14: 125 | H14: Roofbox possible | I14: 3-Phase Charging | J14: Type 2 CCS | L14: 5 | M14: Heatpump | P14: 4 | Q14: 4 | R14: V2 | S14: L | T14: H | U14: 0 - 100 | V14: 9.2 sec | W14: Top Speed* | X14: 150 km/h | Y14: Range* | Z14: 330 km | AA14: Efficiency* | AB14: 154 Wh/km | AC14: Fastcharge | AD14: 470 km/h | AE14: 470 | AF14: N/A | AG14: N/A | AH14: £35,800 | AI14: 41170 | AJ14: 41170 | AK14: 1.69E+09 | AL14: 166 | AM14: 1938 | AO14: G | AP14: C | AQ14: Hatchback | AT14: 154 | AU14: 6.49 | AV14: 125 | AW14: 150 | AX14: 50.8 | AY14: 330 | AZ14: 45331
A15: https://ev-database.org/car/1939/Citroen-e-C4-X-54-kWh | B15: https://ev-database.org/img/auto/Citroen_e-C4_X/Citroen_e-C4_X-01-thumb.jpg | C15: e-C4 X 54 kWh | D15: Available to order since February 2023 | E15: kWh useable battery | /km of range | F15: 50.8 | G15: 125 | H15: Roofbox possible | I15: 3-Phase Charging | J15: Type 2 CCS | K15: Sedan | L15: 5 | M15: Heatpump | P15: 4 | Q15: 4 | R15: V2 | S15: L | T15: H | U15: 0 - 100 | V15: 9.3 sec | W15: Top Speed* | X15: 150 km/h | Y15: Range | Z15: 330 km | AA15: Efficiency | AB15: 154 Wh/km | AC15: Fastcharge | AD15: 470 km/h | AE15: 470 | AF15: N/A | AG15: N/A | AH15: £35,800 | AI15: 41170 | AJ15: 41170 | AK15: 1.68E+09 | AL15: 192 | AM15: 1939 | AO15: G | AP15: C | AT15: 154 | AU15: 6.49 | AV15: 125 | AW15: 150 | AX15: 50.8 | AY15: 330 | AZ15: 45360
A16: https://ev-database.org/car/1949/Peugeot-e-208-51-kWh | B16: https://ev-database.org/img/auto/Peugeot_e-208_2024/Peugeot_e-208_2024-01-thumb.jpg | C16: e-208 51 kWh | D16: Available to order since August 2023 | E16: kWh useable battery | /km of range* | F16: 48.1 | G16: 126 | I16: 3-Phase Charging | J16: Type 2 CCS | L16: 5 | M16: Heatpump | P16: -1 | Q16: V2 | R16: L | S16: H | T16: G | U16: 0 - 100 | V16: 8.2 sec | W16: Top Speed | X16: 150 km/h | Y16: Range* | Z16: 310 km | AA16: Efficiency* | AB16: 155 Wh/km | AC16: Fastcharge | AD16: 480 km/h | AE16: 480 | AF16: 40.875 | AG16: 39.17 | AH16: £32,400 | AI16: 39101 | AJ16: 39101 | AK16: 1.69E+09 | AL16: 397 | AM16: 1949 | AQ16: Hatchback | AR16: B | AT16: 155 | AU16: 6.45 | AV16: 126 | AW16: 150 | AX16: 48.1 | AY16: 310 | AZ16: 45330
A17: https://ev-database.org/car/2117/Lancia-Ypsilon | B17: https://ev-database.org/img/auto/Lancia_Ypsilon/Lancia_Ypsilon-01-thumb.jpg | C17: Ypsilon | D17: Available to order since June 2024 | E17: kWh useable battery | /km of range* | F17: 48.1 | G17: 122 | I17: 3-Phase Charging | J17: Type 2 CCS | L17: 5 | M17: Heatpump | P17: -1 | Q17: V2 | R17: L | S17: H | T17: G | U17: 0 - 100 | V17: 8.2 sec | W17: Top Speed | X17: 150 km/h | Y17: Range* | Z17: 310 km | AA17: Efficiency* | AB17: 155 Wh/km | AC17: Fastcharge | AD17: 480 km/h | AE17: 480 | AF17: * €40,000 | AG17: 35.4 | AH17: N/A | AI17: 37700 | AJ17: 37700 | AK17: 1.72E+09 | AL17: 439 | AM17: 2117 | AQ17: Hatchback | AR17: B | AT17: 155 | AU17: 6.45 | AV17: 122 | AW17: 150 | AX17: 48.1 | AY17: 310 | AZ17: 45330
A18: https://ev-database.org/car/3039/Leapmotor-T03 | B18: https://ev-database.org/img/auto/Leapmotor_T03/Leapmotor_T03-01-thumb.jpg | C18: T03 | D18: Available to order since October 2024 | E18: kWh useable battery | /km of range* | F18: 37.3 | G18: 80 | J18: Type 2 CCS | L18: 4 | P18: -1 | Q18: V2 | R18: L | S18: H | T18: G | U18: 0 - 100 | V18: 12.7 sec | W18: Top Speed | X18: 130 km/h | Y18: Range* | Z18: 240 km | AA18: Efficiency* | AB18: 155 Wh/km | AC18: Fastcharge | AD18: 180 km/h | AE18: 180 | AF18: 18.9 | AG18: 19.95 | AH18: £15,995 | AI18: 19081 | AJ18: 19081 | AK18: 1.73E+09 | AL18: 846 | AM18: 3039 | AQ18: Hatchback | AT18: 155 | AU18: 6.45 | AV18: 80 | AW18: 130 | AX18: 37.3 | AY18: 240 | AZ18: 45485
A19: https://ev-database.org/car/3066/Peugeot-e-408-58-kWh | B19: https://ev-database.org/img/auto/Peugeot_e-408_2024/Peugeot_e-408_2024-01-thumb.jpg | C19: e-408 58 kWh | D19: Available to order since October 2024 | E19: kWh useable battery | /km of range* | F19: 58.2 | G19: 119 | I19: 3-Phase Charging | J19: Type 2 CCS | L19: 5 | M19: Heatpump | P19: -1 | Q19: V2 | R19: L | S19: H | T19: G | U19: 0 - 100 | V19: 7.2 sec | W19: Top Speed | X19: 160 km/h | Y19: Range* | Z19: 375 km | AA19: Efficiency* | AB19: 155 Wh/km | AC19: Fastcharge | AD19: 420 km/h | AE19: 420 | AF19: 44.6 | AG19: 44.78 | AH19: N/A | AI19: 44690 | AJ19: 44690 | AK19: 1.73E+09 | AL19: 867 | AM19: 3066 | AT19: 155 | AU19: 6.45 | AV19: 119 | AW19: 160 | AX19: 58.2 | AY19: 375 | AZ19: 45329
A20: https://ev-database.org/car/2127/Dacia-Spring-Electric-65 | B20: https://ev-database.org/img/auto/Dacia_Spring_Electric_2024/Dacia_Spring_Electric_2024-01-thumb.jpg | C20: Spring Electric 65 | D20: Available to order since April 2024 | E20: kWh useable battery *| /km of range* | F20: 25 | G20: 119 | J20: Type 2 CCS | L20: 4 | P20: -1 | Q20: V2 | R20: L | S20: H | T20: G | U20: 0 - 100* | V20: 13.7 sec | W20: Top Speed | X20: 125 km/h | Y20: Range* | Z20: 160 km | AA20: Efficiency* | AB20: 156 Wh/km | AC20: Fastcharge | AD20: 170 km/h | AE20: 170 | AF20: 18.9 | AG20: 19.95 | AH20: £15,995 | AI20: 19081 | AJ20: 19081 | AK20: 1.71E+09 | AL20: 506 | AM20: 2127 | AN20: V2XL | AQ20: Hatchback | AT20: 156 | AU20: 6.41 | AV20: 119 | AW20: 125 | AX20: 25 | AY20: 160 | AZ20: 45486
A21: https://ev-database.org/car/2198/BMW-i4-eDrive35 | B21: https://ev-database.org/img/auto/BMW_i4_2024/BMW_i4_2024-01-thumb.jpg | C21: i4 eDrive35 | D21: Available to order since June 2024 | E21: kWh useable battery | /km of range* | F21: 67.1 | G21: 137 | H21: Roofbox possible | I21: 3-Phase Charging | J21: Type 2 CCS | K21: Liftback | L21: 5 | M21: Heatpump | N21: Towbar possible | O21: 1600 | P21: -1 | Q21: V2 | R21: L | S21: H | T21: G | U21: 0 - 100 | V21: 6.0 sec | W21: Top Speed | X21: 190 km/h | Y21: Range* | Z21: 430 km | AA21: Efficiency* | AB21: 156 Wh/km | AC21: Fastcharge | AD21: 580 km/h | AE21: 580 | AF21: 57.5 | AG21: 59.728 | AH21: £51,270 | AI21: 58729 | AJ21: 58729 | AK21: 1.72E+09 | AL21: 532 | AM21: 2198 | AT21: 156 | AU21: 6.41 | AV21: 137 | AW21: 190 | AX21: 67.1 | AY21: 430 | AZ21: 6
A22: https://ev-database.org/car/2230/Hyundai-INSTER-Standard-Range | B22: https://ev-database.org/img/auto/Hyundai_Inster_2025/Hyundai_Inster_2025-01-thumb.jpg | C22: INSTER Standard Range | D22: Available to order since October 2024 | E22: kWh useable battery *| /km of range* | F22: 39 | G22: 100 | H22: Roofbox possible | I22: 3-Phase Charging | J22: Type 2 CCS | L22: 4 | M22: Heatpump | P22: -1 | Q22: V2 | R22: L | S22: H | T22: G | U22: 0 - 100 | V22: 11.7 sec | W22: Top Speed | X22: 140 km/h | Y22: Range* | Z22: 250 km | AA22: Efficiency* | AB22: 156 Wh/km | AC22: Fastcharge | AD22: 360 km/h | AE22: 360 | AF22: * €24,000 | AG22: 24.295 | AH22: £23,495 | AI22: 25104 | AJ22: 25104 | AK22: 1.73E+09 | AL22: 800 | AM22: 2230 | AN22: V2XL | AT22: 156 | AU22: 6.41 | AV22: 100 | AW22: 140 | AX22: 39 | AY22: 250 | AZ22: 45484
A23: https://ev-database.org/car/2231/Hyundai-INSTER-Long-Range | B23: https://ev-database.org/img/auto/Hyundai_Inster_2025/Hyundai_Inster_2025-01-thumb.jpg | C23: INSTER Long Range | D23: Available to order since October 2024 | E23: kWh useable battery *| /km of range* | F23: 46 | G23: 92 | H23: Roofbox possible | I23: 3-Phase Charging | J23: Type 2 CCS | L23: 4 | M23: Heatpump | P23: -1 | Q23: V2 | R23: L | S23: H | T23: G | U23: 0 - 100 | V23: 10.6 sec | W23: Top Speed | X23: 150 km/h | Y23: Range* | Z23: 295 km | AA23: Efficiency* | AB23: 156 Wh/km | AC23: Fastcharge | AD23: 420 km/h | AE23: 420 | AF23: * €27,000 | AG23: 25.995 | AH23: £25,045 | AI23: 27265 | AJ23: 27265 | AK23: 1.73E+09 | AL23: 1057 | AM23: 2231 | AN23: V2XL | AT23: 156 | AU23: 6.41 | AV23: 92 | AW23: 150 | AX23: 46 | AY23: 295 | AZ23: 45453
A24: https://ev-database.org/car/3053/Audi-A6-Sportback-e-tron | B24: https://ev-database.org/img/auto/Audi_A6_Sportback_etron_2024/Audi_A6_Sportback_etron_2024-01-thumb.jpg | C24: A6 Sportback e-tron | D24: Available to order since October 2024 | E24: kWh useable battery | /km of range* | F24: 75.8 | G24: 131 | H24: Roofbox possible | I24: 3-Phase Charging | J24: Type 2 CCS | K24: Liftback | L24: 5 | M24: Heatpump | N24: Towbar possible | O24: 2100 | P24: -1 | Q24: V2 | R24: L | S24: H | T24: G | U24: 0 - 100 | V24: 6.0 sec | W24: Top Speed | X24: 210 km/h | Y24: Range* | Z24: 485 km | AA24: Efficiency* | AB24: 156 Wh/km | AC24: Fastcharge | AD24: 920 km/h | AE24: 920 | AF24: 62.8 | AG24: 63.99 | AH24: N/A | AI24: 63395 | AJ24: 63395 | AK24: 1.73E+09 | AL24: 357 | AM24: 3053 | AT24: 156 | AU24: 6.41 | AV24: 131 | AW24: 210 | AX24: 75.8 | AY24: 485 | AZ24: 6
A25: https://ev-database.org/car/1941/Opel-Corsa-Electric-50-kWh | B25: https://ev-database.org/img/auto/Opel_Corsa_Electric_2023/Opel_Corsa_Electric_2023-01-thumb.jpg | C25: Corsa Electric 50 kWh | D25: Available to order since July 2023 | E25: kWh useable battery | /km of range* | F25: 46.3 | G25: 121 | H25: Roofbox possible | I25: 3-Phase Charging | J25: Type 2 CCS | L25: 5 | M25: Heatpump | P25: -1 | Q25: V2 | R25: L | S25: H | T25: G | U25: 0 - 100 | V25: 8.7 sec | W25: Top Speed | X25: 150 km/h | Y25: Range* | Z25: 295 km | AA25: Efficiency* | AB25: 157 Wh/km | AC25: Fastcharge | AD25: 470 km/h | AE25: 470 | AF25: 34.65 | AG25: 34.999 | AH25: £32,445 | AI25: 35653 | AJ25: 35653 | AK25: 1.69E+09 | AL25: 374 | AM25: 1941 | AQ25: Hatchback | AR25: B | AT25: 157 | AU25: 6.37 | AV25: 121 | AW25: 150 | AX25: 46.3 | AY25: 295 | AZ25: 45481
A26: https://ev-database.org/car/2133/Renault-5-E-Tech-40kWh-95hp | B26: https://ev-database.org/img/auto/Renault_5_ETech/Renault_5_ETech-01-thumb.jpg | C26: 5 E-Tech 40kWh 95hp | E26: kWh useable battery | /km of range* | F26: 40 | G26: 98 | I26: 3-Phase Charging | L26: 5 | M26: Heatpump | N26: Towbar possible | O26: 500 | P26: -1 | Q26: V2 | R26: L | S26: H | T26: G | U26: 0 - 100* | V26: 10.0 sec | W26: Top Speed | X26: 140 km/h | Y26: Range* | Z26: 255 km | AA26: Efficiency* | AB26: 157 Wh/km | AC26: Fastcharge | AD26: - | AF26: 24.9 | AG26: * €25,000 | AH26: * £22,000 | AI26: 25066 | AJ26: 25066 | AK26: 1.75E+09 | AL26: 493 | AM26: 2133 | AQ26: Hatchback | AR26: B | AT26: 157 | AU26: 6.37 | AV26: 98 | AW26: 140 | AX26: 40 | AY26: 255 | AZ26: 10
A27: https://ev-database.org/car/2134/Renault-5-E-Tech-40kWh-120hp | B27: https://ev-database.org/img/auto/Renault_5_ETech/Renault_5_ETech-01-thumb.jpg | C27: 5 E-Tech 40kWh 120hp | D27: Available to order since November 2024 | E27: kWh useable battery | /km of range* | F27: 40 | G27: 108 | I27: 3-Phase Charging | J27: Type 2 CCS | L27: 5 | M27: Heatpump | N27: Towbar possible | O27: 500 | P27: -1 | Q27: V2 | R27: L | S27: H | T27: G | U27: 0 - 100 | V27: 9.0 sec | W27: Top Speed | X27: 140 km/h | Y27: Range* | Z27: 255 km | AA27: Efficiency* | AB27: 157 Wh/km | AC27: Fastcharge | AD27: 330 km/h | AE27: 330 | AF27: 27.9 | AG27: 27.99 | AH27: £22,995 | AI27: 27444 | AJ27: 27444 | AK27: 1.73E+09 | AL27: 298 | AM27: 2134 | AN27: V2XL | AQ27: Hatchback | AR27: B | AT27: 157 | AU27: 6.37 | AV27: 108 | AW27: 140 | AX27: 40 | AY27: 255 | AZ27: 9
A28: https://ev-database.org/car/3036/Dongfeng-Box-423-kWh | B28: https://ev-database.org/img/auto/Dongfeng_Box/Dongfeng_Box-01-thumb.jpg | C28: Box 42.3 kWh | D28: Available to order since October 2024 | E28: kWh useable battery *| /km of range* | F28: 40 | G28: 92 | J28: Type 2 CCS | L28: 5 | P28: -1 | Q28: V2 | R28: L | S28: H | T28: G | U28: 0 - 100* | V28: 12.5 sec | W28: Top Speed | X28: 140 km/h | Y28: Range* | Z28: 255 km | AA28: Efficiency* | AB28: 157 Wh/km | AC28: Fastcharge | AD28: 240 km/h | AE28: 240 | AF28: N/A | AG28: 23.4 | AH28: N/A | AI28: 23400 | AJ28: 23400 | AK28: 1.73E+09 | AL28: 652 | AM28: 3036 | AN28: V2XL | AQ28: Hatchback | AR28: B | AT28: 157 | AU28: 6.37 | AV28: 92 | AW28: 140 | AX28: 40 | AY28: 255 | AZ28: 45424
A29: https://ev-database.org/car/3049/Citroen-e-C4-X | B29: https://ev-database.org/img/auto/Citroen_e-C4_X_2024/Citroen_e-C4_X_2024-01-thumb.jpg | C29: e-C4 X | D29: Available to order since October 2024 | E29: kWh useable battery | /km of range* | F29: 46.3 | G29: 116 | H29: Roofbox possible | I29: 3-Phase Charging | J29: Type 2 CCS | K29: Sedan | L29: 5 | M29: Heatpump | P29: 4 | Q29: 4 | R29: V2 | S29: L | T29: H | U29: 0 - 100 | V29: 10.8 sec | W29: Top Speed | X29: 150 km/h | Y29: Range* | Z29: 295 km | AA29: Efficiency* | AB29: 157 Wh/km | AC29: Fastcharge | AD29: 470 km/h | AE29: 470 | AF29: 32.6 | AG29: 35.915 | AH29: N/A | AI29: 34257 | AJ29: 34257 | AK29: 1.73E+09 | AL29: 192 | AM29: 3049 | AO29: G | AP29: C | AT29: 157 | AU29: 6.37 | AV29: 116 | AW29: 150 | AX29: 46.3 | AY29: 295 | AZ29: 45514
A30: https://ev-database.org/car/1327/Fiat-500e-Hatchback-24-kWh | B30: https://ev-database.org/img/auto/Fiat_500e_Hatchback_2020/Fiat_500e_Hatchback_2020-01-thumb.jpg | C30: 500e Hatchback 24 kWh | D30: Available to order since November 2020 | E30: kWh useable battery | /km of range* | F30: 45372 | G30: 219 | I30: 3-Phase Charging | J30: Type 2 CCS | L30: 4 | P30: 4 | Q30: 4 | R30: V2 | S30: L | T30: H | U30: 0 - 100 | V30: 9.0 sec | W30: Top Speed | X30: 135 km/h | Y30: Range* | Z30: 135 km | AA30: Efficiency* | AB30: 158 Wh/km | AC30: Fastcharge | AD30: 230 km/h | AE30: 230 | AF30: 30.99 | AG30: 28.99 | AH30: £24,995 | AI30: 29574 | AJ30: 29574 | AK30: 1.6E+09 | AL30: 297 | AM30: 1327 | AO30: G | AQ30: Hatchback | AR30: B | AT30: 158 | AU30: 6.33 | AV30: 219 | AW30: 135 | AX30: 45372 | AY30: 135 | AZ30: 9
A31: https://ev-database.org/car/1521/Renault-Megane-E-Tech-EV60-220hp | B31: https://ev-database.org/img/auto/Renault_Megane_ETech/Renault_Megane_ETech-01-thumb.jpg | C31: Megane E-Tech EV60 220hp | D31: Available to order since April 2022 | E31: kWh useable battery | /km of range | F31: 60 | G31: 113 | H31: Roofbox possible | I31: 3-Phase Charging | J31: Type 2 CCS | L31: 5 | M31: Heatpump | N31: Towbar possible | O31: 900 | P31: 5 | Q31: 5 | R31: V2 | S31: L | T31: H | U31: 0 - 100 | V31: 7.4 sec | W31: Top Speed | X31: 160 km/h | Y31: Range | Z31: 380 km | AA31: Efficiency | AB31: 158 Wh/km | AC31: Fastcharge | AD31: 530 km/h | AE31: 530 | AF31: 46.6 | AG31: 39.37 | AH31: £36,995 | AI31: 42838 | AJ31: 42838 | AK31: 1.65E+09 | AL31: 1414 | AM31: 1521 | AO31: G | AP31: C | AQ31: Hatchback | AT31: 158 | AU31: 6.33 | AV31: 113 | AW31: 160 | AX31: 60 | AY31: 380 | AZ31: 45389
A32: https://ev-database.org/car/1588/Renault-Megane-E-Tech-EV60-130hp | B32: https://ev-database.org/img/auto/Renault_Megane_ETech/Renault_Megane_ETech-01-thumb.jpg | C32: Megane E-Tech EV60 130hp | D32: Available to order since April 2022 | E32: kWh useable battery | /km of range* | F32: 60 | G32: 114 | H32: Roofbox possible | I32: 3-Phase Charging | J32: Type 2 CCS | L32: 5 | M32: Heatpump | N32: Towbar possible | O32: 500 | P32: 5 | Q32: 5 | R32: V2 | S32: L | T32: H | U32: 0 - 100 | V32: 10.5 sec | W32: Top Speed | X32: 150 km/h | Y32: Range* | Z32: 380 km | AA32: Efficiency* | AB32: 158 Wh/km | AC32: Fastcharge | AD32: 530 km/h | AE32: 530 | AF32: 47 | AG32: 39.37 | AH32: N/A | AI32: 43185 | AJ32: 43185 | AK32: 1.65E+09 | AL32: 237 | AM32: 1588 | AO32: G | AP32: C | AQ32: Hatchback | AT32: 158 | AU32: 6.33 | AV32: 114 | AW32: 150 | AX32: 60 | AY32: 380 | AZ32: 45422
A33: https://ev-database.org/car/1726/Fiat-500e-3plus1-24-kWh | B33: https://ev-database.org/img/auto/Fiat_500e_3plus1_2020/Fiat_500e_3plus1_2020-01-thumb.jpg | C33: 500e 3+1 24 kWh | D33: Available to order since July 2022 | E33: kWh useable battery | /km of range* | F33: 45372 | G33: 230 | I33: 3-Phase Charging | J33: Type 2 CCS | L33: 4 | P33: 4 | Q33: 4 | R33: V2 | S33: L | T33: H | U33: 0 - 100 | V33: 9.0 sec | W33: Top Speed | X33: 135 km/h | Y33: Range* | Z33: 135 km | AA33: Efficiency* | AB33: 158 Wh/km | AC33: Fastcharge | AD33: 230 km/h | AE33: 230 | AF33: N/A | AG33: 30.99 | AH33: N/A | AI33: 30990 | AJ33: 30990 | AK33: 1.66E+09 | AL33: 109 | AM33: 1726 | AO33: G | AQ33: Hatchback | AR33: B | AT33: 158 | AU33: 6.33 | AV33: 230 | AW33: 135 | AX33: 45372 | AY33: 135 | AZ33: 9
A34: https://ev-database.org/car/1727/Fiat-500e-Cabrio-24-kWh | B34: https://ev-database.org/img/auto/Fiat_500e_Convertible_2020/Fiat_500e_Convertible_2020-01-thumb.jpg | C34: 500e Cabrio 24 kWh | D34: Available to order since July 2022 | E34: kWh useable battery | /km of range* | F34: 45372 | G34: 250 | I34: 3-Phase Charging | J34: Type 2 CCS | L34: 4 | P34: 4 | Q34: 4 | R34: V2 | S34: L | T34: H | U34: 0 - 100 | V34: 9.0 sec | W34: Top Speed | X34: 135 km/h | Y34: Range* | Z34: 135 km | AA34: Efficiency* | AB34: 158 Wh/km | AC34: Fastcharge | AD34: 230 km/h | AE34: 230 | AF34: 35.49 | AG34: 31.99 | AH34: N/A | AI34: 33740 | AJ34: 33740 | AK34: 1.66E+09 | AL34: 114 | AM34: 1727 | AO34: G | AR34: B | AT34: 158 | AU34: 6.33 | AV34: 250 | AW34: 135 | AX34: 45372 | AY34: 135 | AZ34: 9
A35: https://ev-database.org/car/2199/BMW-i4-eDrive40 | B35: https://ev-database.org/img/auto/BMW_i4_2024/BMW_i4_2024-01-thumb.jpg | C35: i4 eDrive40 | D35: Available to order since June 2024 | E35: kWh useable battery | /km of range* | F35: 81.3 | G35: 124 | H35: Roofbox possible | I35: 3-Phase Charging | J35: Type 2 CCS | K35: Liftback | L35: 5 | M35: Heatpump | N35: Towbar possible | O35: 1600 | P35: -1 | Q35: V2 | R35: L | S35: H | T35: G | U35: 0 - 100 | V35: 5.6 sec | W35: Top Speed | X35: 190 km/h | Y35: Range* | Z35: 515 km | AA35: Efficiency* | AB35: 158 Wh/km | AC35: Fastcharge | AD35: 800 km/h | AE35: 800 | AF35: 60.5 | AG35: 63.358 | AH35: £59,365 | AI35: 64042 | AJ35: 64042 | AK35: 1.72E+09 | AL35: 1230 | AM35: 2199 | AT35: 158 | AU35: 6.33 | AV35: 124 | AW35: 190 | AX35: 81.3 | AY35: 515 | AZ35: 45448
A36: https://ev-database.org/car/2270/Audi-A6-Sportback-e-tron-performance | B36: https://ev-database.org/img/auto/Audi_A6_Sportback_etron_2024/Audi_A6_Sportback_etron_2024-01-thumb.jpg | C36: A6 Sportback e-tron performance | D36: Available to order since September 2024 | E36: kWh useable battery | /km of range* | F36: 94.9 | G36: 129 | H36: Roofbox possible | I36: 3-Phase Charging | J36: Type 2 CCS | K36: Liftback | L36: 5 | M36: Heatpump | N36: Towbar possible | O36: 2100 | P36: -1 | Q36: V2 | R36: L | S36: H | T36: G | U36: 0 - 100 | V36: 5.4 sec | W36: Top Speed | X36: 210 km/h | Y36: Range* | Z36: 600 km | AA36: Efficiency* | AB36: 158 Wh/km | AC36: Fastcharge | AD36: 1200 km/h | AE36: 1200 | AF36: 75.6 | AG36: 75.99 | AH36: £69,900 | AI36: 77325 | AJ36: 77325 | AK36: 1.73E+09 | AL36: 1056 | AM36: 2270 | AT36: 158 | AU36: 6.33 | AV36: 129 | AW36: 210 | AX36: 94.9 | AY36: 600 | AZ36: 45387
A37: https://ev-database.org/car/1285/Fiat-500e-Hatchback-42-kWh | B37: https://ev-database.org/img/auto/Fiat_500e_Hatchback_2020/Fiat_500e_Hatchback_2020-01-thumb.jpg | C37: 500e Hatchback 42 kWh | D37: Available to order since November 2020 | E37: kWh useable battery | /km of range | F37: 37.3 | G37: 144 | I37: 3-Phase Charging | J37: Type 2 CCS | L37: 4 | P37: 4 | Q37: 4 | R37: V2 | S37: L | T37: H | U37: 0 - 100 | V37: 9.0 sec | W37: Top Speed | X37: 150 km/h | Y37: Range | Z37: 235 km | AA37: Efficiency | AB37: 159 Wh/km | AC37: Fastcharge | AD37: 390 km/h | AE37: 390 | AF37: 34.99 | AG37: 34.49 | AH37: £27,995 | AI37: 33891 | AJ37: 33891 | AK37: 1.6E+09 | AL37: 1146 | AM37: 1285 | AO37: G | AQ37: Hatchback | AR37: B | AT37: 159 | AU37: 6.29 | AV37: 144 | AW37: 150 | AX37: 37.3 | AY37: 235 | AZ37: 9
A38: https://ev-database.org/car/1317/Lucid-Air-Touring | B38: https://ev-database.org/img/auto/Lucid_Air/Lucid_Air-01-thumb.jpg | C38: Air Touring | D38: Available to order since May 2023 | E38: kWh useable battery *| /km of range* | F38: 92 | G38: 173 | I38: 3-Phase Charging | J38: Type 2 CCS | K38: Sedan | L38: 5 | P38: 5 | Q38: 5 | R38: V2 | S38: L | T38: H | U38: 0 - 100 | V38: 3.2 sec | W38: Top Speed | X38: 250 km/h | Y38: Range* | Z38: 580 km | AA38: Efficiency* | AB38: 159 Wh/km | AC38: Fastcharge* | AD38: 970 km/h | AE38: 970 | AF38: 99 | AG38: 102 | AH38: N/A | AI38: 100000 | AJ38: 100500 | AK38: 1.68E+09 | AL38: 310 | AM38: 1317 | AN38: V2XL | AO38: G | AT38: 159 | AU38: 6.29 | AV38: 173 | AW38: 250 | AX38: 92 | AY38: 580 | AZ38: 45325
A39: https://ev-database.org/car/1328/Fiat-500e-3plus1-42-kWh | B39: https://ev-database.org/img/auto/Fiat_500e_3plus1_2020/Fiat_500e_3plus1_2020-01-thumb.jpg | C39: 500e 3+1 42 kWh | D39: Available to order since November 2020 | E39: kWh useable battery | /km of range* | F39: 37.3 | G39: 154 | I39: 3-Phase Charging | J39: Type 2 CCS | L39: 4 | P39: 4 | Q39: 4 | R39: V2 | S39: L | T39: H | U39: 0 - 100 | V39: 9.0 sec | W39: Top Speed | X39: 150 km/h | Y39: Range* | Z39: 235 km | AA39: Efficiency* | AB39: 159 Wh/km | AC39: Fastcharge | AD39: 390 km/h | AE39: 390 | AF39: 36.99 | AG39: 35.49 | AH39: N/A | AI39: 36240 | AJ39: 36240 | AK39: 1.6E+09 | AL39: 157 | AM39: 1328 | AO39: G | AQ39: Hatchback | AR39: B | AT39: 159 | AU39: 6.29 | AV39: 154 | AW39: 150 | AX39: 37.3 | AY39: 235 | AZ39: 9
A40: https://ev-database.org/car/1792/Opel-Astra-Electric | B40: https://ev-database.org/img/auto/Opel_Astra_Electric/Opel_Astra_Electric-01-thumb.jpg | C40: Astra Electric | D40: Available to order since June 2023 | E40: kWh useable battery | /km of range* | F40: 50.8 | G40: 131 | I40: 3-Phase Charging | J40: Type 2 CCS | L40: 5 | M40: Heatpump | N40: Towbar possible | O40: 0 | P40: -1 | Q40: V2 | R40: L | S40: H | T40: G | U40: 0 - 100 | V40: 9.2 sec | W40: Top Speed | X40: 170 km/h | Y40: Range* | Z40: 320 km | AA40: Efficiency* | AB40: 159 Wh/km | AC40: Fastcharge | AD40: 510 km/h | AE40: 510 | AF40: 41.99 | AG40: 39.999 | AH40: £37,795 | AI40: 41817 | AJ40: 41817 | AK40: 1.69E+09 | AL40: 608 | AM40: 1792 | AP40: C | AQ40: Hatchback | AT40: 159 | AU40: 6.29 | AV40: 131 | AW40: 170 | AX40: 50.8 | AY40: 320 | AZ40: 45331
A41: https://ev-database.org/car/2184/Alfa-Romeo-Junior-Elettrica-54-kWh | B41: https://ev-database.org/img/auto/Alfa_Romeo_Junior/Alfa_Romeo_Junior-01-thumb.jpg | C41: Junior Elettrica 54 kWh | D41: Available to order since April 2024 | E41: kWh useable battery | /km of range* | F41: 50.8 | G41: 122 | I41: 3-Phase Charging | J41: Type 2 CCS | L41: 5 | M41: Heatpump | P41: -1 | Q41: V2 | R41: L | S41: H | T41: G | U41: 0 - 100 | V41: 9.0 sec | W41: Top Speed | X41: 150 km/h | Y41: Range* | Z41: 320 km | AA41: Efficiency* | AB41: 159 Wh/km | AC41: Fastcharge | AD41: 510 km/h | AE41: 510 | AF41: 39.5 | AG41: 39 | AH41: £33,895 | AI41: 39159 | AJ41: 39159 | AK41: 1.71E+09 | AL41: 343 | AM41: 2184 | AR41: B | AT41: 159 | AU41: 6.29 | AV41: 122 | AW41: 150 | AX41: 50.8 | AY41: 320 | AZ41: 9
A42: https://ev-database.org/car/1587/Citroen-e-C4 | B42: https://ev-database.org/img/auto/Citroen_e-C4/Citroen_e-C4-01-thumb.jpg | C42: e-C4 | D42: Available to order since November 2021 | E42: kWh useable battery | /km of range* | F42: 46.3 | G42: 127 | H42: Roofbox possible | I42: 3-Phase Charging | J42: Type 2 CCS | L42: 5 | M42: Heatpump | P42: 4 | Q42: 4 | R42: V2 | S42: L | T42: H | U42: 0 - 100 | V42: 9.7 sec | W42: Top Speed | X42: 150 km/h | Y42: Range* | Z42: 290 km | AA42: Efficiency* | AB42: 160 Wh/km | AC42: Fastcharge | AD42: 460 km/h | AE42: 460 | AF42: N/A | AG42: N/A | AH42: £31,960 | AI42: 36754 | AJ42: 36754 | AK42: 1.64E+09 | AL42: 925 | AM42: 1587 | AO42: G | AP42: C | AQ42: Hatchback | AT42: 160 | AU42: 6.25 | AV42: 127 | AW42: 150 | AX42: 46.3 | AY42: 290 | AZ42: 45482
A43: https://ev-database.org/car/1948/Peugeot-e-208-50-kWh | B43: https://ev-database.org/img/auto/Peugeot_e-208_2024/Peugeot_e-208_2024-01-thumb.jpg | C43: e-208 50 kWh | D43: Available to order since August 2023 | E43: kWh useable battery | /km of range* | F43: 46.3 | G43: 126 | I43: 3-Phase Charging | J43: Type 2 CCS | L43: 5 | M43: Heatpump | P43: -1 | Q43: V2 | R43: L | S43: H | T43: G | U43: 0 - 100 | V43: 9.0 sec | W43: Top Speed | X43: 150 km/h | Y43: Range* | Z43: 290 km | AA43: Efficiency* | AB43: 160 Wh/km | AC43: Fastcharge | AD43: 460 km/h | AE43: 460 | AF43: 35.975 | AG43: 35.87 | AH43: £32,650 | AI43: 36464 | AJ43: 36464 | AK43: 1.69E+09 | AL43: 582 | AM43: 1948 | AQ43: Hatchback | AR43: B | AT43: 160 | AU43: 6.25 | AV43: 126 | AW43: 150 | AX43: 46.3 | AY43: 290 | AZ43: 9
A44: https://ev-database.org/car/2024/Skoda-Enyaq-Coupe-85 | B44: https://ev-database.org/img/auto/Skoda_Enyaq_Coupe_iV_2022/Skoda_Enyaq_Coupe_iV_2022-01-thumb.jpg | C44: Enyaq Coupe 85 | D44: Available to order since September 2023 | E44: kWh useable battery | /km of range* | F44: 77 | G44: 109 | H44: Roofbox possible | I44: 3-Phase Charging | J44: Type 2 CCS | L44: 5 | M44: Heatpump | N44: Towbar possible | O44: 1000 | P44: 5 | Q44: 5 | R44: V2 | S44: L | T44: H | U44: 0 - 100 | V44: 6.7 sec | W44: Top Speed | X44: 180 km/h | Y44: Range* | Z44: 480 km | AA44: Efficiency* | AB44: 160 Wh/km | AC44: Fastcharge | AD44: 720 km/h | AE44: 720 | AF44: 51.15 | AG44: 52.49 | AH44: £46,440 | AI44: 52348 | AJ44: 52348 | AK44: 1.69E+09 | AL44: 481 | AM44: 2024 | AO44: G | AP44: C | AT44: 160 | AU44: 6.25 | AV44: 109 | AW44: 180 | AX44: 77 | AY44: 480 | AZ44: 45479
A45: https://ev-database.org/car/3047/Citroen-e-C4 | B45: https://ev-database.org/img/auto/Citroen_e-C4_2024/Citroen_e-C4_2024-01-thumb.jpg | C45: e-C4 | D45: Available to order since October 2024 | E45: kWh useable battery | /km of range* | F45: 46.3 | G45: 116 | H45: Roofbox possible | I45: 3-Phase Charging | J45: Type 2 CCS | L45: 5 | M45: Heatpump | P45: 4 | Q45: 4 | R45: V2 | S45: L | T45: H | U45: 0 - 100 | V45: 10.8 sec | W45: Top Speed | X45: 150 km/h | Y45: Range* | Z45: 290 km | AA45: Efficiency* | AB45: 160 Wh/km | AC45: Fastcharge | AD45: 460 km/h | AE45: 460 | AF45: 31.9 | AG45: 35.215 | AH45: N/A | AI45: 33557 | AJ45: 33557 | AK45: 1.73E+09 | AL45: 221 | AM45: 3047 | AO45: G | AP45: C | AQ45: Hatchback | AT45: 160 | AU45: 6.25 | AV45: 116 | AW45: 150 | AX45: 46.3 | AY45: 290 | AZ45: 45514
A46: https://ev-database.org/car/3055/Audi-A6-Avant-e-tron | B46: https://ev-database.org/img/auto/Audi_A6_Avant_etron_2024/Audi_A6_Avant_etron_2024-01-thumb.jpg | C46: A6 Avant e-tron | D46: Available to order since October 2024 | E46: kWh useable battery | /km of range* | F46: 75.8 | G46: 137 | H46: Roofbox possible | I46: 3-Phase Charging | J46: Type 2 CCS | L46: 5 | M46: Heatpump | N46: Towbar possible | O46: 2100 | P46: -1 | Q46: V2 | R46: L | S46: H | T46: G | U46: 0 - 100 | V46: 6.0 sec | W46: Top Speed | X46: 210 km/h | Y46: Range* | Z46: 475 km | AA46: Efficiency* | AB46: 160 Wh/km | AC46: Fastcharge | AD46: 900 km/h | AE46: 900 | AF46: 64.45 | AG46: 65.49 | AH46: N/A | AI46: 64970 | AJ46: 64970 | AK46: 1.73E+09 | AL46: 428 | AM46: 3055 | AT46: 160 | AU46: 6.25 | AV46: 137 | AW46: 210 | AX46: 75.8 | AY46: 475 | AZ46: 6
A47: https://ev-database.org/car/1275/Fiat-500e-Cabrio-42-kWh | B47: https://ev-database.org/img/auto/Fiat_500e_Convertible_2020/Fiat_500e_Convertible_2020-01-thumb.jpg | C47: 500e Cabrio 42 kWh | D47: Available to order since November 2020 | E47: kWh useable battery | /km of range* | F47: 37.3 | G47: 161 | I47: 3-Phase Charging | J47: Type 2 CCS | L47: 4 | P47: 4 | Q47: 4 | R47: V2 | S47: L | T47: H | U47: 0 - 100 | V47: 9.0 sec | W47: Top Speed | X47: 150 km/h | Y47: Range* | Z47: 230 km | AA47: Efficiency* | AB47: 162 Wh/km | AC47: Fastcharge | AD47: 380 km/h | AE47: 380 | AF47: 37.99 | AG47: 37.49 | AH47: £30,995 | AI47: 37041 | AJ47: 37041 | AK47: 1.6E+09 | AL47: 206 | AM47: 1275 | AO47: G | AR47: B | AT47: 162 | AU47: 6.17 | AV47: 161 | AW47: 150 | AX47: 37.3 | AY47: 230 | AZ47: 9
A48: https://ev-database.org/car/1706/Citroen-e-C4-X | B48: https://ev-database.org/img/auto/Citroen_e-C4_X/Citroen_e-C4_X-01-thumb.jpg | C48: e-C4 X | D48: Available to order since November 2022 | E48: kWh useable battery | /km of range* | F48: 46.3 | G48: 129 | H48: Roofbox possible | I48: 3-Phase Charging | J48: Type 2 CCS | K48: Sedan | L48: 5 | M48: Heatpump | P48: 4 | Q48: 4 | R48: V2 | S48: L | T48: H | U48: 0 - 100 | V48: 9.7 sec | W48: Top Speed | X48: 150 km/h | Y48: Range* | Z48: 285 km | AA48: Efficiency* | AB48: 162 Wh/km | AC48: Fastcharge | AD48: 460 km/h | AE48: 460 | AF48: N/A | AG48: N/A | AH48: £31,960 | AI48: 36754 | AJ48: 36754 | AK48: 1.67E+09 | AL48: 348 | AM48: 1706 | AO48: G | AP48: C | AT48: 162 | AU48: 6.17 | AV48: 129 | AW48: 150 | AX48: 46.3 | AY48: 285 | AZ48: 45482
A49: https://ev-database.org/car/1839/Volkswagen-ID7-Pro | B49: https://ev-database.org/img/auto/Volkswagen_ID7/Volkswagen_ID7-01-thumb.jpg | C49: ID.7 Pro | D49: Available to order since August 2023 | E49: kWh useable battery | /km of range | F49: 77 | G49: 120 | H49: Roofbox possible | I49: 3-Phase Charging | J49: Type 2 CCS | K49: Liftback | L49: 5 | M49: Heatpump | N49: Towbar possible | O49: 1000 | P49: 5 | Q49: 5 | R49: V2 | S49: L | T49: H | U49: 0 - 100 | V49: 6.5 sec | W49: Top Speed | X49: 180 km/h | Y49: Range | Z49: 475 km | AA49: Efficiency | AB49: 162 Wh/km | AC49: Fastcharge | AD49: 730 km/h | AE49: 730 | AF49: 53.995 | AG49: 57.99 | AH49: £51,550 | AI49: 57089 | AJ49: 57089 | AK49: 1.69E+09 | AL49: 1778 | AM49: 1839 | AO49: G | AT49: 162 | AU49: 6.17 | AV49: 120 | AW49: 180 | AX49: 77 | AY49: 475 | AZ49: 45418
A50: https://ev-database.org/car/2025/Skoda-Enyaq-Coupe-85x | B50: https://ev-database.org/img/auto/Skoda_Enyaq_Coupe_iV_2022/Skoda_Enyaq_Coupe_iV_2022-01-thumb.jpg | C50: Enyaq Coupe 85x | D50: Available to order since September 2023 | E50: kWh useable battery | /km of range* | F50: 77 | G50: 117 | H50: Roofbox possible | I50: 3-Phase Charging | J50: Type 2 CCS | L50: 5 | M50: Heatpump | N50: Towbar possible | O50: 1200 | P50: 5 | Q50: 5 | R50: V2 | S50: L | T50: H | U50: 0 - 100 | V50: 6.6 sec | W50: Top Speed | X50: 180 km/h | Y50: Range* | Z50: 475 km | AA50: Efficiency* | AB50: 162 Wh/km | AC50: Fastcharge | AD50: 710 km/h | AE50: 710 | AF50: 53.4 | AG50: N/A | AH50: £50,305 | AI50: 55625 | AJ50: 55625 | AK50: 1.69E+09 | AL50: 220 | AM50: 2025 | AO50: G | AP50: C | AT50: 162 | AU50: 6.17 | AV50: 117 | AW50: 180 | AX50: 77 | AY50: 475 | AZ50: 45449
A51: https://ev-database.org/car/3052/Audi-A6-Sportback-e-tron-quattro | B51: https://ev-database.org/img/auto/Audi_A6_Sportback_etron_2024/Audi_A6_Sportback_etron_2024-01-thumb.jpg | C51: A6 Sportback e-tron quattro | D51: Available to order since October 2024 | E51: kWh useable battery | /km of range* | F51: 94.9 | G51: 137 | H51: Roofbox possible | I51: 3-Phase Charging | J51: Type 2 CCS | K51: Liftback | L51: 5 | M51: Heatpump | N51: Towbar possible | O51: 2100 | P51: -1 | Q51: V2 | R51: L | S51: H | T51: G | U51: 0 - 100 | V51: 4.7 sec | W51: Top Speed | X51: 210 km/h | Y51: Range* | Z51: 585 km | AA51: Efficiency* | AB51: 162 Wh/km | AC51: Fastcharge | AD51: 1170 km/h | AE51: 1170 | AF51: 79.8 | AG51: 79.99 | AH51: N/A | AI51: 79895 | AJ51: 79895 | AK51: 1.73E+09 | AL51: 527 | AM51: 3052 | AT51: 162 | AU51: 6.17 | AV51: 137 | AW51: 210 | AX51: 94.9 | AY51: 585 | AZ51: 45477
A52: https://ev-database.org/car/1997/Mini-Cooper-E | B52: https://ev-database.org/img/auto/Mini_Cooper_Electric_2024/Mini_Cooper_Electric_2024-01-thumb.jpg | C52: Cooper E | D52: Available to order since December 2023 | E52: kWh useable battery | /km of range* | F52: 36.6 | G52: 153 | I52: 3-Phase Charging | J52: Type 2 CCS | L52: 4 | M52: Heatpump | P52: -1 | Q52: V2 | R52: L | S52: H | T52: G | U52: 0 - 100 | V52: 7.3 sec | W52: Top Speed | X52: 160 km/h | Y52: Range* | Z52: 225 km | AA52: Efficiency* | AB52: 163 Wh/km | AC52: Fastcharge | AD52: 350 km/h | AE52: 350 | AF52: 32.9 | AG52: 35.99 | AH52: £30,000 | AI52: 34463 | AJ52: 34463 | AK52: 1.7E+09 | AL52: 284 | AM52: 1997 | AQ52: Hatchback | AR52: B | AT52: 163 | AU52: 6.13 | AV52: 153 | AW52: 160 | AX52: 36.6 | AY52: 225 | AZ52: 45358
A53: https://ev-database.org/car/2116/Lucid-Air-Pure-RWD | B53: https://ev-database.org/img/auto/Lucid_Air/Lucid_Air-01-thumb.jpg | C53: Air Pure RWD | D53: Available to order since February 2024 | E53: kWh useable battery *| /km of range* | F53: 92 | G53: 153 | I53: 3-Phase Charging | J53: Type 2 CCS | K53: Sedan | L53: 5 | P53: 5 | Q53: 5 | R53: V2 | S53: L | T53: H | U53: 0 - 100 | V53: 4.7 sec | W53: Top Speed | X53: 200 km/h | Y53: Range* | Z53: 565 km | AA53: Efficiency* | AB53: 163 Wh/km | AC53: Fastcharge* | AD53: 940 km/h | AE53: 940 | AF53: 85 | AG53: 88 | AH53: N/A | AI53: 86500 | AJ53: 86500 | AK53: 1.71E+09 | AL53: 190 | AM53: 2116 | AN53: V2XL | AO53: G | AT53: 163 | AU53: 6.13 | AV53: 153 | AW53: 200 | AX53: 92 | AY53: 565 | AZ53: 45477
A54: https://ev-database.org/car/2135/Renault-5-E-Tech-52kWh-150hp | B54: https://ev-database.org/img/auto/Renault_5_ETech/Renault_5_ETech-01-thumb.jpg | C54: 5 E-Tech 52kWh 150hp | D54: Available to order since June 2024 | E54: kWh useable battery | /km of range* | F54: 52 | G54: 101 | I54: 3-Phase Charging | J54: Type 2 CCS | L54: 5 | M54: Heatpump | N54: Towbar possible | O54: 500 | P54: -1 | Q54: V2 | R54: L | S54: H | T54: G | U54: 0 - 100 | V54: 8.0 sec | W54: Top Speed | X54: 150 km/h | Y54: Range* | Z54: 320 km | AA54: Efficiency* | AB54: 163 Wh/km | AC54: Fastcharge | AD54: 400 km/h | AE54: 400 | AF54: 32.9 | AG54: 32.99 | AH54: £26,995 | AI54: 32311 | AJ54: 32311 | AK54: 1.72E+09 | AL54: 1927 | AM54: 2135 | AN54: V2XL | AQ54: Hatchback | AR54: B | AT54: 163 | AU54: 6.13 | AV54: 101 | AW54: 150 | AX54: 52 | AY54: 320 | AZ54: 8
A55: https://ev-database.org/car/2214/Volkswagen-ID3-Pure | B55: https://ev-database.org/img/auto/Volkswagen_ID3_2024/Volkswagen_ID3_2024-01-thumb.jpg | C55: ID.3 Pure | D55: Available to order since May 2024 | E55: kWh useable battery | /km of range* | F55: 52 | G55: 114 | I55: 3-Phase Charging | J55: Type 2 CCS | L55: 5 | M55: Heatpump | P55: -1 | Q55: V2 | R55: L | S55: H | T55: G | U55: 0 - 100 | V55: 8.2 sec | W55: Top Speed | X55: 160 km/h | Y55: Range* | Z55: 320 km | AA55: Efficiency* | AB55: 163 Wh/km | AC55: Fastcharge | AD55: 510 km/h | AE55: 510 | AF55: 36.9 | AG55: 35.99 | AH55: N/A | AI55: 36445 | AJ55: 36445 | AK55: 1.71E+09 | AL55: 544 | AM55: 2214 | AP55: C | AQ55: Hatchback | AT55: 163 | AU55: 6.13 | AV55: 114 | AW55: 160 | AX55: 52 | AY55: 320 | AZ55: 45330
A56: https://ev-database.org/car/1743/Tesla-Model-Y | B56: https://ev-database.org/img/auto/Tesla_Model_Y/Tesla_Model_Y-01-thumb.jpg | C56: Model Y | D56: Available to order since November 2022 | E56: kWh useable battery *| /km of range | F56: 57.5 | G56: 131 | H56: Roofbox possible | I56: 3-Phase Charging | J56: Type 2 CCS | L56: 5 | M56: Heatpump | N56: Towbar possible | O56: 1600 | P56: 5 | Q56: 5 | R56: V2 | S56: L | T56: H | U56: 0 - 100 | V56: 6.9 sec | W56: Top Speed | X56: 217 km/h | Y56: Range | Z56: 350 km | AA56: Efficiency | AB56: 164 Wh/km | AC56: Fastcharge | AD56: 580 km/h | AE56: 580 | AF56: 45.97 | AG56: 45.99 | AH56: N/A | AI56: 45980 | AJ56: 45980 | AK56: 1.67E+09 | AL56: 4623 | AM56: 1743 | AO56: G | AT56: 164 | AU56: 45571 | AV56: 131 | AW56: 217 | AX56: 57.5 | AY56: 350 | AZ56: 45541
A57: https://ev-database.org/car/1793/Opel-Astra-Sports-Tourer-Electric | B57: https://ev-database.org/img/auto/Opel_Astra_Sports_Tourer_Electric/Opel_Astra_Sports_Tourer_Electric-01-thumb.jpg | C57: Astra Sports Tourer Electric | D57: Available to order since October 2023 | E57: kWh useable battery | /km of range | F57: 50.8 | G57: 141 | I57: 3-Phase Charging | J57: Type 2 CCS | L57: 5 | M57: Heatpump | N57: Towbar possible | O57: 0 | P57: -1 | Q57: V2 | R57: L | S57: H | T57: G | U57: 0 - 100 | V57: 9.3 sec | W57: Top Speed | X57: 170 km/h | Y57: Range | Z57: 310 km | AA57: Efficiency | AB57: 164 Wh/km | AC57: Fastcharge | AD57: 500 km/h | AE57: 500 | AF57: 43.49 | AG57: 41.499 | AH57: £39,995 | AI57: 43661 | AJ57: 43661 | AK57: 1.7E+09 | AL57: 190 | AM57: 1793 | AP57: C | AT57: 164 | AU57: 45571 | AV57: 141 | AW57: 170 | AX57: 50.8 | AY57: 310 | AZ57: 45360
A58: https://ev-database.org/car/1816/Jeep-Avenger-Electric | B58: https://ev-database.org/img/auto/Jeep_Avenger/Jeep_Avenger-01-thumb.jpg | C58: Avenger Electric | D58: Available to order since January 2023 | E58: kWh useable battery | /km of range | F58: 50.8 | G58: 127 | I58: 3-Phase Charging | J58: Type 2 CCS | L58: 5 | M58: Heatpump | P58: 3 | Q58: 3 | R58: V2 | S58: L | T58: H | U58: 0 - 100 | V58: 9.0 sec | W58: Top Speed | X58: 150 km/h | Y58: Range | Z58: 310 km | AA58: Efficiency | AB58: 164 Wh/km | AC58: Fastcharge | AD58: 500 km/h | AE58: 500 | AF58: 38.5 | AG58: 39.5 | AH58: £34,800 | AI58: 39340 | AJ58: 39340 | AK58: 1.67E+09 | AL58: 696 | AM58: 1816 | AO58: G | AR58: B | AT58: 164 | AU58: 45571 | AV58: 127 | AW58: 150 | AX58: 50.8 | AY58: 310 | AZ58: 9
A59: https://ev-database.org/car/1829/Hyundai-Kona-Electric-48-kWh | B59: https://ev-database.org/img/auto/Hyundai_Kona_Electric_2024/Hyundai_Kona_Electric_2024-01-thumb.jpg | C59: Kona Electric 48 kWh | D59: Available to order since July 2023 | E59: kWh useable battery | /km of range* | F59: 48.4 | G59: 138 | H59: Roofbox possible | I59: 3-Phase Charging | J59: Type 2 CCS | L59: 5 | M59: Heatpump | N59: Towbar possible | O59: 300 | P59: 4 | Q59: 4 | R59: V2 | S59: L | T59: H | U59: 0 - 100 | V59: 8.8 sec | W59: Top Speed | X59: 160 km/h | Y59: Range* | Z59: 295 km | AA59: Efficiency* | AB59: 164 Wh/km | AC59: Fastcharge* | AD59: 280 km/h | AE59: 280 | AF59: 41.99 | AG59: 39.995 | AH59: £34,995 | AI59: 40743 | AJ59: 40743 | AK59: 1.69E+09 | AL59: 559 | AM59: 1829 | AN59: V2XL | AO59: G | AR59: B | AT59: 164 | AU59: 45571 | AV59: 138 | AW59: 160 | AX59: 48.4 | AY59: 295 | AZ59: 45512
A60: https://ev-database.org/car/1840/Volkswagen-ID7-Pro-S | B60: https://ev-database.org/img/auto/Volkswagen_ID7/Volkswagen_ID7-01-thumb.jpg | C60: ID.7 Pro S | D60: Available to order since June 2024 | E60: kWh useable battery | /km of range* | F60: 86 | G60: 117 | H60: Roofbox possible | I60: 3-Phase Charging | J60: Type 2 CCS | K60: Liftback | L60: 5 | M60: Heatpump | N60: Towbar possible | O60: 1000 | P60: 5 | Q60: 5 | R60: V2 | S60: L | T60: H | U60: 0 - 100 | V60: 6.6 sec | W60: Top Speed | X60: 180 km/h | Y60: Range* | Z60: 525 km | AA60: Efficiency* | AB60: 164 Wh/km | AC60: Fastcharge | AD60: 840 km/h | AE60: 840 | AF60: 58.985 | AG60: 60.99 | AH60: £55,450 | AI60: 61247 | AJ60: 61247 | AK60: 1.72E+09 | AL60: 686 | AM60: 1840 | AO60: G | AT60: 164 | AU60: 45571 | AV60: 117 | AW60: 180 | AX60: 86 | AY60: 525 | AZ60: 45449
A61: https://ev-database.org/car/1945/Fiat-600e | B61: https://ev-database.org/img/auto/Fiat_600e/Fiat_600e-01-thumb.jpg | C61: 600e | D61: Available to order since July 2023 | E61: kWh useable battery | /km of range | F61: 50.8 | G61: 119 | I61: 3-Phase Charging | J61: Type 2 CCS | L61: 5 | M61: Heatpump | P61: -1 | Q61: V2 | R61: L | S61: H | T61: G | U61: 0 - 100 | V61: 9.0 sec | W61: Top Speed | X61: 150 km/h | Y61: Range | Z61: 310 km | AA61: Efficiency | AB61: 164 Wh/km | AC61: Fastcharge | AD61: 460 km/h | AE61: 460 | AF61: 36.49 | AG61: 35.99 | AH61: £32,995 | AI61: 36808 | AJ61: 36808 | AK61: 1.69E+09 | AL61: 468 | AM61: 1945 | AR61: B | AT61: 164 | AU61: 45571 | AV61: 119 | AW61: 150 | AX61: 50.8 | AY61: 310 | AZ61: 9
A62: https://ev-database.org/car/1974/Tesla-Model-Y | B62: https://ev-database.org/img/auto/Tesla_Model_Y/Tesla_Model_Y-01-thumb.jpg | C62: Model Y | D62: Available to order since May 2023 | E62: kWh useable battery *| /km of range | F62: 57.5 | G62: 131 | H62: Roofbox possible | I62: 3-Phase Charging | J62: Type 2 CCS | L62: 5 | M62: Heatpump | N62: Towbar possible | O62: 1600 | P62: 5 | Q62: 5 | R62: V2 | S62: L | T62: H | U62: 0 - 100 | V62: 6.9 sec | W62: Top Speed | X62: 217 km/h | Y62: Range | Z62: 350 km | AA62: Efficiency | AB62: 164 Wh/km | AC62: Fastcharge | AD62: 810 km/h | AE62: 810 | AF62: 45.97 | AG62: 45.99 | AH62: N/A | AI62: 45980 | AJ62: 45980 | AK62: 1.68E+09 | AL62: 1048 | AM62: 1974 | AO62: G | AT62: 164 | AU62: 45571 | AV62: 131 | AW62: 217 | AX62: 57.5 | AY62: 350 | AZ62: 45541
A63: https://ev-database.org/car/1998/Mini-Cooper-SE | B63: https://ev-database.org/img/auto/Mini_Cooper_Electric_2024/Mini_Cooper_Electric_2024-01-thumb.jpg | C63: Cooper SE | D63: Available to order since November 2023 | E63: kWh useable battery | /km of range* | F63: 49.2 | G63: 128 | I63: 3-Phase Charging | J63: Type 2 CCS | L63: 4 | M63: Heatpump | P63: -1 | Q63: V2 | R63: L | S63: H | T63: G | U63: 0 - 100 | V63: 6.7 sec | W63: Top Speed | X63: 170 km/h | Y63: Range* | Z63: 300 km | AA63: Efficiency* | AB63: 164 Wh/km | AC63: Fastcharge | AD63: 430 km/h | AE63: 430 | AF63: 36.9 | AG63: 38.99 | AH63: £34,500 | AI63: 38521 | AJ63: 38521 | AK63: 1.7E+09 | AL63: 588 | AM63: 1998 | AQ63: Hatchback | AR63: B | AT63: 164 | AU63: 45571 | AV63: 128 | AW63: 170 | AX63: 49.2 | AY63: 300 | AZ63: 45479
A64: https://ev-database.org/car/2097/BMW-iX2-eDrive20 | B64: https://ev-database.org/img/auto/BMW_iX2_2024/BMW_iX2_2024-01-thumb.jpg | C64: iX2 eDrive20 | D64: Available to order since January 2024 | E64: kWh useable battery | /km of range* | F64: 64.7 | G64: 134 | H64: Roofbox possible | I64: 3-Phase Charging | J64: Type 2 CCS | L64: 5 | M64: Heatpump | N64: Towbar possible | O64: 750 | P64: -1 | Q64: V2 | R64: L | S64: H | T64: G | U64: 0 - 100 | V64: 8.6 sec | W64: Top Speed | X64: 170 km/h | Y64: Range* | Z64: 395 km | AA64: Efficiency* | AB64: 164 Wh/km | AC64: Fastcharge | AD64: 530 km/h | AE64: 530 | AF64: 49.4 | AG64: 49.976 | AH64: £51,615 | AI64: 52911 | AJ64: 52911 | AK64: 1.7E+09 | AL64: 493 | AM64: 2097 | AP64: C | AT64: 164 | AU64: 45571 | AV64: 134 | AW64: 170 | AX64: 64.7 | AY64: 395 | AZ64: 45451
A65: https://ev-database.org/car/2118/Volkswagen-ID7-Tourer-Pro | B65: https://ev-database.org/img/auto/Volkswagen_ID7_Tourer/Volkswagen_ID7_Tourer-01-thumb.jpg | C65: ID.7 Tourer Pro | D65: Available to order since March 2024 | E65: kWh useable battery | /km of range | F65: 77 | G65: 123 | H65: Roofbox possible | I65: 3-Phase Charging | J65: Type 2 CCS | L65: 5 | M65: Heatpump | N65: Towbar possible | O65: 1000 | P65: 5 | Q65: 5 | R65: V2 | S65: L | T65: H | U65: 0 - 100 | V65: 6.6 sec | W65: Top Speed | X65: 180 km/h | Y65: Range | Z65: 470 km | AA65: Efficiency | AB65: 164 Wh/km | AC65: Fastcharge | AD65: 730 km/h | AE65: 730 | AF65: 54.795 | AG65: 58.99 | AH65: £52,240 | AI65: 57953 | AJ65: 57953 | AK65: 1.71E+09 | AL65: 435 | AM65: 2118 | AO65: G | AT65: 164 | AU65: 45571 | AV65: 123 | AW65: 180 | AX65: 77 | AY65: 470 | AZ65: 45449
A66: https://ev-database.org/car/2185/Alfa-Romeo-Junior-Elettrica-54-kWh-Veloce | B66: https://ev-database.org/img/auto/Alfa_Romeo_Junior/Alfa_Romeo_Junior-01-thumb.jpg | C66: Junior Elettrica 54 kWh Veloce | D66: Available to order since June 2024 | E66: kWh useable battery | /km of range* | F66: 50.8 | G66: 156 | I66: 3-Phase Charging | J66: Type 2 CCS | L66: 5 | P66: -1 | Q66: V2 | R66: L | S66: H | T66: G | U66: 0 - 100 | V66: 6.0 sec | W66: Top Speed | X66: 200 km/h | Y66: Range* | Z66: 310 km | AA66: Efficiency* | AB66: 164 Wh/km | AC66: Fastcharge | AD66: 500 km/h | AE66: 500 | AF66: 48.5 | AG66: 48 | AH66: £42,295 | AI66: 48379 | AJ66: 48379 | AK66: 1.72E+09 | AL66: 281 | AM66: 2185 | AR66: B | AT66: 164 | AU66: 45571 | AV66: 156 | AW66: 200 | AX66: 50.8 | AY66: 310 | AZ66: 6
A67: https://ev-database.org/car/2213/Volkswagen-ID3-Pro | B67: https://ev-database.org/img/auto/Volkswagen_ID3_2024/Volkswagen_ID3_2024-01-thumb.jpg | C67: ID.3 Pro | D67: Available to order since May 2024 | E67: kWh useable battery | /km of range* | F67: 59 | G67: 112 | I67: 3-Phase Charging | J67: Type 2 CCS | L67: 5 | M67: Heatpump | N67: Towbar possible | O67: 0 | P67: -1 | Q67: V2 | R67: L | S67: H | T67: G | U67: 0 - 100 | V67: 7.6 sec | W67: Top Speed | X67: 160 km/h | Y67: Range* | Z67: 360 km | AA67: Efficiency* | AB67: 164 Wh/km | AC67: Fastcharge | AD67: 600 km/h | AE67: 600 | AF67: 39.995 | AG67: 39.99 | AH67: £35,700 | AI67: 40346 | AJ67: 40346 | AK67: 1.71E+09 | AL67: 680 | AM67: 2213 | AP67: C | AQ67: Hatchback | AT67: 164 | AU67: 45571 | AV67: 112 | AW67: 160 | AX67: 59 | AY67: 360 | AZ67: 45450
A68: https://ev-database.org/car/2225/Polestar-2-Standard-Range-Single-Motor | B68: https://ev-database.org/img/auto/Polestar_2_2024/Polestar_2_2024-01-thumb.jpg | C68: 2 Standard Range Single Motor | D68: Available to order since June 2024 | E68: kWh useable battery *| /km of range* | F68: 68 | G68: 117 | H68: Roofbox possible | I68: 3-Phase Charging | J68: Type 2 CCS | K68: Liftback | L68: 5 | M68: Heatpump | N68: Towbar possible | O68: 1500 | P68: 5 | Q68: 5 | R68: V2 | S68: L | T68: H | U68: 0 - 100 | V68: 6.4 sec | W68: Top Speed | X68: 205 km/h | Y68: Range* | Z68: 415 km | AA68: Efficiency* | AB68: 164 Wh/km | AC68: Fastcharge | AD68: 640 km/h | AE68: 640 | AF68: 48.99 | AG68: 44.95 | AH68: £44,950 | AI68: 48544 | AJ68: 48544 | AK68: 1.72E+09 | AL68: 344 | AM68: 2225 | AO68: G | AT68: 164 | AU68: 45571 | AV68: 117 | AW68: 205 | AX68: 68 | AY68: 415 | AZ68: 45388
A69: https://ev-database.org/car/2233/CUPRA-Born-170-kW---59-kWh | B69: https://ev-database.org/img/auto/Cupra_el-Born/Cupra_el-Born-01-thumb.jpg | C69: Born 170 kW - 59 kWh | D69: Available to order since June 2024 | E69: kWh useable battery | /km of range* | F69: 59 | G69: 111 | I69: 3-Phase Charging | J69: Type 2 CCS | L69: 5 | M69: Heatpump | P69: 5 | Q69: 5 | R69: V2 | S69: L | T69: H | U69: 0 - 100 | V69: 6.7 sec | W69: Top Speed | X69: 160 km/h | Y69: Range* | Z69: 360 km | AA69: Efficiency* | AB69: 164 Wh/km | AC69: Fastcharge | AD69: 630 km/h | AE69: 630 | AF69: 41.45 | AG69: 37.49 | AH69: £35,495 | AI69: 39919 | AJ69: 39919 | AK69: 1.72E+09 | AL69: 487 | AM69: 2233 | AO69: G | AP69: C | AQ69: Hatchback | AT69: 164 | AU69: 45571 | AV69: 111 | AW69: 160 | AX69: 59 | AY69: 360 | AZ69: 45479
A70: https://ev-database.org/car/1404/Tesla-Model-S-Dual-Motor | B70: https://ev-database.org/img/auto/Tesla_Model_S_2021/Tesla_Model_S_2021-01-thumb.jpg | C70: Model S Dual Motor | D70: Available to order since January 2023 | E70: kWh useable battery *| /km of range* | F70: 95 | G70: 166 | H70: Roofbox possible | I70: 3-Phase Charging | J70: Type 2 CCS | K70: Liftback | L70: 5 | M70: Heatpump | N70: Towbar possible | O70: 1600 | P70: 5 | Q70: 5 | R70: V2 | S70: L | T70: H | U70: 0 - 100 | V70: 3.2 sec | W70: Top Speed | X70: 250 km/h | Y70: Range | Z70: 575 km | AA70: Efficiency | AB70: 165 Wh/km | AC70: Fastcharge* | AD70: 800 km/h | AE70: 800 | AF70: 93.97 | AG70: 93.99 | AH70: * £85,000 | AI70: 95236 | AJ70: 95236 | AK70: 1.67E+09 | AL70: 1645 | AM70: 1404 | AO70: G | AT70: 165 | AU70: 45449 | AV70: 166 | AW70: 250 | AX70: 95 | AY70: 575 | AZ70: 45325
A71: https://ev-database.org/car/2119/Volkswagen-ID7-Tourer-Pro-S | B71: https://ev-database.org/img/auto/Volkswagen_ID7_Tourer/Volkswagen_ID7_Tourer-01-thumb.jpg | C71: ID.7 Tourer Pro S | D71: Available to order since June 2024 | E71: kWh useable battery | /km of range* | F71: 86 | G71: 119 | H71: Roofbox possible | I71: 3-Phase Charging | J71: Type 2 CCS | L71: 5 | M71: Heatpump | N71: Towbar possible | O71: 1000 | P71: 5 | Q71: 5 | R71: V2 | S71: L | T71: H | U71: 0 - 100 | V71: 6.7 sec | W71: Top Speed | X71: 180 km/h | Y71: Range* | Z71: 520 km | AA71: Efficiency* | AB71: 165 Wh/km | AC71: Fastcharge | AD71: 840 km/h | AE71: 840 | AF71: 59.785 | AG71: 61.99 | AH71: £56,140 | AI71: 62112 | AJ71: 62112 | AK71: 1.72E+09 | AL71: 728 | AM71: 2119 | AO71: G | AT71: 165 | AU71: 45449 | AV71: 119 | AW71: 180 | AX71: 86 | AY71: 520 | AZ71: 45479
A72: https://ev-database.org/car/2186/Tesla-Model-Y-Long-Range-RWD | B72: https://ev-database.org/img/auto/Tesla_Model_Y/Tesla_Model_Y-01-thumb.jpg | C72: Model Y Long Range RWD | D72: Available to order since April 2024 | E72: kWh useable battery *| /km of range | F72: 75 | G72: 113 | H72: Roofbox possible | I72: 3-Phase Charging | J72: Type 2 CCS | L72: 5 | M72: Heatpump | N72: Towbar possible | O72: 1600 | P72: 5 | Q72: 5 | R72: V2 | S72: L | T72: H | U72: 0 - 100 | V72: 5.9 sec | W72: Top Speed | X72: 217 km/h | Y72: Range | Z72: 455 km | AA72: Efficiency | AB72: 165 Wh/km | AC72: Fastcharge | AD72: 700 km/h | AE72: 700 | AF72: 49.97 | AG72: 49.99 | AH72: £46,990 | AI72: 51332 | AJ72: 51332 | AK72: 1.71E+09 | AL72: 1910 | AM72: 2186 | AO72: G | AT72: 165 | AU72: 45449 | AV72: 113 | AW72: 217 | AX72: 75 | AY72: 455 | AZ72: 45540
A73: https://ev-database.org/car/3031/Skoda-Elroq-50 | B73: https://ev-database.org/img/auto/Skoda_Elroq_2024/Skoda_Elroq_2024-01-thumb.jpg | C73: Elroq 50 | D73: Available to order since October 2024 | E73: kWh useable battery | /km of range* | F73: 52 | G73: 112 | H73: Roofbox possible | I73: 3-Phase Charging | J73: Type 2 CCS | L73: 5 | N73: Towbar possible | O73: 1000 | P73: -1 | Q73: V2 | R73: L | S73: H | T73: G | U73: 0 - 100 | V73: 9.0 sec | W73: Top Speed | X73: 160 km/h | Y73: Range* | Z73: 315 km | AA73: Efficiency* | AB73: 165 Wh/km | AC73: Fastcharge | AD73: 500 km/h | AE73: 500 | AF73: 34.56 | AG73: 34.99 | AH73: £31,500 | AI73: 35258 | AJ73: 35258 | AK73: 1.73E+09 | AL73: 429 | AM73: 3031 | AP73: C | AT73: 165 | AU73: 45449 | AV73: 112 | AW73: 160 | AX73: 52 | AY73: 315 | AZ73: 9
A74: https://ev-database.org/car/1656/Nissan-Leaf | B74: https://ev-database.org/img/auto/Nissan_Leaf_2022/Nissan_Leaf_2022-01-thumb.jpg | C74: Leaf | D74: Available to order since March 2022 | E74: kWh useable battery | /km of range* | F74: 39 | G74: 146 | H74: Roofbox possible | L74: 5 | M74: Heatpump | P74: 5 | Q74: 5 | R74: V2 | S74: L | T74: H | U74: 0 - 100 | V74: 7.9 sec | W74: Top Speed | X74: 144 km/h | Y74: Range* | Z74: 235 km | AA74: Efficiency* | AB74: 166 Wh/km | AC74: Fastcharge | AD74: 230 km/h | AE74: 230 | AF74: 35.9 | AG74: N/A | AH74: £28,495 | AI74: 34334 | AJ74: 34334 | AK74: 1.65E+09 | AL74: 936 | AM74: 1656 | AO74: G | AP74: C | AQ74: Hatchback | AT74: 166 | AU74: 45328 | AV74: 146 | AW74: 144 | AX74: 39 | AY74: 235 | AZ74: 45542
A75: https://ev-database.org/car/1996/BMW-iX1-eDrive20 | B75: https://ev-database.org/img/auto/BMW_iX1_2022/BMW_iX1_2022-01-thumb.jpg | C75: iX1 eDrive20 | D75: Available to order since September 2023 | E75: kWh useable battery | /km of range* | F75: 64.7 | G75: 127 | H75: Roofbox possible | I75: 3-Phase Charging | J75: Type 2 CCS | L75: 5 | M75: Heatpump | N75: Towbar possible | O75: 750 | P75: -1 | Q75: V2 | R75: L | S75: H | T75: G | U75: 0 - 100 | V75: 8.3 sec | W75: Top Speed | X75: 170 km/h | Y75: Range* | Z75: 390 km | AA75: Efficiency* | AB75: 166 Wh/km | AC75: Fastcharge | AD75: 520 km/h | AE75: 520 | AF75: 47.9 | AG75: 48.316 | AH75: £45,465 | AI75: 49500 | AJ75: 49500 | AK75: 1.69E+09 | AL75: 1070 | AM75: 1996 | AP75: C | AT75: 166 | AU75: 45328 | AV75: 127 | AW75: 170 | AX75: 64.7 | AY75: 390 | AZ75: 45359
A76: https://ev-database.org/car/2098/Porsche-Taycan | B76: https://ev-database.org/img/auto/Porsche_Taycan_2024/Porsche_Taycan_2024-01-thumb.jpg | C76: Taycan | D76: Available to order since February 2024 | E76: kWh useable battery | /km of range* | F76: 82.3 | G76: 207 | H76: Roofbox possible | I76: 3-Phase Charging | J76: Type 2 CCS | K76: Sedan | L76: 5 | M76: Heatpump | P76: -1 | Q76: V2 | R76: L | S76: H | T76: G | U76: 0 - 100 | V76: 4.8 sec | W76: Top Speed | X76: 230 km/h | Y76: Range* | Z76: 495 km | AA76: Efficiency* | AB76: 166 Wh/km | AC76: Fastcharge | AD76: 1090 km/h | AE76: 1090 | AF76: 101.5 | AG76: 107 | AH76: £86,500 | AI76: 100000 | AJ76: 102658 | AK76: 1.71E+09 | AL76: 308 | AM76: 2098 | AT76: 166 | AU76: 45328 | AV76: 207 | AW76: 230 | AX76: 82.3 | AY76: 495 | AZ76: 45508
A77: https://ev-database.org/car/2200/BMW-i4-xDrive40 | B77: https://ev-database.org/img/auto/BMW_i4_2024/BMW_i4_2024-01-thumb.jpg | C77: i4 xDrive40 | D77: Available to order since June 2024 | E77: kWh useable battery | /km of range* | F77: 81.3 | G77: 137 | H77: Roofbox possible | I77: 3-Phase Charging | J77: Type 2 CCS | K77: Liftback | L77: 5 | M77: Heatpump | N77: Towbar possible | O77: 1600 | P77: -1 | Q77: V2 | R77: L | S77: H | T77: G | U77: 0 - 100 | V77: 5.1 sec | W77: Top Speed | X77: 200 km/h | Y77: Range* | Z77: 490 km | AA77: Efficiency* | AB77: 166 Wh/km | AC77: Fastcharge | AD77: 760 km/h | AE77: 760 | AF77: 63 | AG77: 65.899 | AH77: * £63,000 | AI77: 67116 | AJ77: 67116 | AK77: 1.72E+09 | AL77: 377 | AM77: 2200 | AT77: 166 | AU77: 45328 | AV77: 137 | AW77: 200 | AX77: 81.3 | AY77: 490 | AZ77: 45296
A78: https://ev-database.org/car/2226/Polestar-2-Long-Range-Single-Motor | B78: https://ev-database.org/img/auto/Polestar_2_2024/Polestar_2_2024-01-thumb.jpg | C78: 2 Long Range Single Motor | D78: Available to order since June 2024 | E78: kWh useable battery | /km of range* | F78: 79 | G78: 112 | H78: Roofbox possible | I78: 3-Phase Charging | J78: Type 2 CCS | K78: Liftback | L78: 5 | M78: Heatpump | N78: Towbar possible | O78: 1500 | P78: 5 | Q78: 5 | R78: V2 | S78: L | T78: H | U78: 0 - 100 | V78: 6.2 sec | W78: Top Speed | X78: 205 km/h | Y78: Range* | Z78: 475 km | AA78: Efficiency* | AB78: 166 Wh/km | AC78: Fastcharge | AD78: 710 km/h | AE78: 710 | AF78: 52.69 | AG78: 51.2 | AH78: £48,950 | AI78: 53394 | AJ78: 53394 | AK78: 1.72E+09 | AL78: 684 | AM78: 2226 | AO78: G | AT78: 166 | AU78: 45328 | AV78: 112 | AW78: 205 | AX78: 79 | AY78: 475 | AZ78: 45328
A79: https://ev-database.org/car/1821/XPENG-P7-RWD-Long-Range | B79: https://ev-database.org/img/auto/XPENG_P7/XPENG_P7-01-thumb.jpg | C79: P7 RWD Long Range | D79: Available to order since February 2023 | E79: kWh useable battery | /km of range* | F79: 82.7 | G79: 102 | I79: 3-Phase Charging | J79: Type 2 CCS | K79: Sedan | L79: 5 | M79: Heatpump | P79: 5 | Q79: 5 | R79: V2 | S79: L | T79: H | U79: 0 - 100 | V79: 6.7 sec | W79: Top Speed | X79: 200 km/h | Y79: Range* | Z79: 495 km | AA79: Efficiency* | AB79: 167 Wh/km | AC79: Fastcharge | AD79: 800 km/h | AE79: 800 | AF79: 49.6 | AG79: 51.188 | AH79: N/A | AI79: 50394 | AJ79: 50394 | AK79: 1.68E+09 | AL79: 291 | AM79: 1821 | AN79: V2XL | AO79: G | AT79: 167 | AU79: 5.99 | AV79: 102 | AW79: 200 | AX79: 82.7 | AY79: 495 | AZ79: 45479
A80: https://ev-database.org/car/2026/Skoda-Enyaq-Coupe-RS | B80: https://ev-database.org/img/auto/Skoda_Enyaq_Coupe_RS_iV_2022/Skoda_Enyaq_Coupe_RS_iV_2022-01-thumb.jpg | C80: Enyaq Coupe RS | D80: Available to order since September 2023 | E80: kWh useable battery | /km of range | F80: 77 | G80: 137 | H80: Roofbox possible | I80: 3-Phase Charging | J80: Type 2 CCS | L80: 5 | M80: Heatpump | N80: Towbar possible | O80: 1200 | P80: 5 | Q80: 5 | R80: V2 | S80: L | T80: H | U80: 0 - 100 | V80: 5.5 sec | W80: Top Speed | X80: 180 km/h | Y80: Range | Z80: 460 km | AA80: Efficiency | AB80: 167 Wh/km | AC80: Fastcharge | AD80: 690 km/h | AE80: 690 | AF80: 63.3 | AG80: 62.69 | AH80: £54,820 | AI80: 63011 | AJ80: 63011 | AK80: 1.69E+09 | AL80: 209 | AM80: 2026 | AO80: G | AP80: C | AT80: 167 | AU80: 5.99 | AV80: 137 | AW80: 180 | AX80: 77 | AY80: 460 | AZ80: 45417
A81: https://ev-database.org/car/2190/Mini-Aceman-E | B81: https://ev-database.org/img/auto/Mini_Aceman_Electric_2024/Mini_Aceman_Electric_2024-01-thumb.jpg | C81: Aceman E | D81: Available to order since June 2024 | E81: kWh useable battery | /km of range* | F81: 38.5 | G81: 160 | I81: 3-Phase Charging | J81: Type 2 CCS | L81: 5 | M81: Heatpump | N81: Towbar possible | O81: 750 | P81: -1 | Q81: V2 | R81: L | S81: H | T81: G | U81: 0 - 100 | V81: 7.9 sec | W81: Top Speed | X81: 160 km/h | Y81: Range* | Z81: 230 km | AA81: Efficiency* | AB81: 167 Wh/km | AC81: Fastcharge | AD81: 340 km/h | AE81: 340 | AF81: 34.9 | AG81: 38.99 | AH81: £31,800 | AI81: 36820 | AJ81: 36820 | AK81: 1.72E+09 | AL81: 244 | AM81: 2190 | AR81: B | AT81: 167 | AU81: 5.99 | AV81: 160 | AW81: 160 | AX81: 38.5 | AY81: 230 | AZ81: 45542
A82: https://ev-database.org/car/2234/CUPRA-Born-170-kW---77-kWh | B82: https://ev-database.org/img/auto/Cupra_el-Born/Cupra_el-Born-01-thumb.jpg | C82: Born 170 kW - 77 kWh | D82: Available to order since June 2024 | E82: kWh useable battery | /km of range* | F82: 77 | G82: 102 | I82: 3-Phase Charging | J82: Type 2 CCS | L82: 5 | M82: Heatpump | P82: 5 | Q82: 5 | R82: V2 | S82: L | T82: H | U82: 0 - 100 | V82: 7.0 sec | W82: Top Speed | X82: 160 km/h | Y82: Range* | Z82: 460 km | AA82: Efficiency* | AB82: 167 Wh/km | AC82: Fastcharge | AD82: 710 km/h | AE82: 710 | AF82: 47.25 | AG82: 44.99 | AH82: £41,795 | AI82: 46768 | AJ82: 46768 | AK82: 1.72E+09 | AL82: 858 | AM82: 2234 | AO82: G | AP82: C | AQ82: Hatchback | AT82: 167 | AU82: 5.99 | AV82: 102 | AW82: 160 | AX82: 77 | AY82: 460 | AZ82: 7
A83: https://ev-database.org/car/1316/Lucid-Air-Grand-Touring | B83: https://ev-database.org/img/auto/Lucid_Air/Lucid_Air-01-thumb.jpg | C83: Air Grand Touring | D83: Available to order since February 2023 | E83: kWh useable battery *| /km of range* | F83: 112 | G83: 196 | I83: 3-Phase Charging | J83: Type 2 CCS | K83: Sedan | L83: 5 | P83: 5 | Q83: 5 | R83: V2 | S83: L | T83: H | U83: 0 - 100 | V83: 3.0 sec | W83: Top Speed | X83: 270 km/h | Y83: Range* | Z83: 665 km | AA83: Efficiency* | AB83: 168 Wh/km | AC83: Fastcharge | AD83: 1030 km/h | AE83: 1030 | AF83: 129 | AG83: 132 | AH83: N/A | AI83: 100000 | AJ83: 130500 | AK83: 1.68E+09 | AL83: 738 | AM83: 1316 | AN83: V2XL | AO83: G | AT83: 168 | AU83: 5.95 | AV83: 196 | AW83: 270 | AX83: 112 | AY83: 665 | AZ83: 3
A84: https://ev-database.org/car/1666/Kia-Niro-EV | B84: https://ev-database.org/img/auto/Kia-NiroEV-2022/Kia-NiroEV-2022-01-thumb.jpg | C84: Niro EV | D84: Available to order since June 2022 | E84: kWh useable battery | /km of range | F84: 64.8 | G84: 111 | H84: Roofbox possible | I84: 3-Phase Charging | J84: Type 2 CCS | L84: 5 | M84: Heatpump | N84: Towbar possible | O84: 750 | P84: 4 | Q84: 4 | R84: V2 | S84: L | T84: H | U84: 0 - 100 | V84: 7.8 sec | W84: Top Speed | X84: 167 km/h | Y84: Range | Z84: 385 km | AA84: Efficiency | AB84: 168 Wh/km | AC84: Fastcharge | AD84: 390 km/h | AE84: 390 | AF84: 45.69 | AG84: 39.995 | AH84: £37,295 | AI84: 42858 | AJ84: 42858 | AK84: 1.65E+09 | AL84: 1884 | AM84: 1666 | AN84: V2XL | AO84: G | AP84: C | AT84: 168 | AU84: 5.95 | AV84: 111 | AW84: 167 | AX84: 64.8 | AY84: 385 | AZ84: 45511
A85: https://ev-database.org/car/1719/Hyundai-IONIQ-6-Long-Range-AWD | B85: https://ev-database.org/img/auto/Hyundai_IONIQ6_2022/Hyundai_IONIQ6_2022-01-thumb.jpg | C85: IONIQ 6 Long Range AWD | D85: Available to order since November 2022 | E85: kWh useable battery *| /km of range* | F85: 74 | G85: 135 | H85: Roofbox possible | I85: 3-Phase Charging | J85: Type 2 CCS | K85: Sedan | L85: 5 | M85: Heatpump | N85: Towbar possible | O85: 1500 | P85: 5 | Q85: 5 | R85: V2 | S85: L | T85: H | U85: 0 - 100 | V85: 5.1 sec | W85: Top Speed | X85: 185 km/h | Y85: Range* | Z85: 440 km | AA85: Efficiency* | AB85: 168 Wh/km | AC85: Fastcharge | AD85: 1150 km/h | AE85: 1150 | AF85: 61.1 | AG85: 59.395 | AH85: £50,540 | AI85: 59538 | AJ85: 59538 | AK85: 1.67E+09 | AL85: 677 | AM85: 1719 | AN85: V2XL | AO85: G | AT85: 168 | AU85: 5.95 | AV85: 135 | AW85: 185 | AX85: 74 | AY85: 440 | AZ85: 45296
A86: https://ev-database.org/car/1830/Hyundai-Kona-Electric-65-kWh | B86: https://ev-database.org/img/auto/Hyundai_Kona_Electric_2024/Hyundai_Kona_Electric_2024-01-thumb.jpg | C86: Kona Electric 65 kWh | D86: Available to order since July 2023 | E86: kWh useable battery | /km of range | F86: 65.4 | G86: 116 | H86: Roofbox possible | I86: 3-Phase Charging | J86: Type 2 CCS | L86: 5 | M86: Heatpump | N86: Towbar possible | O86: 750 | P86: 4 | Q86: 4 | R86: V2 | S86: L | T86: H | U86: 0 - 100 | V86: 7.8 sec | W86: Top Speed | X86: 170 km/h | Y86: Range | Z86: 390 km | AA86: Efficiency | AB86: 168 Wh/km | AC86: Fastcharge* | AD86: 480 km/h | AE86: 480 | AF86: 47.19 | AG86: 43.995 | AH86: £38,595 | AI86: 45189 | AJ86: 45189 | AK86: 1.69E+09 | AL86: 1655 | AM86: 1830 | AN86: V2XL | AO86: G | AR86: B | AT86: 168 | AU86: 5.95 | AV86: 116 | AW86: 170 | AX86: 65.4 | AY86: 390 | AZ86: 45511
A87: https://ev-database.org/car/1903/Abarth-500e-Hatchback | B87: https://ev-database.org/img/auto/Abarth_500e_Hatchback/Abarth_500e_Hatchback-01-thumb.jpg | C87: 500e Hatchback | D87: Available to order since May 2023 | E87: kWh useable battery | /km of range* | F87: 37.8 | G87: 169 | I87: 3-Phase Charging | J87: Type 2 CCS | L87: 4 | P87: -1 | Q87: V2 | R87: L | S87: H | T87: G | U87: 0 - 100 | V87: 7.0 sec | W87: Top Speed | X87: 155 km/h | Y87: Range* | Z87: 225 km | AA87: Efficiency* | AB87: 168 Wh/km | AC87: Fastcharge | AD87: 370 km/h | AE87: 370 | AF87: 37.99 | AG87: 36.49 | AH87: £34,195 | AI87: 37934 | AJ87: 37934 | AK87: 1.68E+09 | AL87: 186 | AM87: 1903 | AQ87: Hatchback | AR87: B | AT87: 168 | AU87: 5.95 | AV87: 169 | AW87: 155 | AX87: 37.8 | AY87: 225 | AZ87: 7
A88: https://ev-database.org/car/1904/Abarth-500e-Convertible | B88: https://ev-database.org/img/auto/Abarth_500e_Convertible/Abarth_500e_Convertible-01-thumb.jpg | C88: 500e Convertible | D88: Available to order since May 2023 | E88: kWh useable battery | /km of range* | F88: 37.8 | G88: 182 | I88: 3-Phase Charging | J88: Type 2 CCS | L88: 4 | P88: -1 | Q88: V2 | R88: L | S88: H | T88: G | U88: 0 - 100 | V88: 7.0 sec | W88: Top Speed | X88: 155 km/h | Y88: Range* | Z88: 225 km | AA88: Efficiency* | AB88: 168 Wh/km | AC88: Fastcharge | AD88: 370 km/h | AE88: 370 | AF88: 40.99 | AG88: 38.99 | AH88: £37,195 | AI88: 40918 | AJ88: 40918 | AK88: 1.68E+09 | AL88: 81 | AM88: 1904 | AQ88: Hatchback | AR88: B | AT88: 168 | AU88: 5.95 | AV88: 182 | AW88: 155 | AX88: 37.8 | AY88: 225 | AZ88: 7
A89: https://ev-database.org/car/1984/Mercedes-Benz-EQA-250 | B89: https://ev-database.org/img/auto/Mercedes_EQA_2024/Mercedes_EQA_2024-01-thumb.jpg | C89: EQA 250 | D89: Available to order since October 2023 | E89: kWh useable battery | /km of range* | F89: 66.5 | G89: 129 | H89: Roofbox possible | I89: 3-Phase Charging | J89: Type 2 CCS | L89: 5 | M89: Heatpump | N89: Towbar possible | O89: 1500 | P89: -1 | Q89: V2 | R89: L | S89: H | T89: G | U89: 0 - 100 | V89: 8.6 sec | W89: Top Speed | X89: 160 km/h | Y89: Range* | Z89: 395 km | AA89: Efficiency* | AB89: 168 Wh/km | AC89: Fastcharge* | AD89: 570 km/h | AE89: 570 | AF89: 50.777 | AG89: N/A | AH89: N/A | AI89: 50777 | AJ89: 50777 | AK89: 1.7E+09 | AL89: 1087 | AM89: 1984 | AP89: C | AT89: 168 | AU89: 5.95 | AV89: 129 | AW89: 160 | AX89: 66.5 | AY89: 395 | AZ89: 45451
A90: https://ev-database.org/car/1985/Mercedes-Benz-EQA-250plus | B90: https://ev-database.org/img/auto/Mercedes_EQA_2024/Mercedes_EQA_2024-01-thumb.jpg | C90: EQA 250+ | D90: Available to order since October 2023 | E90: kWh useable battery | /km of range | F90: 70.5 | G90: 129 | H90: Roofbox possible | I90: 3-Phase Charging | J90: Type 2 CCS | L90: 5 | M90: Heatpump | N90: Towbar possible | O90: 1500 | P90: -1 | Q90: V2 | R90: L | S90: H | T90: G | U90: 0 - 100 | V90: 8.6 sec | W90: Top Speed | X90: 160 km/h | Y90: Range | Z90: 420 km | AA90: Efficiency | AB90: 168 Wh/km | AC90: Fastcharge | AD90: 500 km/h | AE90: 500 | AF90: 52.205 | AG90: 52.546 | AH90: £49,750 | AI90: 53987 | AJ90: 53987 | AK90: 1.7E+09 | AL90: 645 | AM90: 1985 | AP90: C | AT90: 168 | AU90: 5.95 | AV90: 129 | AW90: 160 | AX90: 70.5 | AY90: 420 | AZ90: 45451
A91: https://ev-database.org/car/2040/BMW-iX2-xDrive30 | B91: https://ev-database.org/img/auto/BMW_iX2_2024/BMW_iX2_2024-01-thumb.jpg | C91: iX2 xDrive30 | D91: Available to order since October 2023 | E91: kWh useable battery | /km of range | F91: 64.7 | G91: 157 | H91: Roofbox possible | I91: 3-Phase Charging | J91: Type 2 CCS | L91: 5 | M91: Heatpump | N91: Towbar possible | O91: 1200 | P91: -1 | Q91: V2 | R91: L | S91: H | T91: G | U91: 0 - 100 | V91: 5.6 sec | W91: Top Speed | X91: 180 km/h | Y91: Range | Z91: 385 km | AA91: Efficiency | AB91: 168 Wh/km | AC91: Fastcharge | AD91: 520 km/h | AE91: 520 | AF91: 56.5 | AG91: 59.35 | AH91: £57,445 | AI91: 60637 | AJ91: 60637 | AK91: 1.7E+09 | AL91: 508 | AM91: 2040 | AP91: C | AT91: 168 | AU91: 5.95 | AV91: 157 | AW91: 180 | AX91: 64.7 | AY91: 385 | AZ91: 45448
A92: https://ev-database.org/car/2100/Porsche-Taycan-4S | B92: https://ev-database.org/img/auto/Porsche_Taycan_2024/Porsche_Taycan_2024-01-thumb.jpg | C92: Taycan 4S | D92: Available to order since February 2024 | E92: kWh useable battery | /km of range* | F92: 82.3 | G92: 244 | H92: Roofbox possible | I92: 3-Phase Charging | J92: Type 2 CCS | K92: Sedan | L92: 5 | M92: Heatpump | P92: -1 | Q92: V2 | R92: L | S92: H | T92: G | U92: 0 - 100 | V92: 3.7 sec | W92: Top Speed | X92: 250 km/h | Y92: Range* | Z92: 490 km | AA92: Efficiency* | AB92: 168 Wh/km | AC92: Fastcharge | AD92: 1080 km/h | AE92: 1080 | AF92: 120.9 | AG92: 126.8 | AH92: £95,900 | AI92: 100000 | AJ92: 119328 | AK92: 1.71E+09 | AL92: 136 | AM92: 2100 | AT92: 168 | AU92: 5.95 | AV92: 244 | AW92: 250 | AX92: 82.3 | AY92: 490 | AZ92: 45476
A93: https://ev-database.org/car/2240/Ford-Capri-Standard-Range-RWD | B93: https://ev-database.org/img/auto/Ford_Capri_2024/Ford_Capri_2024-01-thumb.jpg | C93: Capri Standard Range RWD | D93: Available to order since October 2024 | E93: kWh useable battery | /km of range* | F93: 52 | G93: 152 | H93: Roofbox possible | I93: 3-Phase Charging | J93: Type 2 CCS | K93: Liftback | L93: 5 | M93: Heatpump | N93: Towbar possible | O93: 1000 | P93: -1 | Q93: V2 | R93: L | S93: H | T93: G | U93: 0 - 100 | V93: 9.0 sec | W93: Top Speed | X93: 160 km/h | Y93: Range* | Z93: 310 km | AA93: Efficiency* | AB93: 168 Wh/km | AC93: Fastcharge | AD93: 480 km/h | AE93: 480 | AF93: 44.95 | AG93: 43.35 | AH93: £45,875 | AI93: 47018 | AJ93: 47018 | AK93: 1.73E+09 | AL93: 102 | AM93: 2240 | AT93: 168 | AU93: 5.95 | AV93: 152 | AW93: 160 | AX93: 52 | AY93: 310 | AZ93: 9
A94: https://ev-database.org/car/2250/Skoda-Enyaq-50 | B94: https://ev-database.org/img/auto/Skoda_Enyaq_iV_2020/Skoda_Enyaq_iV_2020-01-thumb.jpg | C94: Enyaq 50 | D94: Available to order since June 2024 | E94: kWh useable battery | /km of range* | F94: 52 | G94: 138 | H94: Roofbox possible | I94: 3-Phase Charging | J94: Type 2 CCS | L94: 5 | N94: Towbar possible | O94: 1000 | P94: 5 | Q94: 5 | R94: V2 | S94: L | T94: H | U94: 0 - 100 | V94: 9.1 sec | W94: Top Speed | X94: 160 km/h | Y94: Range* | Z94: 310 km | AA94: Efficiency* | AB94: 168 Wh/km | AC94: Fastcharge | AD94: 500 km/h | AE94: 500 | AF94: N/A | AG94: 42.99 | AH94: £36,970 | AI94: 42752 | AJ94: 42752 | AK94: 1.72E+09 | AL94: 234 | AM94: 2250 | AO94: G | AP94: C | AT94: 168 | AU94: 5.95 | AV94: 138 | AW94: 160 | AX94: 52 | AY94: 310 | AZ94: 45300
A95: https://ev-database.org/car/2251/Fiat-Grande-Panda | B95: https://ev-database.org/img/auto/Fiat_Grande_Panda_2024/Fiat_Grande_Panda_2024-01-thumb.jpg | C95: Grande Panda | D95: Available to order since October 2024 | E95: kWh useable battery | /km of range* | F95: 43.8 | G95: 97 | I95: 3-Phase Charging | J95: Type 2 CCS | L95: 5 | N95: Towbar possible | O95: 550 | P95: -1 | Q95: V2 | R95: L | S95: H | T95: G | U95: 0 - 100 | V95: 11.0 sec | W95: Top Speed | X95: 132 km/h | Y95: Range* | Z95: 260 km | AA95: Efficiency* | AB95: 168 Wh/km | AC95: Fastcharge | AD95: 340 km/h | AE95: 340 | AF95: * €24,000 | AG95: 25.99 | AH95: * £22,000 | AI95: 25096 | AJ95: 25096 | AK95: 1.73E+09 | AL95: 702 | AM95: 2251 | AQ95: Hatchback | AR95: B | AT95: 168 | AU95: 5.95 | AV95: 97 | AW95: 132 | AX95: 43.8 | AY95: 260 | AZ95: 11
A96: https://ev-database.org/car/2268/Alpine-A290-Electric-180-hp | B96: https://ev-database.org/img/auto/Alpine_A290_2024/Alpine_A290_2024-01-thumb.jpg | C96: A290 Electric 180 hp | D96: Available to order since July 2024 | E96: kWh useable battery | /km of range* | F96: 52 | G96: 124 | I96: 3-Phase Charging | J96: Type 2 CCS | L96: 5 | M96: Heatpump | N96: Towbar possible | O96: 500 | P96: -1 | Q96: V2 | R96: L | S96: H | T96: G | U96: 0 - 100 | V96: 7.4 sec | W96: Top Speed | X96: 160 km/h | Y96: Range* | Z96: 310 km | AA96: Efficiency* | AB96: 168 Wh/km | AC96: Fastcharge | AD96: 390 km/h | AE96: 390 | AF96: 38.7 | AG96: 38.8 | AH96: * £33,000 | AI96: 38483 | AJ96: 38483 | AK96: 1.72E+09 | AL96: 164 | AM96: 2268 | AN96: V2XL | AQ96: Hatchback | AR96: B | AT96: 168 | AU96: 5.95 | AV96: 124 | AW96: 160 | AX96: 52 | AY96: 310 | AZ96: 45389
A97: https://ev-database.org/car/2272/Audi-A6-Avant-e-tron-performance | B97: https://ev-database.org/img/auto/Audi_A6_Avant_etron_2024/Audi_A6_Avant_etron_2024-01-thumb.jpg | C97: A6 Avant e-tron performance | D97: Available to order since September 2024 | E97: kWh useable battery | /km of range* | F97: 94.9 | G97: 140 | H97: Roofbox possible | I97: 3-Phase Charging | J97: Type 2 CCS | L97: 5 | M97: Heatpump | N97: Towbar possible | O97: 2100 | P97: -1 | Q97: V2 | R97: L | S97: H | T97: G | U97: 0 - 100 | V97: 5.4 sec | W97: Top Speed | X97: 210 km/h | Y97: Range* | Z97: 565 km | AA97: Efficiency* | AB97: 168 Wh/km | AC97: Fastcharge | AD97: 1130 km/h | AE97: 1130 | AF97: 77.25 | AG97: 77.49 | AH97: £71,700 | AI97: 79065 | AJ97: 79065 | AK97: 1.73E+09 | AL97: 803 | AM97: 2272 | AT97: 168 | AU97: 5.95 | AV97: 140 | AW97: 210 | AX97: 94.9 | AY97: 565 | AZ97: 45387
A98: https://ev-database.org/car/3060/Porsche-Taycan-4 | B98: https://ev-database.org/img/auto/Porsche_Taycan_2024/Porsche_Taycan_2024-01-thumb.jpg | C98: Taycan 4 | D98: Available to order since November 2024 | E98: kWh useable battery | /km of range* | F98: 82.3 | G98: 221 | H98: Roofbox possible | I98: 3-Phase Charging | J98: Type 2 CCS | K98: Sedan | L98: 5 | M98: Heatpump | P98: -1 | Q98: V2 | R98: L | S98: H | T98: G | U98: 0 - 100 | V98: 4.6 sec | W98: Top Speed | X98: 230 km/h | Y98: Range* | Z98: 490 km | AA98: Efficiency* | AB98: 168 Wh/km | AC98: Fastcharge | AD98: 1080 km/h | AE98: 1080 | AF98: 106.2 | AG98: 110.433 | AH98: N/A | AI98: 100000 | AJ98: 108316 | AK98: 1.73E+09 | AL98: 172 | AM98: 3060 | AT98: 168 | AU98: 5.95 | AV98: 221 | AW98: 230 | AX98: 82.3 | AY98: 490 | AZ98: 45447
A99: https://ev-database.org/car/1619/Tesla-Model-Y-Long-Range-Dual-Motor | B99: https://ev-database.org/img/auto/Tesla_Model_Y/Tesla_Model_Y-01-thumb.jpg | C99: Model Y Long Range Dual Motor | D99: Available to order since February 2022 | E99: kWh useable battery *| /km of range* | F99: 75 | G99: 126 | H99: Roofbox possible | I99: 3-Phase Charging | J99: Type 2 CCS | L99: 7 | M99: Heatpump | N99: Towbar possible | O99: 1600 | P99: 5 | Q99: 5 | R99: V2 | S99: L | T99: H | U99: 0 - 100 | V99: 5.0 sec | W99: Top Speed | X99: 217 km/h | Y99: Range* | Z99: 445 km | AA99: Efficiency* | AB99: 169 Wh/km | AC99: Fastcharge | AD99: 690 km/h | AE99: 690 | AF99: 55.97 | AG99: 52.99 | AH99: £51,990 | AI99: 56249 | AJ99: 56249 | AK99: 1.64E+09 | AL99: 3901 | AM99: 1619 | AO99: G | AT99: 169 | AU99: 5.92 | AV99: 126 | AW99: 217 | AX99: 75 | AY99: 445 | AZ99: 5
A100: https://ev-database.org/car/1707/MG-MG4-Electric-51-kWh | B100: https://ev-database.org/img/auto/MG_MG4_Electric_2022/MG_MG4_Electric_2022-01-thumb.jpg | C100: MG4 Electric 51 kWh | D100: Available to order since October 2022 | E100: kWh useable battery | /km of range* | F100: 50.8 | G100: 109 | J100: Type 2 CCS | L100: 5 | N100: Towbar possible | O100: 500 | P100: 5 | Q100: 5 | R100: V2 | S100: L | T100: H | U100: 0 - 100 | V100: 7.7 sec | W100: Top Speed | X100: 160 km/h | Y100: Range* | Z100: 300 km | AA100: Efficiency* | AB100: 169 Wh/km | AC100: Fastcharge | AD100: 380 km/h | AE100: 380 | AF100: 34.99 | AG100: 32.285 | AH100: £26,995 | AI100: 32773 | AJ100: 32773 | AK100: 1.66E+09 | AL100: 887 | AM100: 1707 | AN100: V2XL | AO100: G | AP100: C | AQ100: Hatchback | AT100: 169 | AU100: 5.92 | AV100: 109 | AW100: 160 | AX100: 50.8 | AY100: 300 | AZ100: 45480
...

Sheet Electricity emissions
A1: 1. Subregion Output Emission Rates (eGRID2022) | T1: 2. Subregion Resource Mix (eGRID2022)
A2: eGRID subregion acronym | B2: eGRID subregion name | C2: Total output emission rates | J2: Non-baseload output emission rates | Q2: Grid Gross Loss (%) | T2: eGRID subregion acronym | U2: eGRID subregion name | V2: Nameplate Capacity (MW) | W2: Net Generation (MWh) | X2: Generation Resource Mix (percent)*
C3: lb/MWh | J3: lb/MWh | X3: Coal | Y3: Oil | Z3: Gas | AA3: Other Fossil | AB3: Nuclear | AC3: Hydro | AD3: Biomass | AE3: Wind | AF3: Solar | AG3: Geo- thermal | AH3: Other unknown/ purchased fuel
C4: CO2 | D4: CH4 | E4: N2O | F4: CO2e | G4: Annual NOX | H4: Ozone Season NOX | I4: SO2 | J4: CO2 | K4: CH4 | L4: N2O | M4: CO2e | N4: Annual NOX | O4: Ozone Season NOX | P4: SO2 | T4: AKGD | U4: ASCC Alaska Grid | V4: 2.17 | W4: 5,016,815 | X4: 14.5% | Y4: 8.8% | Z4: 62.3% | AA4: 0.0% | AB4: 0.0% | AC4: 11.5% | AD4: 0.8% | AE4: 2.1% | AF4: 0.0% | AG4: 0.0% | AH4: 0.0%
A5: AKGD | B5: ASCC Alaska Grid | C5: 1,052.1 | D5: 88 | E5: 12 | F5: 1,057.8 | G5: 45296 | H5: 45387 | I5: 423 | J5: 1,224.5 | K5: 123 | L5: 17 | M5: 1,232.5 | N5: 7.0 | O5: 45450 | P5: 583 | Q5: 5.0% | T5: AKMS | U5: ASCC Miscellaneous | V5: 920 | W5: 1,677,313 | X5: 0.0% | Y5: 24.1% | Z5: 6.3% | AA5: 0.0% | AB5: 0.0% | AC5: 67.7% | AD5: 0.0% | AE5: 2.0% | AF5: 0.0% | AG5: 0.0% | AH5: 0.0%
A6: AKMS | B6: ASCC Miscellaneous | C6: 495.8 | D6: 23 | E6: 4 | F6: 497.6 | G6: 45542 | H6: 45358 | I6: 680 | J6: 1,587.9 | K6: 69 | L6: 12 | M6: 1,593.3 | N6: 45407 | O6: 45467 | P6: 2185 | Q6: 5.0% | T6: AZNM | U6: WECC Southwest | V6: 52.133 | W6: 170,369,549 | X6: 15.7% | Y6: 0.0% | Z6: 44.3% | AA6: 0.0% | AB6: 18.7% | AC6: 3.1% | AD6: 0.3% | AE6: 7.4% | AF6: 7.0% | AG6: 3.4% | AH6: 0.0%
A7: AZNM | B7: WECC Southwest | C7: 776.0 | D7: 51 | E7: 7 | F7: 779.4 | G7: 0.4 | H7: 0.4 | I7: 121 | J7: 1,205.2 | K7: 65 | L7: 9 | M7: 1,209.5 | N7: 0.7 | O7: 0.7 | P7: 162 | Q7: 5.1% | T7: CAMX | U7: WECC California | V7: 93.348 | W7: 209,353,986 | X7: 2.7% | Y7: 0.1% | Z7: 46.2% | AA7: 0.8% | AB7: 8.4% | AC7: 7.9% | AD7: 2.4% | AE7: 7.2% | AF7: 20.4% | AG7: 3.9% | AH7: 0.0%
A8: CAMX | B8: WECC California | C8: 497.4 | D8: 30 | E8: 4 | F8: 499.3 | G8: 0.5 | H8: 0.4 | I8: 30 | J8: 1,055.0 | K8: 49 | L8: 6 | M8: 1,058.0 | N8: 0.8 | O8: 0.7 | P8: 55 | Q8: 5.1% | T8: ERCT | U8: ERCOT All | V8: 139.101 | W8: 458,259,386 | X8: 15.5% | Y8: 0.1% | Z8: 46.8% | AA8: 0.4% | AB8: 9.1% | AC8: 0.1% | AD8: 0.2% | AE8: 23.0% | AF8: 4.7% | AG8: 0.0% | AH8: 0.1%
A9: ERCT | B9: ERCOT All | C9: 771.1 | D9: 49 | E9: 7 | F9: 774.3 | G9: 0.5 | H9: 0.5 | I9: 407 | J9: 1,194.9 | K9: 67 | L9: 9 | M9: 1,199.2 | N9: 0.9 | O9: 0.9 | P9: 665 | Q9: 5.1% | T9: FRCC | U9: FRCC All | V9: 70.81 | W9: 250,233,811 | X9: 6.1% | Y9: 0.5% | Z9: 74.4% | AA9: 0.6% | AB9: 12.3% | AC9: 0.1% | AD9: 1.4% | AE9: 0.0% | AF9: 4.3% | AG9: 0.0% | AH9: 0.3%
A10: FRCC | B10: FRCC All | C10: 813.8 | D10: 48 | E10: 6 | F10: 816.9 | G10: 0.3 | H10: 0.3 | I10: 142 | J10: 1,044.4 | K10: 56 | L10: 7 | M10: 1,048.0 | N10: 0.4 | O10: 0.4 | P10: 208 | Q10: 5.1% | T10: HIMS | U10: HICC Miscellaneous | V10: 1.045 | W10: 2,708,213 | X10: 0.0% | Y10: 64.4% | Z10: 0.0% | AA10: 0.0% | AB10: 0.0% | AC10: 4.1% | AD10: 3.6% | AE10: 12.6% | AF10: 5.5% | AG10: 7.7% | AH10: 2.1%
A11: HIMS | B11: HICC Miscellaneous | C11: 1,155.5 | D11: 124 | E11: 19 | F11: 1,163.1 | G11: 45329 | H11: 45358 | I11: 3069 | J11: 1,619.2 | K11: 157 | L11: 25 | M11: 1,629.6 | N11: 45393 | O11: 45546 | P11: 4074 | Q11: 5.4% | T11: HIOA | U11: HICC Oahu | V11: 2.298 | W11: 6,595,979 | X11: 9.8% | Y11: 74.5% | Z11: 0.0% | AA11: 3.1% | AB11: 0.0% | AC11: 0.0% | AD11: 2.7% | AE11: 3.8% | AF11: 6.1% | AG11: 0.0% | AH11: 0.0%
A12: HIOA | B12: HICC Oahu | C12: 1,575.4 | D12: 163 | E12: 25 | F12: 1,586.9 | G12: 45538 | H12: 45476 | I12: 6353 | J12: 1,810.3 | K12: 177 | L12: 28 | M12: 1,822.9 | N12: 45386 | O12: 45326 | P12: 7330 | Q12: 5.4% | T12: MROE | U12: MRO East | V12: 8.453 | W12: 22,864,489 | X12: 45.8% | Y12: 0.7% | Z12: 37.8% | AA12: 0.1% | AB12: 0.0% | AC12: 4.8% | AD12: 3.7% | AE12: 3.8% | AF12: 3.2% | AG12: 0.0% | AH12: 0.0%
A13: MROE | B13: MRO East | C13: 1,479.6 | D13: 133 | E13: 19 | F13: 1,488.7 | G13: 1.0 | H13: 1.0 | I13: 306 | J13: 1,672.9 | K13: 147 | L13: 21 | M13: 1,682.8 | N13: 45292 | O13: 45323 | P13: 334 | Q13: 5.1% | T13: MROW | U13: MRO West | V13: 76.84 | W13: 251,623,837 | X13: 38.0% | Y13: 0.1% | Z13: 8.3% | AA13: 0.1% | AB13: 8.1% | AC13: 3.9% | AD13: 0.7% | AE13: 39.8% | AF13: 1.0% | AG13: 0.0% | AH13: 0.1%
A14: MROW | B14: MRO West | C14: 936.5 | D14: 102 | E14: 15 | F14: 943.4 | G14: 0.8 | H14: 0.9 | I14: 907 | J14: 1,794.7 | K14: 183 | L14: 26 | M14: 1,807.0 | N14: 45444 | O14: 45444 | P14: 1640 | Q14: 5.1% | T14: NEWE | U14: NPCC New England | V14: 38.88 | W14: 105,455,877 | X14: 0.3% | Y14: 1.8% | Z14: 52.7% | AA14: 1.6% | AB14: 26.0% | AC14: 5.9% | AD14: 4.5% | AE14: 3.8% | AF14: 3.3% | AG14: 0.0% | AH14: 0.1%
A15: NEWE | B15: NPCC New England | C15: 536.4 | D15: 63 | E15: 8 | F15: 540.5 | G15: 0.3 | H15: 0.3 | I15: 122 | J15: 923.3 | K15: 73 | L15: 10 | M15: 928.1 | N15: 0.5 | O15: 0.3 | P15: 249 | Q15: 5.1% | T15: NWPP | U15: WECC Northwest | V15: 80.186 | W15: 290,045,161 | X15: 18.2% | Y15: 0.2% | Z15: 18.9% | AA15: 0.2% | AB15: 3.4% | AC15: 44.0% | AD15: 1.0% | AE15: 10.8% | AF15: 2.5% | AG15: 0.6% | AH15: 0.1%
A16: NWPP | B16: WECC Northwest | C16: 602.1 | D16: 56 | E16: 8 | F16: 605.9 | G16: 0.5 | H16: 0.5 | I16: 318 | J16: 1,515.7 | K16: 134 | L16: 19 | M16: 1,524.7 | N16: 45413 | O16: 45413 | P16: 790 | Q16: 5.1% | T16: NYCW | U16: NPCC NYC/Westchester | V16: 12.79 | W16: 32,721,381 | X16: 0.0% | Y16: 2.3% | Z16: 96.6% | AA16: 0.6% | AB16: 0.0% | AC16: 0.0% | AD16: 0.5% | AE16: 0.0% | AF16: 0.1% | AG16: 0.0% | AH16: 0.0%
A17: NYCW | B17: NPCC NYC/Westchester | C17: 885.2 | D17: 23 | E17: 3 | F17: 886.6 | G17: 0.2 | H17: 0.2 | I17: 28 | J17: 971.8 | K17: 21 | L17: 2 | M17: 973.0 | N17: 0.3 | O17: 0.3 | P17: 21 | Q17: 5.1% | T17: NYLI | U17: NPCC Long Island | V17: 5.885 | W17: 10,828,139 | X17: 0.0% | Y17: 6.4% | Z17: 82.7% | AA17: 4.8% | AB17: 0.0% | AC17: 0.0% | AD17: 3.9% | AE17: 0.0% | AF17: 2.3% | AG17: 0.0% | AH17: 0.0%
A18: NYLI | B18: NPCC Long Island | C18: 1,200.7 | D18: 135 | E18: 18 | F18: 1,209.3 | G18: 0.9 | H18: 0.9 | I18: 474 | J18: 1,316.7 | K18: 39 | L18: 5 | M18: 1,319.1 | N18: 0.9 | O18: 0.8 | P18: 654 | Q18: 5.1% | T18: NYUP | U18: NPCC Upstate NY | V18: 26.053 | W18: 87,177,697 | X18: 0.0% | Y18: 0.5% | Z18: 29.2% | AA18: 0.3% | AB18: 30.8% | AC18: 30.9% | AD18: 1.5% | AE18: 5.2% | AF18: 1.6% | AG18: 0.0% | AH18: 0.0%
A19: NYUP | B19: NPCC Upstate NY | C19: 274.6 | D19: 15 | E19: 2 | F19: 275.4 | G19: 0.1 | H19: 0.1 | I19: 43 | J19: 920.1 | K19: 43 | L19: 5 | M19: 922.5 | N19: 0.5 | O19: 0.3 | P19: 189 | Q19: 5.1% | T19: PRMS | U19: Puerto Rico Miscellaneous | V19: 6.405 | W19: 17,762,020 | X19: 16.7% | Y19: 48.6% | Z19: 32.3% | AA19: 0.0% | AB19: 0.0% | AC19: 0.0% | AD19: 0.0% | AE19: 0.9% | AF19: 1.6% | AG19: 0.0% | AH19: 0.0%
A20: PRMS | B20: Puerto Rico Miscellaneous | C20: 1,593.5 | D20: 87 | E20: 14 | F20: 1,599.9 | G20: 45294 | H20: 45294 | I20: 4262 | J20: 1,670.9 | K20: 74 | L20: 13 | M20: 1,676.7 | N20: 45415 | O20: 45415 | P20: 5578 | Q20: 0.0% | T20: RFCE | U20: RFC East | V20: 78.447 | W20: 289,058,252 | X20: 8.8% | Y20: 0.2% | Z20: 50.2% | AA20: 0.7% | AB20: 36.2% | AC20: 1.1% | AD20: 0.9% | AE20: 1.0% | AF20: 0.9% | AG20: 0.0% | AH20: 0.0%
A21: RFCE | B21: RFC East | C21: 657.4 | D21: 45 | E21: 6 | F21: 660.3 | G21: 0.3 | H21: 0.2 | I21: 302 | J21: 1,278.7 | K21: 97 | L21: 13 | M21: 1,285.1 | N21: 0.7 | O21: 0.6 | P21: 773 | Q21: 5.1% | T21: RFCM | U21: RFC Michigan | V21: 31.06 | W21: 93,807,524 | X21: 36.6% | Y21: 1.6% | Z21: 38.5% | AA21: 1.4% | AB21: 10.0% | AC21: 0.0% | AD21: 1.6% | AE21: 9.4% | AF21: 0.9% | AG21: 0.0% | AH21: 0.0%
A22: RFCM | B22: RFC Michigan | C22: 1,216.4 | D22: 116 | E22: 16 | F22: 1,224.2 | G22: 0.6 | H22: 0.6 | I22: 931 | J22: 1,597.3 | K22: 149 | L22: 21 | M22: 1,607.4 | N22: 0.9 | O22: 0.8 | P22: 1413 | Q22: 5.1% | T22: RFCW | U22: RFC West | V22: 140.293 | W22: 535,522,392 | X22: 31.4% | Y22: 0.3% | Z22: 32.0% | AA22: 0.7% | AB22: 27.6% | AC22: 1.0% | AD22: 0.4% | AE22: 6.0% | AF22: 0.5% | AG22: 0.0% | AH22: 0.1%
A23: RFCW | B23: RFC West | C23: 1,000.1 | D23: 87 | E23: 12 | F23: 1,005.9 | G23: 0.5 | H23: 0.4 | I23: 620 | J23: 1,843.6 | K23: 178 | L23: 26 | M23: 1,855.7 | N23: 45292 | O23: 0.9 | P23: 1180 | Q23: 5.1% | T23: RMPA | U23: WECC Rockies | V23: 23.744 | W23: 67,125,368 | X23: 36.6% | Y23: 0.0% | Z23: 23.6% | AA23: 0.0% | AB23: 0.0% | AC23: 8.4% | AD23: 0.2% | AE23: 27.5% | AF23: 3.5% | AG23: 0.0% | AH23: 0.1%
A24: RMPA | B24: WECC Rockies | C24: 1,124.9 | D24: 101 | E24: 14 | F24: 1,131.7 | G24: 0.6 | H24: 0.6 | I24: 348 | J24: 1,676.4 | K24: 129 | L24: 18 | M24: 1,685.1 | N24: 0.9 | O24: 0.9 | P24: 430 | Q24: 5.1% | T24: SPNO | U24: SPP North | V24: 26.861 | W24: 78,559,613 | X24: 37.1% | Y24: 0.0% | Z24: 10.9% | AA24: 0.0% | AB24: 11.4% | AC24: 0.2% | AD24: 0.1% | AE24: 40.3% | AF24: 0.1% | AG24: 0.0% | AH24: 0.0%
A25: SPNO | B25: SPP North | C25: 952.6 | D25: 100 | E25: 14 | F25: 959.4 | G25: 0.5 | H25: 0.6 | I25: 160 | J25: 1,943.0 | K25: 198 | L25: 29 | M25: 1,956.5 | N25: 45323 | O25: 45323 | P25: 325 | Q25: 5.1% | T25: SPSO | U25: SPP South | V25: 57.781 | W25: 155,729,281 | X25: 23.4% | Y25: 1.2% | Z25: 38.8% | AA25: 0.1% | AB25: 0.0% | AC25: 3.2% | AD25: 1.4% | AE25: 31.4% | AF25: 0.4% | AG25: 0.0% | AH25: 0.1%
A26: SPSO | B26: SPP South | C26: 970.4 | D26: 72 | E26: 10 | F26: 975.3 | G26: 0.8 | H26: 0.8 | I26: 862 | J26: 1,528.2 | K26: 105 | L26: 15 | M26: 1,535.2 | N26: 45352 | O26: 45352 | P26: 1291 | Q26: 5.1% | T26: SRMV | U26: SERC Mississippi Valley | V26: 47.214 | W26: 183,054,493 | X26: 10.5% | Y26: 0.8% | Z26: 63.4% | AA26: 1.2% | AB26: 21.4% | AC26: 1.2% | AD26: 1.0% | AE26: 0.0% | AF26: 0.5% | AG26: 0.0% | AH26: 0.2%
A27: SRMV | B27: SERC Mississippi Valley | C27: 801.0 | D27: 40 | E27: 6 | F27: 803.7 | G27: 0.5 | H27: 0.5 | I27: 602 | J27: 1,220.7 | K27: 73 | L27: 10 | M27: 1,225.6 | N27: 0.9 | O27: 0.9 | P27: 1407 | Q27: 5.1% | T27: SRMW | U27: SERC Midwest | V27: 33.72 | W27: 118,737,335 | X27: 59.1% | Y27: 0.1% | Z27: 11.8% | AA27: 0.1% | AB27: 15.2% | AC27: 1.3% | AD27: 0.1% | AE27: 10.9% | AF27: 1.2% | AG27: 0.0% | AH27: 0.2%
A28: SRMW | B28: SERC Midwest | C28: 1,369.9 | D28: 151 | E28: 22 | F28: 1,380.2 | G28: 1.0 | H28: 0.7 | I28: 2410 | J28: 1,808.6 | K28: 186 | L28: 27 | M28: 1,821.2 | N28: 45383 | O28: 45292 | P28: 3244 | Q28: 5.1% | T28: SRSO | U28: SERC South | V28: 72.05 | W28: 257,187,544 | X28: 17.7% | Y28: 0.2% | Z28: 53.8% | AA28: 0.0% | AB28: 18.3% | AC28: 2.9% | AD28: 3.9% | AE28: 0.0% | AF28: 3.2% | AG28: 0.0% | AH28: 0.0%
A29: SRSO | B29: SERC South | C29: 893.3 | D29: 64 | E29: 9 | F29: 897.7 | G29: 0.4 | H29: 0.4 | I29: 151 | J29: 1,354.8 | K29: 92 | L29: 13 | M29: 1,361.1 | N29: 0.8 | O29: 0.6 | P29: 309 | Q29: 5.1% | T29: SRTV | U29: SERC Tennessee Valley | V29: 57.331 | W29: 214,916,301 | X29: 29.2% | Y29: 0.1% | Z29: 30.4% | AA29: 0.0% | AB29: 30.2% | AC29: 8.7% | AD29: 0.7% | AE29: 0.0% | AF29: 0.7% | AG29: 0.0% | AH29: 0.0%
A30: SRTV | B30: SERC Tennessee Valley | C30: 933.1 | D30: 82 | E30: 12 | F30: 938.6 | G30: 0.4 | H30: 0.4 | I30: 537 | J30: 1,671.0 | K30: 152 | L30: 22 | M30: 1,681.3 | N30: 0.7 | O30: 0.6 | P30: 968 | Q30: 5.1% | T30: SRVC | U30: SERC Virginia/Carolina | V30: 95.391 | W30: 323,748,776 | X30: 11.0% | Y30: 0.3% | Z30: 40.2% | AA30: 0.2% | AB30: 38.7% | AC30: 1.2% | AD30: 2.3% | AE30: 0.5% | AF30: 5.5% | AG30: 0.0% | AH30: 0.1%
A31: SRVC | B31: SERC Virginia/Carolina | C31: 623.0 | D31: 47 | E31: 7 | F31: 625.9 | G31: 0.3 | H31: 0.3 | I31: 157 | J31: 1,308.8 | K31: 99 | L31: 14 | M31: 1,315.1 | N31: 0.7 | O31: 0.7 | P31: 351 | Q31: 5.1% | T31: U.S. | V31: 1,281,209 | W31: 4,240,140,533 | X31: 19.7% | Y31: 0.7% | Z31: 39.8% | AA31: 0.5% | AB31: 18.2% | AC31: 5.9% | AD31: 1.2% | AE31: 10.2% | AF31: 3.4% | AG31: 0.4% | AH31: 0.1%
A32: U.S. | C32: 823.1 | D32: 66 | E32: 9 | F32: 827.5 | G32: 0.5 | H32: 0.5 | I32: 473 | J32: 1,405.3 | K32: 107 | L32: 15 | M32: 1,412.5 | N32: 1.0 | O32: 0.9 | P32: 838 | Q32: 5.1% | T32: *percentages may not sum to 100 due to rounding
A35: 1 lb/MWh = (0.45359237 Kg) / (1,000 KWh) = 0.00045359237 Kg/KWh | F35: =SUMPRODUCT(C5:C31,W4:W30) -> 3490301475905
A36: 0.00045359237
A38: CO2 Ib / MWh | B38: 823.1
A39: CO2 Kg / KWh | B39: =B38*A36 -> 0.37335188 | D39: THIS IS WAY TOO HIGH

Sheet Gasoline and electricity
A1: Date | B1: Month | C1: Year | D1: Weekly U.S. Regular Conventional Retail Gasoline Prices (Dollars per Gallon) | E1: Monthly U.S. Regular Conventional Retail Gasoline Prices (Dollars per Gallon) | F1: Date(simple) | H1: Monthly U.S. Regular Conventional Retail Gasoline Prices (Dollars per Gallon) | I1: Date(simple) | K1: DATE | L1: Average Price: Electricity per Kilowatt-Hour in U.S. City Average
A2: 33105 | B2: =MONTH(A2) -> 8 | C2: =YEAR(A2) -> 1990 | D2: 1.191 | E2: =AVERAGEIFS($D$2:$D$1789,$B$2:$B$1789,B2,$C$2:$C$1789,C2) -> 1.218 | F2: =DATE(C2,B2,1) -> 33086 | H2: 1.218 | I2: 33086 | K2: 28795 | L2: 0.046
A3: 33112 | B3: =MONTH(A3) -> 8 | C3: =YEAR(A3) -> 1990 | D3: 1.245 | E3: =AVERAGEIFS($D$2:$D$1789,$B$2:$B$1789,B3,$C$2:$C$1789,C3) -> 1.218 | F3: =DATE(C3,B3,1) -> 33086 | H3: 1.258 | I3: 33117 | K3: 28825 | L3: 0.046
A4: 33119 | B4: =MONTH(A4) -> 9 | C4: =YEAR(A4) -> 1990 | D4: 1.242 | E4: =AVERAGEIFS($D$2:$D$1789,$B$2:$B$1789,B4,$C$2:$C$1789,C4) -> 1.258 | F4: =DATE(C4,B4,1) -> 33117 | H4: 1.3354 | I4: 33147 | K4: 28856 | L4: 0.046
A5: 33126 | B5: =MONTH(A5) -> 9 | C5: =YEAR(A5) -> 1990 | D5: 1.252 | E5: =AVERAGEIFS($D$2:$D$1789,$B$2:$B$1789,B5,$C$2:$C$1789,C5) -> 1.258 | F5: =DATE(C5,B5,1) -> 33117 | H5: 1.324 | I5: 33178 | K5: 28887 | L5: 0.047
A6: 33133 | B6: =MONTH(A6) -> 9 | C6: =YEAR(A6) -> 1990 | D6: 1.266 | E6: =AVERAGEIFS($D$2:$D$1789,$B$2:$B$1789,B6,$C$2:$C$1789,C6) -> 1.258 | F6: =DATE(C6,B6,1) -> 33117 | H6: 1.341 | I6: 33208 | K6: 28915 | L6: 0.047
A7: 33140 | B7: =MONTH(A7) -> 9 | C7: =YEAR(A7) -> 1990 | D7: 1.272 | E7: =AVERAGEIFS($D$2:$D$1789,$B$2:$B$1789,B7,$C$2:$C$1789,C7) -> 1.258 | F7: =DATE(C7,B7,1) -> 33117 | H7: 1.18 | I7: 33239 | K7: 28946 | L7: 0.048
A8: 33147 | B8: =MONTH(A8) -> 10 | C8: =YEAR(A8) -> 1990 | D8: 1.321 | E8: =AVERAGEIFS($D$2:$D$1789,$B$2:$B$1789,B8,$C$2:$C$1789,C8) -> 1.3354 | F8: =DATE(C8,B8,1) -> 33147 | H8: 1.09425 | I8: 33270 | K8: 28976 | L8: 0.049
A9: 33154 | B9: =MONTH(A9) -> 10 | C9: =YEAR(A9) -> 1990 | D9: 1.333 | E9: =AVERAGEIFS($D$2:$D$1789,$B$2:$B$1789,B9,$C$2:$C$1789,C9) -> 1.3354 | F9: =DATE(C9,B9,1) -> 33147 | H9: 1.04 | I9: 33298 | K9: 29007 | L9: 0.052
A10: 33161 | B10: =MONTH(A10) -> 10 | C10: =YEAR(A10) -> 1990 | D10: 1.339 | E10: =AVERAGEIFS($D$2:$D$1789,$B$2:$B$1789,B10,$C$2:$C$1789,C10) -> 1.3354 | F10: =DATE(C10,B10,1) -> 33147 | H10: 1.0762 | I10: 33329 | K10: 29037 | L10: 0.053
A11: 33168 | B11: =MONTH(A11) -> 10 | C11: =YEAR(A11) -> 1990 | D11: 1.345 | E11: =AVERAGEIFS($D$2:$D$1789,$B$2:$B$1789,B11,$C$2:$C$1789,C11) -> 1.3354 | F11: =DATE(C11,B11,1) -> 33147 | H11: 1.12575 | I11: 33359 | K11: 29068 | L11: 0.053
A12: 33175 | B12: =MONTH(A12) -> 10 | C12: =YEAR(A12) -> 1990 | D12: 1.339 | E12: =AVERAGEIFS($D$2:$D$1789,$B$2:$B$1789,B12,$C$2:$C$1789,C12) -> 1.3354 | F12: =DATE(C12,B12,1) -> 33147 | H12: 1.12825 | I12: 33390 | K12: 29099 | L12: 0.053
A13: 33182 | B13: =MONTH(A13) -> 11 | C13: =YEAR(A13) -> 1990 | D13: 1.334 | E13: =AVERAGEIFS($D$2:$D$1789,$B$2:$B$1789,B13,$C$2:$C$1789,C13) -> 1.324 | F13: =DATE(C13,B13,1) -> 33178 | H13: 1.0956 | I13: 33420 | K13: 29129 | L13: 0.053
... A17: 33210 | B17: =MONTH(A17) -> 12 | C17: =YEAR(A17) -> 1990 | D17: 1.341 | E17: =AVERAGEIFS($D$2:$D$1789,$B$2:$B$1789,B17,$C$2:$C$1789,C17) -> 1.341 | F17: =DATE(C17,B17,1) -> 33208 | H17: 1.099 | I17: 33543 | K17: 29252 | L17: 0.055
A18: 33217 | B18: =MONTH(A18) -> 12 | C18: =YEAR(A18) -> 1990 | E18: =AVERAGEIFS($D$2:$D$1789,$B$2:$B$1789,B18,$C$2:$C$1789,C18) -> 1.341 | F18: =DATE(C18,B18,1) -> 33208 | H18: 1.0762 | I18: 33573 | K18: 29281 | L18: 0.056
A19: 33224 | B19: =MONTH(A19) -> 12 | C19: =YEAR(A19) -> 1990 | E19: =AVERAGEIFS($D$2:$D$1789,$B$2:$B$1789,B19,$C$2:$C$1789,C19) -> 1.341 | F19: =DATE(C19,B19,1) -> 33208 | H19: 1.022 | I19: 33604 | K19: 29312 | L19: 0.056
A20: 33231 | B20: =MONTH(A20) -> 12 | C20: =YEAR(A20) -> 1990 | E20: =AVERAGEIFS($D$2:$D$1789,$B$2:$B$1789,B20,$C$2:$C$1789,C20) -> 1.341 | F20: =DATE(C20,B20,1) -> 33208 | H20: 1.006 | I20: 33635 | K20: 29342 | L20: 0.058
A21: 33238 | B21: =MONTH(A21) -> 12 | C21: =YEAR(A21) -> 1990 | E21: =AVERAGEIFS($D$2:$D$1789,$B$2:$B$1789,B21,$C$2:$C$1789,C21) -> 1.341 | F21: =DATE(C21,B21,1) -> 33208 | H21: 1.0126 | I21: 33664 | K21: 29373 | L21: 0.063
A22: 33245 | B22: =MONTH(A22) -> 1 | C22: =YEAR(A22) -> 1991 | E22: =AVERAGEIFS($D$2:$D$1789,$B$2:$B$1789,B22,$C$2:$C$1789,C22) -> 1.18 | F22: =DATE(C22,B22,1) -> 33239 | H22: 1.05175 | I22: 33695 | K22: 29403 | L22: 0.064
A23: 33252 | B23: =MONTH(A23) -> 1 | C23: =YEAR(A23) -> 1991 | E23: =AVERAGEIFS($D$2:$D$1789,$B$2:$B$1789,B23,$C$2:$C$1789,C23) -> 1.18 | F23: =DATE(C23,B23,1) -> 33239 | H23: 1.10725 | I23: 33725 | K23: 29434 | L23: 0.064
A24: 33259 | B24: =MONTH(A24) -> 1 | C24: =YEAR(A24) -> 1991 | D24: 1.192 | E24: =AVERAGEIFS($D$2:$D$1789,$B$2:$B$1789,B24,$C$2:$C$1789,C24) -> 1.18 | F24: =DATE(C24,B24,1) -> 33239 | H24: 1.1448 | I24: 33756 | K24: 29465 | L24: 0.065
A25: 33266 | B25: =MONTH(A25) -> 1 | C25: =YEAR(A25) -> 1991 | D25: 1.168 | E25: =AVERAGEIFS($D$2:$D$1789,$B$2:$B$1789,B25,$C$2:$C$1789,C25) -> 1.18 | F25: =DATE(C25,B25,1) -> 33239 | H25: 1.1365 | I25: 33786 | K25: 29495 | L25: 0.063
A26: 33273 | B26: =MONTH(A26) -> 2 | C26: =YEAR(A26) -> 1991 | D26: 1.139 | E26: =AVERAGEIFS($D$2:$D$1789,$B$2:$B$1789,B26,$C$2:$C$1789,C26) -> 1.09425 | F26: =DATE(C26,B26,1) -> 33270 | H26: 1.1218 | I26: 33817 | K26: 29526 | L26: 0.061
A27: 33280 | B27: =MONTH(A27) -> 2 | C27: =YEAR(A27) -> 1991 | D27: 1.106 | E27: =AVERAGEIFS($D$2:$D$1789,$B$2:$B$1789,B27,$C$2:$C$1789,C27) -> 1.09425 | F27: =DATE(C27,B27,1) -> 33270 | H27: 1.1215 | I27: 33848 | K27: 29556 | L27: 0.062
A28: 33287 | B28: =MONTH(A28) -> 2 | C28: =YEAR(A28) -> 1991 | D28: 1.078 | E28: =AVERAGEIFS($D$2:$D$1789,$B$2:$B$1789,B28,$C$2:$C$1789,C28) -> 1.09425 | F28: =DATE(C28,B28,1) -> 33270 | H28: 1.114 | I28: 33878 | K28: 29587 | L28: 0.063
A29: 33294 | B29: =MONTH(A29) -> 2 | C29: =YEAR(A29) -> 1991 | D29: 1.054 | E29: =AVERAGEIFS($D$2:$D$1789,$B$2:$B$1789,B29,$C$2:$C$1789,C29) -> 1.09425 | F29: =DATE(C29,B29,1) -> 33270 | H29: 1.1112 | I29: 33909 | K29: 29618 | L29: 0.064
A30: 33301 | B30: =MONTH(A30) -> 3 | C30: =YEAR(A30) -> 1991 | D30: 1.025 | E30: =AVERAGEIFS($D$2:$D$1789,$B$2:$B$1789,B30,$C$2:$C$1789,C30) -> 1.04 | F30: =DATE(C30,B30,1) -> 33298 | H30: 1.0775 | I30: 33939 | K30: 29646 | L30: 0.065
A31: 33308 | B31: =MONTH(A31) -> 3 | C31: =YEAR(A31) -> 1991 | D31: 1.045 | E31: =AVERAGEIFS($D$2:$D$1789,$B$2:$B$1789,B31,$C$2:$C$1789,C31) -> 1.04 | F31: =DATE(C31,B31,1) -> 33298 | H31: 1.06175 | I31: 33970 | K31: 29677 | L31: 0.066
A32: 33315 | B32: =MONTH(A32) -> 3 | C32: =YEAR(A32) -> 1991 | D32: 1.043 | E32: =AVERAGEIFS($D$2:$D$1789,$B$2:$B$1789,B32,$C$2:$C$1789,C32) -> 1.04 | F32: =DATE(C32,B32,1) -> 33298 | H32: 1.05425 | I32: 34001 | K32: 29707 | L32: 0.067
A33: 33322 | B33: =MONTH(A33) -> 3 | C33: =YEAR(A33) -> 1991 | D33: 1.047 | E33: =AVERAGEIFS($D$2:$D$1789,$B$2:$B$1789,B33,$C$2:$C$1789,C33) -> 1.04 | F33: =DATE(C33,B33,1) -> 33298 | H33: 1.0522 | I33: 34029 | K33: 29738 | L33: 0.071
A34: 33329 | B34: =MONTH(A34) -> 4 | C34: =YEAR(A34) -> 1991 | D34: 1.052 | E34: =AVERAGEIFS($D$2:$D$1789,$B$2:$B$1789,B34,$C$2:$C$1789,C34) -> 1.0762 | F34: =DATE(C34,B34,1) -> 33329 | H34: 1.078 | I34: 34060 | K34: 29768 | L34: 0.073
A35: 33336 | B35: =MONTH(A35) -> 4 | C35: =YEAR(A35) -> 1991 | D35: 1.066 | E35: =AVERAGEIFS($D$2:$D$1789,$B$2:$B$1789,B35,$C$2:$C$1789,C35) -> 1.0762 | F35: =DATE(C35,B35,1) -> 33329 | H35: 1.1004 | I35: 34090 | K35: 29799 | L35: 0.075
... A83: 33672 | B83: =MONTH(A83) -> 3 | C83: =YEAR(A83) -> 1992 | D83: 1.013 | E83: =AVERAGEIFS($D$2:$D$1789,$B$2:$B$1789,B83,$C$2:$C$1789,C83) -> 1.0126 | F83: =DATE(C83,B83,1) -> 33664 | H83: 1.19075 | I83: 35551 | K83: 31260 | L83: 0.085
A84: 33679 | B84: =MONTH(A84) -> 3 | C84: =YEAR(A84) -> 1992 | D84: 1.01 | E84: =AVERAGEIFS($D$2:$D$1789,$B$2:$B$1789,B84,$C$2:$C$1789,C84) -> 1.0126 | F84: =DATE(C84,B84,1) -> 33664 | H84: 1.1886 | I84: 35582 | K84: 31291 | L84: .
A85: 33686 | B85: =MONTH(A85) -> 3 | C85: =YEAR(A85) -> 1992 | D85: 1.015 | E85: =AVERAGEIFS($D$2:$D$1789,$B$2:$B$1789,B85,$C$2:$C$1789,C85) -> 1.0126 | F85: =DATE(C85,B85,1) -> 33664 | H85: 1.167 | I85: 35612 | K85: 31321 | L85: 0.082
A86: 33693 | B86: =MONTH(A86) -> 3 | C86: =YEAR(A86) -> 1992 | D86: 1.013 | E86: =AVERAGEIFS($D$2:$D$1789,$B$2:$B$1789,B86,$C$2:$C$1789,C86) -> 1.0126 | F86: =DATE(C86,B86,1) -> 33664 | H86: 1.213 | I86: 35643 | K86: 31352 | L86: 0.08
A87: 33700 | B87: =MONTH(A87) -> 4 | C87: =YEAR(A87) -> 1992 | D87: 1.026 | E87: =AVERAGEIFS($D$2:$D$1789,$B$2:$B$1789,B87,$C$2:$C$1789,C87) -> 1.05175 | F87: =DATE(C87,B87,1) -> 33695 | H87: 1.2156 | I87: 35674 | K87: 31382 | L87: 0.08
A88: 33707 | B88: =MONTH(A88) -> 4 | C88: =YEAR(A88) -> 1992 | D88: 1.051 | E88: =AVERAGEIFS($D$2:$D$1789,$B$2:$B$1789,B88,$C$2:$C$1789,C88) -> 1.05175 | F88: =DATE(C88,B88,1) -> 33695 | H88: 1.182 | I88: 35704 | K88: 31413 | L88: 0.081
A89: 33714 | B89: =MONTH(A89) -> 4 | C89: =YEAR(A89) -> 1992 | D89: 1.058 | E89: =AVERAGEIFS($D$2:$D$1789,$B$2:$B$1789,B89,$C$2:$C$1789,C89) -> 1.05175 | F89: =DATE(C89,B89,1) -> 33695 | H89: 1.15825 | I89: 35735 | K89: 31444 | L89: 0.075
A90: 33721 | B90: =MONTH(A90) -> 4 | C90: =YEAR(A90) -> 1992 | D90: 1.072 | E90: =AVERAGEIFS($D$2:$D$1789,$B$2:$B$1789,B90,$C$2:$C$1789,C90) -> 1.05175 | F90: =DATE(C90,B90,1) -> 33695 | H90: 1.1186 | I90: 35765 | K90: 31472 | L90: 0.075
A91: 33728 | B91: =MONTH(A91) -> 5 | C91: =YEAR(A91) -> 1992 | D91: 1.089 | E91: =AVERAGEIFS($D$2:$D$1789,$B$2:$B$1789,B91,$C$2:$C$1789,C91) -> 1.10725 | F91: =DATE(C91,B91,1) -> 33725 | H91: 1.07475 | I91: 35796 | K91: 31503 | L91: 0.074
A92: 33735 | B92: =MONTH(A92) -> 5 | C92: =YEAR(A92) -> 1992 | D92: 1.102 | E92: =AVERAGEIFS($D$2:$D$1789,$B$2:$B$1789,B92,$C$2:$C$1789,C92) -> 1.10725 | F92: =DATE(C92,B92,1) -> 33725 | H92: 1.0415 | I92: 35827 | K92: 31533 | L92: 0.074
A93: 33742 | B93: =MONTH(A93) -> 5 | C93: =YEAR(A93) -> 1992 | D93: 1.118 | E93: =AVERAGEIFS($D$2:$D$1789,$B$2:$B$1789,B93,$C$2:$C$1789,C93) -> 1.10725 | F93: =DATE(C93,B93,1) -> 33725 | H93: 1.0144 | I93: 35855 | K93: 31564 | L93: 0.08
A94: 33749 | B94: =MONTH(A94) -> 5 | C94: =YEAR(A94) -> 1992 | D94: 1.12 | E94: =AVERAGEIFS($D$2:$D$1789,$B$2:$B$1789,B94,$C$2:$C$1789,C94) -> 1.10725 | F94: =DATE(C94,B94,1) -> 33725 | H94: 1.0235 | I94: 35886 | K94: 31594 | L94: 0.08
A95: 33756 | B95: =MONTH(A95) -> 6 | C95: =YEAR(A95) -> 1992 | D95: 1.128 | E95: =AVERAGEIFS($D$2:$D$1789,$B$2:$B$1789,B95,$C$2:$C$1789,C95) -> 1.1448 | F95: =DATE(C95,B95,1) -> 33756 | H95: 1.04925 | I95: 35916 | K95: 31625 | L95: 0.08
A96: 33763 | B96: =MONTH(A96) -> 6 | C96: =YEAR(A96) -> 1992 | D96: 1.143 | E96: =AVERAGEIFS($D$2:$D$1789,$B$2:$B$1789,B96,$C$2:$C$1789,C96) -> 1.1448 | F96: =DATE(C96,B96,1) -> 33756 | H96: 1.0478 | I96: 35947 | K96: 31656 | L96: 0.08
... A413: 35982 | B413: =MONTH(A413) -> 7 | C413: =YEAR(A413) -> 1998 | D413: 1.041 | E413: =AVERAGEIFS($D$2:$D$1789,$B$2:$B$1789,B413,$C$2:$C$1789,C413) -> 1.03925 | F413: =DATE(C413,B413,1) -> 35977 | H413: 2.9623333 | I413: 45597 | K413: 41306 | L413: 0.129
A414: 35989 | B414: =MONTH(A414) -> 7 | C414: =YEAR(A414) -> 1998 | D414: 1.037 | E414: =AVERAGEIFS($D$2:$D$1789,$B$2:$B$1789,B414,$C$2:$C$1789,C414) -> 1.03925 | F414: =DATE(C414,B414,1) -> 35977 | K414: 41334 | L414: 0.128
A415: 35996 | B415: =MONTH(A415) -> 7 | C415: =YEAR(A415) -> 1998 | D415: 1.044 | E415: =AVERAGEIFS($D$2:$D$1789,$B$2:$B$1789,B415,$C$2:$C$1789,C415) -> 1.03925 | F415: =DATE(C415,B415,1) -> 35977 | K415: 41365 | L415: 0.128
A416: 36003 | B416: =MONTH(A416) -> 7 | C416: =YEAR(A416) -> 1998 | D416: 1.035 | E416: =AVERAGEIFS($D$2:$D$1789,$B$2:$B$1789,B416,$C$2:$C$1789,C416) -> 1.03925 | F416: =DATE(C416,B416,1) -> 35977 | K416: 41395 | L416: 0.131
A417: 36010 | B417: =MONTH(A417) -> 8 | C417: =YEAR(A417) -> 1998 | D417: 1.023 | E417: =AVERAGEIFS($D$2:$D$1789,$B$2:$B$1789,B417,$C$2:$C$1789,C417) -> 1.0108 | F417: =DATE(C417,B417,1) -> 36008 | K417: 41426 | L417: 0.137
A418: 36017 | B418: =MONTH(A418) -> 8 | C418: =YEAR(A418) -> 1998 | D418: 1.018 | E418: =AVERAGEIFS($D$2:$D$1789,$B$2:$B$1789,B418,$C$2:$C$1789,C418) -> 1.0108 | F418: =DATE(C418,B418,1) -> 36008 | K418: 41456 | L418: 0.137
A419: 36024 | B419: =MONTH(A419) -> 8 | C419: =YEAR(A419) -> 1998 | D419: 1.011 | E419: =AVERAGEIFS($D$2:$D$1789,$B$2:$B$1789,B419,$C$2:$C$1789,C419) -> 1.0108 | F419: =DATE(C419,B419,1) -> 36008 | K419: 41487 | L419: 0.137
A420: 36031 | B420: =MONTH(A420) -> 8 | C420: =YEAR(A420) -> 1998 | D420: 1.004 | E420: =AVERAGEIFS($D$2:$D$1789,$B$2:$B$1789,B420,$C$2:$C$1789,C420) -> 1.0108 | F420: =DATE(C420,B420,1) -> 36008 | K420: 41518 | L420: 0.137
A421: 36038 | B421: =MONTH(A421) -> 8 | C421: =YEAR(A421) -> 1998 | D421: 0.998 | E421: =AVERAGEIFS($D$2:$D$1789,$B$2:$B$1789,B421,$C$2:$C$1789,C421) -> 1.0108 | F421: =DATE(C421,B421,1) -> 36008 | K421: 41548 | L421: 0.132
A422: 36045 | B422: =MONTH(A422) -> 9 | C422: =YEAR(A422) -> 1998 | D422: 0.991 | E422: =AVERAGEIFS($D$2:$D$1789,$B$2:$B$1789,B422,$C$2:$C$1789,C422) -> 0.994 | F422: =DATE(C422,B422,1) -> 36039 | K422: 41579 | L422: 0.13
A423: 36052 | B423: =MONTH(A423) -> 9 | C423: =YEAR(A423) -> 1998 | D423: 0.987 | E423: =AVERAGEIFS($D$2:$D$1789,$B$2:$B$1789,B423,$C$2:$C$1789,C423) -> 0.994 | F423: =DATE(C423,B423,1) -> 36039 | K423: 41609 | L423: 0.131
A424: 36059 | B424: =MONTH(A424) -> 9 | C424: =YEAR(A424) -> 1998 | D424: 0.999 | E424: =AVERAGEIFS($D$2:$D$1789,$B$2:$B$1789,B424,$C$2:$C$1789,C424) -> 0.994 | F424: =DATE(C424,B424,1) -> 36039 | K424: 41640 | L424: 0.134
A425: 36066 | B425: =MONTH(A425) -> 9 | C425: =YEAR(A425) -> 1998 | D425: 0.999 | E425: =AVERAGEIFS($D$2:$D$1789,$B$2:$B$1789,B425,$C$2:$C$1789,C425) -> 0.994 | F425: =DATE(C425,B425,1) -> 36039 | K425: 41671 | L425: 0.134
... A553: 36962 | B553: =MONTH(A553) -> 3 | C553: =YEAR(A553) -> 2001 | D553: 1.387 | E553: =AVERAGEIFS($D$2:$D$1789,$B$2:$B$1789,B553,$C$2:$C$1789,C553) -> 1.384 | F553: =DATE(C553,B553,1) -> 36951 | K553: 45566 | L553: 0.177
A554: 36969 | B554: =MONTH(A554) -> 3 | C554: =YEAR(A554) -> 2001 | D554: 1.377 | E554: =AVERAGEIFS($D$2:$D$1789,$B$2:$B$1789,B554,$C$2:$C$1789,C554) -> 1.384 | F554: =DATE(C554,B554,1) -> 36951
A555: 36976 | B555: =MONTH(A555) -> 3 | C555: =YEAR(A555) -> 2001 | D555: 1.379 | E555: =AVERAGEIFS($D$2:$D$1789,$B$2:$B$1789,B555,$C$2:$C$1789,C555) -> 1.384 | F555: =DATE(C555,B555,1) -> 36951
A556: 36983 | B556: =MONTH(A556) -> 4 | C556: =YEAR(A556) -> 2001 | D556: 1.411 | E556: =AVERAGEIFS($D$2:$D$1789,$B$2:$B$1789,B556,$C$2:$C$1789,C556) -> 1.5172 | F556: =DATE(C556,B556,1) -> 36982
A557: 36990 | B557: =MONTH(A557) -> 4 | C557: =YEAR(A557) -> 2001 | D557: 1.469 | E557: =AVERAGEIFS($D$2:$D$1789,$B$2:$B$1789,B557,$C$2:$C$1789,C557) -> 1.5172 | F557: =DATE(C557,B557,1) -> 36982
A558: 36997 | B558: =MONTH(A558) -> 4 | C558: =YEAR(A558) -> 2001 | D558: 1.535 | E558: =AVERAGEIFS($D$2:$D$1789,$B$2:$B$1789,B558,$C$2:$C$1789,C558) -> 1.5172 | F558: =DATE(C558,B558,1) -> 36982
A559: 37004 | B559: =MONTH(A559) -> 4 | C559: =YEAR(A559) -> 2001 | D559: 1.586 | E559: =AVERAGEIFS($D$2:$D$1789,$B$2:$B$1789,B559,$C$2:$C$1789,C559) -> 1.5172 | F559: =DATE(C559,B559,1) -> 36982
A560: 37011 | B560: =MONTH(A560) -> 4 | C560: =YEAR(A560) -> 2001 | D560: 1.585 | E560: =AVERAGEIFS($D$2:$D$1789,$B$2:$B$1789,B560,$C$2:$C$1789,C560) -> 1.5172 | F560: =DATE(C560,B560,1) -> 36982
A561: 37018 | B561: =MONTH(A561) -> 5 | C561: =YEAR(A561) -> 2001 | D561: 1.659 | E561: =AVERAGEIFS($D$2:$D$1789,$B$2:$B$1789,B561,$C$2:$C$1789,C561) -> 1.65375 | F561: =DATE(C561,B561,1) -> 37012
A562: 37025 | B562: =MONTH(A562) -> 5 | C562: =YEAR(A562) -> 2001 | D562: 1.663 | E562: =AVERAGEIFS($D$2:$D$1789,$B$2:$B$1789,B562,$C$2:$C$1789,C562) -> 1.65375 | F562: =DATE(C562,B562,1) -> 37012
A563: 37032 | B563: =MONTH(A563) -> 5 | C563: =YEAR(A563) -> 2001 | D563: 1.637 | E563: =AVERAGEIFS($D$2:$D$1789,$B$2:$B$1789,B563,$C$2:$C$1789,C563) -> 1.65375 | F563: =DATE(C563,B563,1) -> 37012
A564: 37039 | B564: =MONTH(A564) -> 5 | C564: =YEAR(A564) -> 2001 | D564: 1.656 | E564: =AVERAGEIFS($D$2:$D$1789,$B$2:$B$1789,B564,$C$2:$C$1789,C564) -> 1.65375 | F564: =DATE(C564,B564,1) -> 37012
A565: 37046 | B565: =MONTH(A565) -> 6 | C565: =YEAR(A565) -> 2001 | D565: 1.63 | E565: =AVERAGEIFS($D$2:$D$1789,$B$2:$B$1789,B565,$C$2:$C$1789,C565) -> 1.5475 | F565: =DATE(C565,B565,1) -> 37043
... A1789: 45614 | B1789: =MONTH(A1789) -> 11 | C1789: =YEAR(A1789) -> 2024 | D1789: 2.95 | E1789: =AVERAGEIFS($D$2:$D$1789,$B$2:$B$1789,B1789,$C$2:$C$1789,C1789) -> 2.9623333 | F1789: =DATE(C1789,B1789,1) -> 45597

Sheet Car costs
A1: Material | B1: Category | C1: Quantity | D1: Minimum | E1: Maximum | F1: Car Type
A2: Steel | B2: Metals and Metal Products | C2: 900-1,100 kg | D2: =IFERROR(IFERROR(LEFT(C2,FIND("-",C2)-1),LEFT(C2,FIND("+",C2)-1)),1)*1 -> 900 | E2: 1100 | F2: Non-Luxury ICE Car
A3: Aluminum | B3: Metals and Metal Products | C3: 80-120 kg | D3: =IFERROR(IFERROR(LEFT(C3,FIND("-",C3)-1),LEFT(C3,FIND("+",C3)-1)),1)*1 -> 80 | E3: 120 | F3: Non-Luxury ICE Car
A4: Copper | B4: Metals and Metal Products | C4: 20-30 kg | D4: =IFERROR(IFERROR(LEFT(C4,FIND("-",C4)-1),LEFT(C4,FIND("+",C4)-1)),1)*1 -> 20 | E4: 30 | F4: Non-Luxury ICE Car
A5: Plastics/Polymers | B5: Rubber and Plastic Products | C5: 150-200 kg | D5: =IFERROR(IFERROR(LEFT(C5,FIND("-",C5)-1),LEFT(C5,FIND("+",C5)-1)),1)*1 -> 150 | E5: 200 | F5: Non-Luxury ICE Car
A6: Rubber | B6: Rubber and Plastic Products | C6: 50-75 kg | D6: =IFERROR(IFERROR(LEFT(C6,FIND("-",C6)-1),LEFT(C6,FIND("+",C6)-1)),1)*1 -> 50 | E6: 75 | F6: Non-Luxury ICE Car
A7: Glass | B7: Nonmetallic Mineral Products | C7: 50-60 kg | D7: =IFERROR(IFERROR(LEFT(C7,FIND("-",C7)-1),LEFT(C7,FIND("+",C7)-1)),1)*1 -> 50 | E7: 60 | F7: Non-Luxury ICE Car
A8: Lead | B8: Metals and Metal Products | C8: 10-15 kg | D8: =IFERROR(IFERROR(LEFT(C8,FIND("-",C8)-1),LEFT(C8,FIND("+",C8)-1)),1)*1 -> 10 | E8: 15 | F8: Non-Luxury ICE Car
A9: Magnesium | B9: Metals and Metal Products | C9: 5-10 kg | D9: =IFERROR(IFERROR(LEFT(C9,FIND("-",C9)-1),LEFT(C9,FIND("+",C9)-1)),1)*1 -> 5 | E9: 10 | F9: Non-Luxury ICE Car
A10: Zinc | B10: Metals and Metal Products | C10: 2-5 kg | D10: =IFERROR(IFERROR(LEFT(C10,FIND("-",C10)-1),LEFT(C10,FIND("+",C10)-1)),1)*1 -> 2 | E10: 5 | F10: Non-Luxury ICE Car
A11: Steel | B11: Metals and Metal Products | C11: 1,200+ kg | D11: =IFERROR(IFERROR(LEFT(C11,FIND("-",C11)-1),LEFT(C11,FIND("+",C11)-1)),1)*1 -> 1200 | E11: =D11*1.44 -> 1728 | F11: Luxury ICE Car
A12: Aluminum | B12: Metals and Metal Products | C12: 200+ kg | D12: =IFERROR(IFERROR(LEFT(C12,FIND("-",C12)-1),LEFT(C12,FIND("+",C12)-1)),1)*1 -> 200 | E12: =D12*1.44 -> 288 | F12: Luxury ICE Car
A13: Copper | B13: Metals and Metal Products | C13: 50-70 kg | D13: =IFERROR(IFERROR(LEFT(C13,FIND("-",C13)-1),LEFT(C13,FIND("+",C13)-1)),1)*1 -> 50 | E13: 70 | F13: Luxury ICE Car
A14: Glass | B14: Nonmetallic Mineral Products | C14: 70-90 kg | D14: =IFERROR(IFERROR(LEFT(C14,FIND("-",C14)-1),LEFT(C14,FIND("+",C14)-1)),1)*1 -> 70 | E14: 90 | F14: Luxury ICE Car
A15: Leather | B15: Hides, Skins, Leather, and Related Products | C15: 30-50 m² | D15: =IFERROR(IFERROR(LEFT(C15,FIND("-",C15)-1),LEFT(C15,FIND("+",C15)-1)),1)*1 -> 30 | E15: 50 | F15: Luxury ICE Car
A16: Platinum/Palladium | B16: Metals and Metal Products | C16: Minimal | D16: =IFERROR(IFERROR(LEFT(C16,FIND("-",C16)-1),LEFT(C16,FIND("+",C16)-1)),1)*1 -> 1 | E16: =D16*1.44 -> 1.44 | F16: Luxury ICE Car
A17: Steel | B17: Metals and Metal Products | C17: 700-900 kg | D17: =IFERROR(IFERROR(LEFT(C17,FIND("-",C17)-1),LEFT(C17,FIND("+",C17)-1)),1)*1 -> 700 | E17: 900 | F17: Non-Luxury EV
A18: Aluminum | B18: Metals and Metal Products | C18: 150-200 kg | D18: =IFERROR(IFERROR(LEFT(C18,FIND("-",C18)-1),LEFT(C18,FIND("+",C18)-1)),1)*1 -> 150 | E18: 200 | F18: Non-Luxury EV
A19: Copper | B19: Metals and Metal Products | C19: 60-80 kg | D19: =IFERROR(IFERROR(LEFT(C19,FIND("-",C19)-1),LEFT(C19,FIND("+",C19)-1)),1)*1 -> 60 | E19: 80 | F19: Non-Luxury EV
A20: Plastics/Polymers | B20: Rubber and Plastic Products | C20: 200-250 kg | D20: =IFERROR(IFERROR(LEFT(C20,FIND("-",C20)-1),LEFT(C20,FIND("+",C20)-1)),1)*1 -> 200 | E20: 250 | F20: Non-Luxury EV
A21: Rubber | B21: Rubber and Plastic Products | C21: 50-75 kg | D21: =IFERROR(IFERROR(LEFT(C21,FIND("-",C21)-1),LEFT(C21,FIND("+",C21)-1)),1)*1 -> 50 | E21: 75 | F21: Non-Luxury EV
A22: Glass | B22: Nonmetallic Mineral Products | C22: 50-60 kg | D22: =IFERROR(IFERROR(LEFT(C22,FIND("-",C22)-1),LEFT(C22,FIND("+",C22)-1)),1)*1 -> 50 | E22: 60 | F22: Non-Luxury EV
A23: Lithium | B23: Chemicals and Allied Products | C23: 8-12 kg | D23: =IFERROR(IFERROR(LEFT(C23,FIND("-",C23)-1),LEFT(C23,FIND("+",C23)-1)),1)*1 -> 8 | E23: 12 | F23: Non-Luxury EV
A24: Nickel | B24: Metals and Metal Products | C24: 25-30 kg | D24: =IFERROR(IFERROR(LEFT(C24,FIND("-",C24)-1),LEFT(C24,FIND("+",C24)-1)),1)*1 -> 25 | E24: 30 | F24: Non-Luxury EV
A25: Cobalt | B25: Metals and Metal Products | C25: 5-10 kg | D25: =IFERROR(IFERROR(LEFT(C25,FIND("-",C25)-1),LEFT(C25,FIND("+",C25)-1)),1)*1 -> 5 | E25: 10 | F25: Non-Luxury EV
A26: Manganese | B26: Metals and Metal Products | C26: 5-7 kg | D26: =IFERROR(IFERROR(LEFT(C26,FIND("-",C26)-1),LEFT(C26,FIND("+",C26)-1)),1)*1 -> 5 | E26: 7 | F26: Non-Luxury EV
A27: Graphite | B27: Chemicals and Allied Products | C27: 30-50 kg | D27: =IFERROR(IFERROR(LEFT(C27,FIND("-",C27)-1),LEFT(C27,FIND("+",C27)-1)),1)*1 -> 30 | E27: 50 | F27: Non-Luxury EV
A28: Steel | B28: Metals and Metal Products | C28: 700-900 kg | D28: =IFERROR(IFERROR(LEFT(C28,FIND("-",C28)-1),LEFT(C28,FIND("+",C28)-1)),1)*1 -> 700 | E28: 900 | F28: Luxury EV
... A38: Graphite | B38: Chemicals and Allied Products | C38: 50-70 kg | D38: =IFERROR(IFERROR(LEFT(C38,FIND("-",C38)-1),LEFT(C38,FIND("+",C38)-1)),1)*1 -> 50 | E38: 70 | F38: Luxury EV
A39: Rare Earths | B39: Chemicals and Allied Products | C39: Minimal | D39: =IFERROR(IFERROR(LEFT(C39,FIND("-",C39)-1),LEFT(C39,FIND("+",C39)-1)),1)*1 -> 1 | E39: =D39*1.44 -> 1.44 | F39: Luxury EV

Sheet PPI
A1: DATE | B1: Metals and Metal Products | C1: Rubber and Plastic Products | D1: Textile Products and Apparel | E1: Hides, Skins, Leather, and Related Products | F1: Electrical Machinery and Equipment | G1: Chemicals and Allied Products | H1: Nonmetallic Mineral Products | I1: Producer Price Index by Commodity: Transportation Equipment: Passenger Cars and Chassis | J1: Fuels and Related Products and Power: Gasoline | K1: Fuels and Related Products and Power: No. 2 Diesel Fuel | L1: Fuels and Related Products and Power: Industrial Electric Power | M1: Electric Power Distribution: Transportation Electric Power
A2: 36526 | B2: 128.3 | C2: 123.8 | D2: 120.8 | E2: 149 | F2: 119 | G2: 147.7 | H2: 141.5 | I2: 121 | J2: 76.3 | K2: 76.1 | L2: 126.8 | M2: .
A3: 36557 | B3: 128.8 | C3: 123.7 | D3: 121 | E3: 148.9 | F3: 118.8 | G3: 148.9 | H3: 141.7 | I3: 120.6 | J3: 86.1 | K3: 86.1 | L3: 126.7 | M3: .
A4: 36586 | B4: 128.7 | C4: 123.9 | D4: 121.2 | E4: 148.4 | F4: 118.6 | G4: 149.9 | H4: 142.1 | I4: 118.4 | J4: 94.9 | K4: 90 | L4: 126.7 | M4: .
A5: 36617 | B5: 128.6 | C5: 124.3 | D5: 121.3 | E5: 149.2 | F5: 118.7 | G5: 150.7 | H5: 142.7 | I5: 129.5 | J5: 88.8 | K5: 84.1 | L5: 126.8 | M5: .
A6: 36647 | B6: 128.2 | C6: 124.4 | D6: 121.4 | E6: 149.7 | F6: 118.8 | G6: 151.3 | H6: 143 | I6: 128.6 | J6: 95.2 | K6: 82.8 | L6: 128.6 | M6: .
A7: 36678 | B7: 127.9 | C7: 125.2 | D7: 121.4 | E7: 149.6 | F7: 118.8 | G7: 151.7 | H7: 143.1 | I7: 127.7 | J7: 110.3 | K7: 85.7 | L7: 133.6 | M7: .
A8: 36708 | B8: 128 | C8: 125.8 | D8: 121.6 | E8: 151 | F8: 119 | G8: 152.6 | H8: 142.9 | I8: 127.5 | J8: 100 | K8: 89.5 | L8: 136.2 | M8: .
A9: 36739 | B9: 128 | C9: 125.7 | D9: 121.7 | E9: 152.3 | F9: 118.9 | G9: 152 | H9: 142.7 | I9: 127 | J9: 94.3 | K9: 92.1 | L9: 137.4 | M9: .
A10: 36770 | B10: 128.4 | C10: 126.4 | D10: 121.6 | E10: 153.3 | F10: 118.9 | G10: 151.9 | H10: 142.8 | I10: 127.6 | J10: 104.2 | K10: 110.8 | L10: 137.8 | M10: .
A11: 36800 | B11: 127.9 | C11: 126.4 | D11: 121.6 | E11: 155 | F11: 118.7 | G11: 151.9 | H11: 142.6 | I11: 127.1 | J11: 98.2 | K11: 110 | L11: 134.1 | M11: .
A12: 36831 | B12: 126.8 | C12: 127.9 | D12: 121.7 | E12: 155 | F12: 118.6 | G12: 151.3 | H12: 142.4 | I12: 126.7 | J12: 98.8 | K12: 110.4 | L12: 130.9 | M12: .
A13: 36861 | B13: 126.9 | C13: 128 | D13: 121.7 | E13: 156.2 | F13: 118.1 | G13: 151.7 | H13: 142.3 | I13: 125.8 | J13: 88.5 | K13: 101.6 | L13: 132.7 | M13: .
... A132: 40483 | B132: 212.2 | C132: 172.5 | D132: 133.3 | E132: 187.8 | F132: 112.6 | G132: 252.1 | H132: 201.6 | I132: 129.7 | J132: 232.8 | K132: 255.3 | L132: 190.9 | M132: .
A133: 40513 | B133: 214.8 | C133: 173.2 | D133: 134 | E133: 189.6 | F133: 112.7 | G133: 254.7 | H133: 201.8 | I133: 128.7 | J133: 241 | K133: 259.2 | L133: 191.4 | M133: 100
A134: 40544 | B134: 219.8 | C134: 175.2 | D134: 136.1 | E134: 192.8 | F134: 112.9 | G134: 262.2 | H134: 202.3 | I134: 125.7 | J134: 253 | K134: 270 | L134: 193.1 | M134: 101.3
A135: 40575 | B135: 224.2 | C135: 176.5 | D135: 137.7 | E135: 196.3 | F135: 113.2 | G135: 267.3 | H135: 202.6 | I135: 125 | J135: 259 | K135: 289.3 | L135: 194.4 | M135: 101.4
A136: 40603 | B136: 225.7 | C136: 178.2 | D136: 139.7 | E136: 198.3 | F136: 113.3 | G136: 270.3 | H136: 202.9 | I136: 125 | J136: 296.2 | K136: 321.8 | L136: 195 | M136: 99.8
A137: 40634 | B137: 229.2 | C137: 180.3 | D137: 141.1 | E137: 202.9 | F137: 113.3 | G137: 276.4 | H137: 203.5 | I137: 134 | J137: 321.9 | K137: 339.8 | L137: 194.1 | M137: 99.9
A138: 40664 | B138: 228.3 | C138: 182.5 | D138: 143 | E138: 203.6 | F138: 113.3 | G138: 280.6 | H138: 204.9 | I138: 130.5 | J138: 343.8 | K138: 328.4 | L138: 196.9 | M138: 100.3
A139: 40695 | B139: 228.4 | C139: 185.2 | D139: 143.3 | E139: 203 | F139: 113.3 | G139: 279.7 | H139: 205.7 | I139: 128.9 | J139: 313.3 | K139: 333.7 | L139: 205.7 | M139: 104.7
A140: 40725 | B140: 230 | C140: 186.2 | D140: 143.3 | E140: 203.4 | F140: 113.3 | G140: 280.5 | H140: 206.6 | I140: 129.7 | J140: 313.1 | K140: 327.8 | L140: 215.3 | M140: 104.4
A141: 40756 | B141: 229 | C141: 186.2 | D141: 143.6 | E141: 202.9 | F141: 113.3 | G141: 280.1 | H141: 206.6 | I141: 129.4 | J141: 297.6 | K141: 307.3 | L141: 216.6 | M141: 105.4
A142: 40787 | B142: 228.1 | C142: 186.3 | D142: 143.8 | E142: 203.5 | F142: 113.1 | G142: 280.9 | H142: 206.5 | I142: 132.6 | J142: 305.7 | K142: 317.8 | L142: 215.8 | M142: 106.2
A143: 40817 | B143: 223.8 | C143: 186.4 | D143: 143.3 | E143: 200.8 | F143: 113.2 | G143: 277.2 | H143: 206.1 | I143: 129.1 | J143: 290 | K143: 310.6 | L143: 206.6 | M143: 100.1
A144: 40848 | B144: 222.5 | C144: 185.2 | D144: 143 | E144: 196.6 | F144: 113.1 | G144: 274.9 | H144: 206 | I144: 128.9 | J144: 281.7 | K144: 337.1 | L144: 204 | M144: 100.3
... A299: 45566 | B299: 307.803 | C299: 254.527 | D299: 186.002 | E299: 176.281 | F299: 137.9 | G299: 350.671 | H299: 344.401 | I299: 132.8 | J299: 219.774 | K299: 321.05 | L299: 304.792 | M299: 127.14
I300: 133.7
I301: 133.1
I302: 132.1
I303: 131.3
I304: 131.6
I305: 134.5
I306: 134.2
I307: 135.3
I308: 135.4
I309: 135.2
I310: 135.4
I311: 135.6
... I401: 139.927
